Workbook
Name UPDATE: 'Data Sheet'!$E$1

Sheet Cover Page 
B1: Tata Steel
H3: Tata Steel Ltd is Asia's first integrated private steel company setup in 1907. The company has presence across the entire value chain of steel manufacturing from mining and processing iron ore and coal to producing and distributing finished products. The company has a target to increase domestic steelmaking capacity to 30 MnTPA by 2025.
B11: Key Company Details | J11: Scope of Work
B13: Chief Operating Officer/Managing Director | F13: Dr.T. V. Narendran | J13: This report presents an equity valuation of Tata Steel Limited to assess its intrinsic value relative to current market pricing. The analysis begins with DuPont Analysis (decomposing Return on Equity into profitability, efficiency, and leverage drivers) and Altman's Z-Score (assessing financial distress risk) to review financial health and earnings quality. A set of operating assumptions, revenue, cost structure, working capital, and capex/depreciation, was then developed to project financials through FY2031, feeding a Discounted Cash Flow valuation. The discount rate uses a bottom-up WACC build with peer beta relevering to a target capital structure, tested across Best/Base/Worst capex scenarios and a WACC-terminal growth sensitivity table. In parallel, Relative Valuation applies EV/EBITDA, EV/Revenue, and EV/EBIT multiples against domestic peers (JSW Steel, SAIL, Jindal Steel & Power, Jindal Stainless). Findings from both approaches are consolidated in a Football Field Analysis, comparing implied valuation ranges against the current market price to support a view on whether Tata Steel is fairly priced, undervalued, or overvalued.
B14: Headquarters | F14: Mumbai, Maharashtra
B15: FY26 Revenue | F15: ₹ 2,32,140 Crores
B16: FY26 EBITDA | F16: ₹ 51,186 Crores
B17: Major Shareholders | F17: Promotors (32.94%)
F18: FIIs (18.9%)
F19: DIIs (26.4%)
F20: Government and Public ( 21.7%)
B30: Key Growth Catalysts
B32: Capacity Expansion: Ongoing expansion projects in India are expected to increase production capacity and support long-term revenue growth.
B33: Infrastructure Demand: Rising government spending on infrastructure and construction is expected to drive domestic steel demand.
B34: Value-Added Products: Increasing focus on high-margin value-added steel products is likely to improve profitability and operating margins.
B35: Operational Efficiency: Continuous cost optimization, digitalization, and efficiency initiatives are expected to enhance margins and cash flow generation.

Sheet Key Financial Metric 
B1: Key Financial Metrics
B3: In (Cr)
B4: Particulars | D4: 45016 | E4: 45382 | F4: 45747 | G4: 46112 | I4: Trend Line | K4: Important Data
B5: Total Sales | D5: ='Forecasted Income Statement '!D5 -> 206922.86 | E5: ='Forecasted Income Statement '!E5 -> 229170.78 | F5: ='Forecasted Income Statement '!F5 -> 218543 | G5: ='Forecasted Income Statement '!G5 -> 232140
B6: Sales Growth (y-o-y) | D6: =D5/'Profit & Loss'!G4-1 -> -0.15181356 | E6: =E5/D5-1 -> 0.10751794 | F6: =F5/E5-1 -> -0.046374935 | G6: =G5/F5-1 -> 0.062216589
B7: EBITDA | D7: ='Forecasted Income Statement '!D10 -> 32383.428 | E7: ='Forecasted Income Statement '!E10 -> 49913.396 | F7: ='Forecasted Income Statement '!F10 -> 47292.705 | G7: ='Forecasted Income Statement '!G10 -> 51186.87
B8: EBITDA Margin (%) | D8: =D7/D5 -> 0.1565 | E8: =E7/E5 -> 0.2178 | F8: =F7/F5 -> 0.2164 | G8: =G7/G5 -> 0.2205
B9: EBIT | D9: ='Forecasted Income Statement '!D12 -> 23048.228 | E9: ='Forecasted Income Statement '!E12 -> 40031.236 | F9: ='Forecasted Income Statement '!F12 -> 36871.375 | G9: ='Forecasted Income Statement '!G12 -> 39232.36
B10: EBIT Margin (%) | D10: =D9/D5 -> 0.1113856 | E10: =E9/E5 -> 0.17467862 | F10: =F9/F5 -> 0.16871451 | G10: =G9/G5 -> 0.16900302
B11: PAT | D11: ='Forecasted Income Statement '!D16 -> 11724.669 | E11: ='Forecasted Income Statement '!E16 -> 22766.566 | F11: ='Forecasted Income Statement '!F16 -> 20671.298 | G11: ='Forecasted Income Statement '!G16 -> 22445.71
B12: Net Margins (%) | D12: =D11/D5 -> 0.05666203 | E12: =E11/E5 -> 0.099343233 | F12: =F11/F5 -> 0.094586867 | G12: =G11/G5 -> 0.096690402
B13: Earnings Per Share | D13: 7.17 | E13: -3.5546441 | F13: 2.7400248 | G13: 8.6465094
B14: EPS Growth (y-o-y) | D14: =D13/'Profit & Loss'!G13-1 -> -0.7819212 | E14: =E13/D13-1 -> -1.4957663 | F14: =F13/E13-1 -> -1.7708296 | G14: =G13/F13-1 -> 2.1556318
B16: Financial Ratios | D16: 45016 | E16: 45382 | F16: 45747 | G16: 46112 | I16: Trend Line
B17: Debt to Equity | D17: ='Ratio Analysis '!D52 -> 0.82354793 | E17: ='Ratio Analysis '!E52 -> 0.94617701 | F17: ='Ratio Analysis '!F52 -> 1.0398315 | G17: ='Ratio Analysis '!G52 -> 0.90421655
B18: Interest Coverage | D18: ='Ratio Analysis '!D53 -> 3.8950609 | E18: ='Ratio Analysis '!E53 -> 0.84721554 | F18: ='Ratio Analysis '!F53 -> 2.1460192 | G18: ='Ratio Analysis '!G53 -> 3.228067
B19: Return on Equity | D19: ='Ratio Analysis '!D22 -> 0.078339013 | E19: ='Ratio Analysis '!E22 -> -0.053344591 | F19: ='Ratio Analysis '!F22 -> 0.034811812 | G19: ='Ratio Analysis '!G22 -> 0.1065486
B20: Return on Capital Employed | D20: ='Ratio Analysis '!D23 -> 0.13051629 | E20: ='Ratio Analysis '!E23 -> 0.035510302 | F20: ='Ratio Analysis '!F23 -> 0.08471131 | G20: ='Ratio Analysis '!G23 -> 0.11891971
B21: Return on Assets | D21: ='Ratio Analysis '!D21 -> 0.028443472 | E21: ='Ratio Analysis '!E21 -> -0.017701595 | F21: ='Ratio Analysis '!F21 -> 0.011651795 | G21: ='Ratio Analysis '!G21 -> 0.038064091
B23: Peer Comparision (Mar 26) | D23: JSW Steel | E23: SAIL | F23: Jindal Steel | G23: Tata Steel | I23: Peer Comparision (Mar 26)
B24: Revenue | D24: 189687 | E24: 110810 | F24: 62412 | G24: =G5 -> 232140
B25: EBITDA Margins | D25: =30712/D24 -> 0.16190883 | E25: =13146/E24 -> 0.1186355 | F25: =9099/F24 -> 0.14578927 | G25: =G8 -> 0.2205
B26: PAT | D26: 12040 | E26: 3233 | F26: 3361 | G26: =G11 -> 22445.71
B27: Net Margins | D27: =D26/D24 -> 0.063472984 | E27: =E26/E24 -> 0.029176067 | F27: =F26/F24 -> 0.053851823 | G27: =G12 -> 0.096690402

Sheet Historical 
B1: Historical Financial Statement - "TATA STEEL"
B4: Income Statement
B5: Particulars | C5: ='[2]Data Sheet'!B56 -> 44286 | D5: ='[2]Data Sheet'!C56 -> 44651 | E5: ='[2]Data Sheet'!D56 -> 45016 | F5: ='[2]Data Sheet'!E56 -> 45382 | G5: ='[2]Data Sheet'!F56 -> 45747 | H5: ='[2]Data Sheet'!G56 -> 46112
B7: Sales | C7: ='[2]Data Sheet'!B17 -> 156477.4 | D7: ='[2]Data Sheet'!C17 -> 243959.17 | E7: ='[2]Data Sheet'!D17 -> 243352.69 | F7: ='[2]Data Sheet'!E17 -> 229170.78 | G7: ='[2]Data Sheet'!F17 -> 218542.51 | H7: ='[2]Data Sheet'!G17 -> 232139.94
B8: COGS | C8: =SUM('[2]Data Sheet'!B18,'[2]Data Sheet'!B20:B22)-1*'[2]Data Sheet'!B19 -> 102979.74 | D8: =SUM('[2]Data Sheet'!C18,'[2]Data Sheet'!C20:C22)-1*'[2]Data Sheet'!C19 -> 143605.19 | E8: =SUM('[2]Data Sheet'!D18,'[2]Data Sheet'!D20:D22)-1*'[2]Data Sheet'!D19 -> 178329.36 | F8: =SUM('[2]Data Sheet'!E18,'[2]Data Sheet'!E20:E22)-1*'[2]Data Sheet'!E19 -> 183154.84 | G8: =SUM('[2]Data Sheet'!F18,'[2]Data Sheet'!F20:F22)-1*'[2]Data Sheet'!F19 -> 171714.99 | H8: =SUM('[2]Data Sheet'!G18,'[2]Data Sheet'!G20:G22)-1*'[2]Data Sheet'!G19 -> 171435.78
B9: Gross Profit | C9: =C7-C8 -> 53497.66 | D9: =D7-D8 -> 100353.98 | E9: =E7-E8 -> 65023.33 | F9: =F7-F8 -> 46015.94 | G9: =G7-G8 -> 46827.52 | H9: =H7-H8 -> 60704.16
B10: Selling & General Expenses | C10: =SUM('[2]Data Sheet'!B23:B24) -> 22993.4 | D10: =SUM('[2]Data Sheet'!C23:C24) -> 36864.03 | E10: =SUM('[2]Data Sheet'!D23:D24) -> 32723.17 | F10: =SUM('[2]Data Sheet'!E23:E24) -> 23768.02 | G10: =SUM('[2]Data Sheet'!F23:F24) -> 21529.07 | H10: =SUM('[2]Data Sheet'!G23:G24) -> 26351.72
B11: EBITDA | C11: =C9-C10 -> 30504.26 | D11: =D9-D10 -> 63489.95 | E11: =E9-E10 -> 32300.16 | F11: =F9-F10 -> 22247.92 | G11: =G9-G10 -> 25298.45 | H11: =H9-H10 -> 34352.44
B12: Interest | C12: ='[2]Data Sheet'!B27 -> 7606.71 | D12: ='[2]Data Sheet'!C27 -> 5462.2 | E12: ='[2]Data Sheet'!D27 -> 6298.7 | F12: ='[2]Data Sheet'!E27 -> 7507.57 | G12: ='[2]Data Sheet'!F27 -> 7340.95 | H12: ='[2]Data Sheet'!G27 -> 7167.06
B13: Depreciation | C13: ='[2]Data Sheet'!B26 -> 9233.64 | D13: ='[2]Data Sheet'!C26 -> 9100.87 | E13: ='[2]Data Sheet'!D26 -> 9335.2 | F13: ='[2]Data Sheet'!E26 -> 9882.16 | G13: ='[2]Data Sheet'!F26 -> 10421.33 | H13: ='[2]Data Sheet'!G26 -> 11954.51
B14: Other Income | C14: ='[2]Data Sheet'!B25 -> 179.78 | D14: ='[2]Data Sheet'!C25 -> 1299.99 | E14: ='[2]Data Sheet'!D25 -> 1568.86 | F14: ='[2]Data Sheet'!E25 -> -6005.23 | G14: ='[2]Data Sheet'!F25 -> 876.7 | H14: ='[2]Data Sheet'!G25 -> 737.82
B15: Earnings Before Tax | C15: =IFERROR(C11-SUM(C13,C12,-C14),0) -> 13843.69 | D15: =IFERROR(D11-SUM(D13,D12,-D14),0) -> 50226.87 | E15: =IFERROR(E11-SUM(E13,E12,-E14),0) -> 18235.12 | F15: =IFERROR(F11-SUM(F13,F12,-F14),0) -> -1147.04 | G15: =IFERROR(G11-SUM(G13,G12,-G14),0) -> 8412.87 | H15: =IFERROR(H11-SUM(H13,H12,-H14),0) -> 15968.69
B16: Tax | C16: ='[2]Data Sheet'!B29 -> 5653.9 | D16: ='[2]Data Sheet'!C29 -> 8477.55 | E16: ='[2]Data Sheet'!D29 -> 10159.77 | F16: ='[2]Data Sheet'!E29 -> 3762.57 | G16: ='[2]Data Sheet'!F29 -> 5239.09 | H16: ='[2]Data Sheet'!G29 -> 5082.87
B17: Net Profit | C17: =IFERROR(C15-C16,0) -> 8189.79 | D17: =IFERROR(D15-D16,0) -> 41749.32 | E17: =IFERROR(E15-E16,0) -> 8075.35 | F17: =IFERROR(F15-F16,0) -> -4909.61 | G17: =IFERROR(G15-G16,0) -> 3173.78 | H17: =IFERROR(H15-H16,0) -> 10885.82
B18: No of Equity Shares | C18: ='[2]Data Sheet'!B127 -> 1196.59 | D18: ='[2]Data Sheet'!C127 -> 1221.3 | E18: ='[2]Data Sheet'!D127 -> 1222.15 | F18: ='[2]Data Sheet'!E127 -> 1248.35 | G18: ='[2]Data Sheet'!F127 -> 1248.35 | H18: ='[2]Data Sheet'!G127 -> 1248.35
B19: Earnings per Share | C19: =IFERROR(C17/C18,0) -> 6.8442741 | D19: =IFERROR(D17/D18,0) -> 34.184328 | E19: =IFERROR(E17/E18,0) -> 6.607495 | F19: =IFERROR(F17/F18,0) -> -3.9328794 | G19: =IFERROR(G17/G18,0) -> 2.5423799 | H19: =IFERROR(H17/H18,0) -> 8.7201666
B20: Dividend per Share | C20: ='[2]Data Sheet'!B31/[2]HistoricalFS!C39 -> 2.5021269 | D20: ='[2]Data Sheet'!C31/[2]HistoricalFS!D39 -> 5.0996234 | E20: ='[2]Data Sheet'!D31/[2]HistoricalFS!E39 -> 3.5973162 | F20: ='[2]Data Sheet'!E31/[2]HistoricalFS!F39 -> 3.5973725 | G20: ='[2]Data Sheet'!F31/[2]HistoricalFS!G39 -> 3.5973725 | H20: ='[2]Data Sheet'!G31/[2]HistoricalFS!H39 -> 3.9970842
B21: Dividend payout ratio | C21: =IFERROR(C20/C19,0) -> 0.36557958 | D21: =IFERROR(D20/D19,0) -> 0.14918015 | E21: =IFERROR(E20/E19,0) -> 0.54442965 | F21: =IFERROR(F20/F19,0) -> -0.9146918 | G21: =IFERROR(G20/G19,0) -> 1.4149626 | H21: =IFERROR(H20/H19,0) -> 0.45837245
B22: Retained Earnings | C22: =IFERROR(IF(C19>C20,1-C21,0),0) -> 0.63442042 | D22: =IFERROR(IF(D19>D20,1-D21,0),0) -> 0.85081985 | E22: =IFERROR(IF(E19>E20,1-E21,0),0) -> 0.45557035 | F22: =IFERROR(IF(F19>F20,1-F21,0),0) -> 0 | G22: =IFERROR(IF(G19>G20,1-G21,0),0) -> 0 | H22: =IFERROR(IF(H19>H20,1-H21,0),0) -> 0.54162755
B24: Balance Sheet
A25: # | B25: Particulars | C25: 44256 | D25: 44651 | E25: 45016 | F25: 45382 | G25: 45747 | H25: 46112
B27: Equity Share Capital | C27: ='[2]Data Sheet'!B57 -> 1197.61 | D27: ='[2]Data Sheet'!C57 -> 1221.21 | E27: ='[2]Data Sheet'!D57 -> 1221.24 | F27: ='[2]Data Sheet'!E57 -> 1247.44 | G27: ='[2]Data Sheet'!F57 -> 1247.44 | H27: ='[2]Data Sheet'!G57 -> 1247.44
B28: Reserves | C28: ='[2]Data Sheet'!B58 -> 73041.16 | D28: ='[2]Data Sheet'!C58 -> 113221.83 | E28: ='[2]Data Sheet'!D58 -> 101860.86 | F28: ='[2]Data Sheet'!E58 -> 90788.32 | G28: ='[2]Data Sheet'!F58 -> 89922.19 | H28: ='[2]Data Sheet'!G58 -> 100920.21
B29: Borrowings | C29: ='[2]Data Sheet'!B59 -> 88501.41 | D29: ='[2]Data Sheet'!C59 -> 75561.35 | E29: ='[2]Data Sheet'!D59 -> 84893.05 | F29: ='[2]Data Sheet'!E59 -> 87082.12 | G29: ='[2]Data Sheet'!F59 -> 94801.05 | H29: ='[2]Data Sheet'!G59 -> 92381.68
B30: Other Liabilities | C30: ='[2]Data Sheet'!B60-SUM('[2]Data Sheet'!B62:B63) -> 52803.01 | D30: ='[2]Data Sheet'!C60-SUM('[2]Data Sheet'!C62:C63) -> 52399.28 | E30: ='[2]Data Sheet'!D60-SUM('[2]Data Sheet'!D62:D63) -> 56193.63 | F30: ='[2]Data Sheet'!E60-SUM('[2]Data Sheet'!E62:E63) -> 57195.54 | G30: ='[2]Data Sheet'!F60-SUM('[2]Data Sheet'!F62:F63) -> 58518.9 | H30: ='[2]Data Sheet'!G60-SUM('[2]Data Sheet'!G62:G63) -> 64933.29
B31: Trade Payables | C31: ='[2]Data Sheet'!B62 -> 25967 | D31: ='[2]Data Sheet'!C62 -> 36765 | E31: ='[2]Data Sheet'!D62 -> 37833 | F31: ='[2]Data Sheet'!E62 -> 30228 | G31: ='[2]Data Sheet'!F62 -> 29314 | H31: ='[2]Data Sheet'!G62 -> 34810
B32: Advance from Customers | C32: ='[2]Data Sheet'!B63 -> 2399 | D32: ='[2]Data Sheet'!C63 -> 3253 | E32: ='[2]Data Sheet'!D63 -> 3394 | F32: ='[2]Data Sheet'!E63 -> 2771 | G32: ='[2]Data Sheet'!F63 -> 1655 | H32: ='[2]Data Sheet'!G63 -> 2222
B33: Total Liabilities | C33: =SUM(C27:C32) -> 243909.19 | D33: =SUM(D27:D32) -> 282421.67 | E33: =SUM(E27:E32) -> 285395.78 | F33: =SUM(F27:F32) -> 269312.42 | G33: =SUM(G27:G32) -> 275458.58 | H33: =SUM(H27:H32) -> 296514.62
B35: Fixed Assets Net Block | C35: ='[2]Data Sheet'!B66 -> 135775.18 | D35: ='[2]Data Sheet'!C66 -> 133287.83 | E35: ='[2]Data Sheet'!D66 -> 146621.46 | F35: ='[2]Data Sheet'!E66 -> 148814.38 | G35: ='[2]Data Sheet'!F66 -> 150914.06 | H35: ='[2]Data Sheet'!G66 -> 179908.13
B36: Capital Work in Progress | C36: ='[2]Data Sheet'!B67 -> 19007.4 | D36: ='[2]Data Sheet'!C67 -> 22045.55 | E36: ='[2]Data Sheet'!D67 -> 31213.02 | F36: ='[2]Data Sheet'!E67 -> 34355.53 | G36: ='[2]Data Sheet'!F67 -> 41622.35 | H36: ='[2]Data Sheet'!G67 -> 28496.71
B37: Investments | C37: ='[2]Data Sheet'!B68 -> 10681.93 | D37: ='[2]Data Sheet'!C68 -> 13139.85 | E37: ='[2]Data Sheet'!D68 -> 8410.31 | F37: ='[2]Data Sheet'!E68 -> 6257.57 | G37: ='[2]Data Sheet'!F68 -> 6194.11 | H37: ='[2]Data Sheet'!G68 -> 7088.85
B38: Other Assets | C38: ='[2]Data Sheet'!B69-SUM('[2]Data Sheet'!B70:B72) -> 29846.28 | D38: ='[2]Data Sheet'!C69-SUM('[2]Data Sheet'!C70:C72) -> 36978.69 | E38: ='[2]Data Sheet'!D69-SUM('[2]Data Sheet'!D70:D72) -> 23121.16 | F38: ='[2]Data Sheet'!E69-SUM('[2]Data Sheet'!E70:E72) -> 15786.18 | G38: ='[2]Data Sheet'!F69-SUM('[2]Data Sheet'!F70:F72) -> 15231.08 | H38: ='[2]Data Sheet'!G69-SUM('[2]Data Sheet'!G70:G72) -> 18797.29
B39: Total Non Current Assets | C39: =SUM(C35:C38) -> 195310.79 | D39: =SUM(D35:D38) -> 205451.92 | E39: =SUM(E35:E38) -> 209365.95 | F39: =SUM(F35:F38) -> 205213.66 | G39: =SUM(G35:G38) -> 213961.6 | H39: =SUM(H35:H38) -> 234290.98
B41: Receivables | C41: ='[2]Data Sheet'!B70 -> 9539.84 | D41: ='[2]Data Sheet'!C70 -> 12246.43 | E41: ='[2]Data Sheet'!D70 -> 8257.24 | F41: ='[2]Data Sheet'!E70 -> 6263.53 | G41: ='[2]Data Sheet'!F70 -> 5260.06 | H41: ='[2]Data Sheet'!G70 -> 4916.89
B42: Inventory | C42: ='[2]Data Sheet'!B71 -> 33276.38 | D42: ='[2]Data Sheet'!C71 -> 48824.39 | E42: ='[2]Data Sheet'!D71 -> 54415.33 | F42: ='[2]Data Sheet'!E71 -> 49157.51 | G42: ='[2]Data Sheet'!F71 -> 44589.94 | H42: ='[2]Data Sheet'!G71 -> 47249.22
B43: Cash & Bank | C43: ='[2]Data Sheet'!B72 -> 5782.18 | D43: ='[2]Data Sheet'!C72 -> 15898.93 | E43: ='[2]Data Sheet'!D72 -> 13357.26 | F43: ='[2]Data Sheet'!E72 -> 8677.72 | G43: ='[2]Data Sheet'!F72 -> 11646.98 | H43: ='[2]Data Sheet'!G72 -> 10057.53
B44: Total Current Assets | C44: =IFERROR(SUM(C41:C43),0) -> 48598.4 | D44: =IFERROR(SUM(D41:D43),0) -> 76969.75 | E44: =IFERROR(SUM(E41:E43),0) -> 76029.83 | F44: =IFERROR(SUM(F41:F43),0) -> 64098.76 | G44: =IFERROR(SUM(G41:G43),0) -> 61496.98 | H44: =IFERROR(SUM(H41:H43),0) -> 62223.64
B46: Total Assets | C46: =IFERROR(C44+C39,0) -> 243909.19 | D46: =IFERROR(D44+D39,0) -> 282421.67 | E46: =IFERROR(E44+E39,0) -> 285395.78 | F46: =IFERROR(F44+F39,0) -> 269312.42 | G46: =IFERROR(G44+G39,0) -> 275458.58 | H46: =IFERROR(H44+H39,0) -> 296514.62
A48: # | B48: Check | C48: =ROUND(C33,0)=ROUND(C46,0) -> TRUE | D48: =ROUND(D33,0)=ROUND(D46,0) -> TRUE | E48: =ROUND(E33,0)=ROUND(E46,0) -> TRUE | F48: =ROUND(F33,0)=ROUND(F46,0) -> TRUE | G48: =ROUND(G33,0)=ROUND(G46,0) -> TRUE | H48: =ROUND(H33,0)=ROUND(H46,0) -> TRUE
A50: # | B50: Cash Flow
B51: Particulars | C51: 44256 | D51: 44621 | E51: 44986 | F51: 45352 | G51: 45717 | H51: 46082
B53: Cash From Operating Activites
B54: ='Cash Flow '!A3 -> Profit from operations | C54: 28450 | D54: ='Cash Flow '!B3 -> 65900 | E54: ='Cash Flow '!C3 -> 30908 | F54: ='Cash Flow '!D3 -> 22237 | G54: ='Cash Flow '!E3 -> 23929 | H54: ='Cash Flow '!F3 -> 34219
B55: ='Cash Flow '!A4 -> Receivables | D55: ='Cash Flow '!B4 -> 0 | E55: ='Cash Flow '!C4 -> 0 | F55: ='Cash Flow '!D4 -> 0 | G55: ='Cash Flow '!E4 -> 0 | H55: ='Cash Flow '!F4 -> 0
B56: ='Cash Flow '!A5 -> Inventory | C56: 46 | D56: ='Cash Flow '!B5 -> -16917 | E56: ='Cash Flow '!C5 -> -4031 | F56: ='Cash Flow '!D5 -> 5566 | G56: ='Cash Flow '!E5 -> 4776 | H56: ='Cash Flow '!F5 -> 1290
B57: ='Cash Flow '!A6 -> Payables | D57: ='Cash Flow '!B6 -> 0 | E57: ='Cash Flow '!C6 -> 0 | F57: ='Cash Flow '!D6 -> 0 | G57: ='Cash Flow '!E6 -> 0 | H57: ='Cash Flow '!F6 -> 0
B58: Loan and Advances | D58: 0 | E58: 0 | F58: 0 | G58: 0 | H58: 0
B59: ='Cash Flow '!A7 -> Other WC items | C59: 16446 | D59: ='Cash Flow '!B7 -> 7299 | E59: ='Cash Flow '!C7 -> 325 | F59: ='Cash Flow '!D7 -> -2182 | G59: ='Cash Flow '!E7 -> -2569 | H59: ='Cash Flow '!F7 -> 4152
B60: ='Cash Flow '!A8 -> Working capital changes | C60: =SUM(C55:C59) -> 16492 | D60: =SUM(D55:D59) -> -9618 | E60: =SUM(E55:E59) -> -3706 | F60: =SUM(F55:F59) -> 3384 | G60: =SUM(G55:G59) -> 2207 | H60: =SUM(H55:H59) -> 5442
B61: Direct taxes | C61: 704 | D61: -11902 | E61: -5519 | F61: -5320 | G61: -2998 | H61: -4597
B62: Cash Flow from Operating Activities | C62: =SUM(C54,C60:C61) -> 45646 | D62: =SUM(D54,D60:D61) -> 44380 | E62: =SUM(E54,E60:E61) -> 21683 | F62: =SUM(F54,F60:F61) -> 20301 | G62: =SUM(G54,G60:G61) -> 23138 | H62: =SUM(H54,H60:H61) -> 35064
B64: Cash From Investing Activity
B65: ='Cash Flow '!A11 -> Fixed assets purchased | C65: -6979 | D65: ='Cash Flow '!B11 -> -10522 | E65: ='Cash Flow '!C11 -> -14142 | F65: ='Cash Flow '!D11 -> -18207 | G65: ='Cash Flow '!E11 -> -15671 | H65: ='Cash Flow '!F11 -> -14559
B66: ='Cash Flow '!A12 -> Fixed assets sold | C66: 445 | D66: ='Cash Flow '!B12 -> 569 | E66: ='Cash Flow '!C12 -> 328 | F66: ='Cash Flow '!D12 -> 475 | G66: ='Cash Flow '!E12 -> 1264 | H66: ='Cash Flow '!F12 -> 1401
B67: ='Cash Flow '!A13 -> Investments purchased | C67: -3631 | D67: ='Cash Flow '!B13 -> -1153 | E67: ='Cash Flow '!C13 -> -326 | F67: ='Cash Flow '!D13 -> -4 | G67: ='Cash Flow '!E13 -> -393 | H67: ='Cash Flow '!F13 -> -553
B68: ='Cash Flow '!A14 -> Investments sold | C68: 0 | D68: ='Cash Flow '!B14 -> 63 | E68: ='Cash Flow '!C14 -> 5191 | F68: ='Cash Flow '!D14 -> 3171 | G68: ='Cash Flow '!E14 -> 554 | H68: ='Cash Flow '!F14 -> 20
B69: ='Cash Flow '!A15 -> Interest received | C69: 266 | D69: ='Cash Flow '!B15 -> 137 | E69: ='Cash Flow '!C15 -> 248 | F69: ='Cash Flow '!D15 -> 333 | G69: ='Cash Flow '!E15 -> 616 | H69: ='Cash Flow '!F15 -> 650
B70: ='Cash Flow '!A16 -> Dividends received | C70: 135 | D70: ='Cash Flow '!B16 -> 162 | E70: ='Cash Flow '!C16 -> 317 | F70: ='Cash Flow '!D16 -> 336 | G70: ='Cash Flow '!E16 -> 294 | H70: ='Cash Flow '!F16 -> 408
B71: ='Cash Flow '!A17 -> Redemp n Canc of Shares | C71: 90 | D71: ='Cash Flow '!B17 -> 1208 | E71: ='Cash Flow '!C17 -> 166 | F71: ='Cash Flow '!D17 -> 123 | G71: ='Cash Flow '!E17 -> 28 | H71: ='Cash Flow '!F17 -> 611
B72: ='Cash Flow '!A18 -> Acquisition of companies | C72: 0 | D72: ='Cash Flow '!B18 -> -53 | E72: ='Cash Flow '!C18 -> -10569 | F72: ='Cash Flow '!D18 -> 0 | G72: ='Cash Flow '!E18 -> -6 | H72: ='Cash Flow '!F18 -> -2846
B73: ='Cash Flow '!A19 -> Inter corporate deposits | C73: 0 | D73: ='Cash Flow '!B19 -> 0 | E73: ='Cash Flow '!C19 -> 0 | F73: ='Cash Flow '!D19 -> 0 | G73: ='Cash Flow '!E19 -> 0 | H73: ='Cash Flow '!F19 -> 0
B74: ='Cash Flow '!A20 -> Other investing items | C74: 236 | D74: ='Cash Flow '!B20 -> -1315 | E74: ='Cash Flow '!C20 -> 609 | F74: ='Cash Flow '!D20 -> -481 | G74: ='Cash Flow '!E20 -> -298 | H74: ='Cash Flow '!F20 -> 472
B75: Cash Flow From Investing Activity | C75: =SUM(C65:C74) -> -9438 | D75: =SUM(D65:D74) -> -10904 | E75: =SUM(E65:E74) -> -18178 | F75: =SUM(F65:F74) -> -14254 | G75: =SUM(G65:G74) -> -13612 | H75: =SUM(H65:H74) -> -14396
B77: Cash From Financing Activity
B78: ='Cash Flow '!A22 -> Proceeds from shares | C78: 3299 | D78: ='Cash Flow '!B22 -> 326 | E78: ='Cash Flow '!C22 -> 1 | F78: ='Cash Flow '!D22 -> 0 | G78: ='Cash Flow '!E22 -> 0 | H78: ='Cash Flow '!F22 -> 0
B79: ='Cash Flow '!A23 -> Proceeds from borrowings | C79: 9801 | D79: ='Cash Flow '!B23 -> 12439 | E79: ='Cash Flow '!C23 -> 16769 | F79: ='Cash Flow '!D23 -> 14120 | G79: ='Cash Flow '!E23 -> 23893 | H79: ='Cash Flow '!F23 -> 15954
B80: ='Cash Flow '!A24 -> Repayment of borrowings | C80: -39177 | D80: ='Cash Flow '!B24 -> -26360 | E80: ='Cash Flow '!C24 -> -10226 | F80: ='Cash Flow '!D24 -> -11908 | G80: ='Cash Flow '!E24 -> -17627 | H80: ='Cash Flow '!F24 -> -23916
B81: ='Cash Flow '!A25 -> Interest paid fin | C81: -6804 | D81: ='Cash Flow '!B25 -> -4687 | E81: ='Cash Flow '!C25 -> -6120 | F81: ='Cash Flow '!D25 -> -8145 | G81: ='Cash Flow '!E25 -> -8119 | H81: ='Cash Flow '!F25 -> -8066
B82: ='Cash Flow '!A26 -> Dividends paid | C82: -1151 | D82: ='Cash Flow '!B26 -> -3020 | E82: ='Cash Flow '!C26 -> -6293 | F82: ='Cash Flow '!D26 -> -4429 | G82: ='Cash Flow '!E26 -> -4490 | H82: ='Cash Flow '!F26 -> -4490
B83: ='Cash Flow '!A27 -> Financial liabilities | C83: -1284 | D83: ='Cash Flow '!B27 -> -1310 | E83: ='Cash Flow '!C27 -> -1114 | F83: ='Cash Flow '!D27 -> -1140 | G83: ='Cash Flow '!E27 -> -971 | H83: ='Cash Flow '!F27 -> -1162
B84: ='Cash Flow '!A28 -> Other financing items | C84: -1714 | D84: ='Cash Flow '!B28 -> -789 | E84: ='Cash Flow '!C28 -> 2 | F84: ='Cash Flow '!D28 -> 404 | G84: ='Cash Flow '!E28 -> 312 | H84: ='Cash Flow '!F28 -> 293
B85: Cash Flow From Financing Activity | C85: =SUM(C78:C84) -> -37030 | D85: =SUM(D78:D84) -> -23401 | E85: =SUM(E78:E84) -> -6981 | F85: =SUM(F78:F84) -> -11098 | G85: =SUM(G78:G84) -> -7002 | H85: =SUM(H78:H84) -> -21387
B87: ='Cash Flow '!A29 -> Net Cash Flow | C87: =C62+C75+C85 -> -822 | D87: =D62+D75+D85 -> 10075 | E87: =E62+E75+E85 -> -3476 | F87: =F62+F75+F85 -> -5051 | G87: =G62+G75+G85 -> 2524 | H87: =H62+H75+H85 -> -719

Sheet Ratio Analysis 
B1: Ratio Analysis
B4: Liquidity Ratio
C6: FY22 | D6: FY23 | E6: FY24 | F6: FY25 | G6: FY26
B7: Current Ratio | C7: ='Historical '!D44/('Historical '!D30+'Historical '!D31+'Historical '!D32) -> 0.8328502 | D7: ='Historical '!E44/('Historical '!E30+'Historical '!E31+'Historical '!E32) -> 0.78042844 | E7: ='Historical '!F44/('Historical '!F30+'Historical '!F31+'Historical '!F32) -> 0.71067229 | F7: ='Historical '!G44/('Historical '!G30+'Historical '!G31+'Historical '!G32) -> 0.68721 | G7: ='Historical '!H44/('Historical '!H30+'Historical '!H31+'Historical '!H32) -> 0.61024335
B8: Quick Ratio | C8: =('Historical '!D41+'Historical '!D43)/('Historical '!D30+'Historical '!D31+'Historical '!D32) -> 0.30454651 | D8: =('Historical '!E41+'Historical '!E43)/('Historical '!E30+'Historical '!E31+'Historical '!E32) -> 0.22186779 | E8: =('Historical '!F41+'Historical '!F43)/('Historical '!F30+'Historical '!F31+'Historical '!F32) -> 0.16565581 | F8: =('Historical '!G41+'Historical '!G43)/('Historical '!G30+'Historical '!G31+'Historical '!G32) -> 0.18893102 | G8: =('Historical '!H41+'Historical '!H43)/('Historical '!H30+'Historical '!H31+'Historical '!H32) -> 0.14685801
B11: Interpretation
B12: Current Ratio: The current ratio declined from 0.83x to 0.61x, indicating weakening short-term liquidity.
B13: Quick Ratio: The quick ratioFell from 0.30x to 0.15x, showing limited ability to meet short-term obligations without relying on inventory.
B15: Profitability Ratio
C17: FY22 | D17: FY23 | E17: FY24 | F17: FY25 | G17: FY26
B18: Gross Profit Margin | C18: ='Historical '!D9/'Historical '!D7 -> 0.41135564 | D18: ='Historical '!E9/'Historical '!E7 -> 0.26719791 | E18: ='Historical '!F9/'Historical '!F7 -> 0.20079323 | F18: ='Historical '!G9/'Historical '!G7 -> 0.21427191 | G18: ='Historical '!H9/'Historical '!H7 -> 0.26149813
B19: Operating Profit Margin | C19: ='Historical '!D11/'Historical '!D7 -> 0.26024826 | D19: ='Historical '!E11/'Historical '!E7 -> 0.13272983 | E19: ='Historical '!F11/'Historical '!F7 -> 0.09708009 | F19: ='Historical '!G11/'Historical '!G7 -> 0.11575986 | G19: ='Historical '!H11/'Historical '!H7 -> 0.1479816
B20: Net Profit Margin | C20: ='Historical '!D17/'Historical '!D7 -> 0.17113241 | D20: ='Historical '!E17/'Historical '!E7 -> 0.03318373 | E20: ='Historical '!F17/'Historical '!F7 -> -0.021423368 | F20: ='Historical '!G17/'Historical '!G7 -> 0.014522484 | G20: ='Historical '!H17/'Historical '!H7 -> 0.046893352
B21: Return on Assets | C21: ='Historical '!D17/(('Historical '!C46+'Historical '!D46)/2) -> 0.15864287 | D21: ='Historical '!E17/(('Historical '!D46+'Historical '!E46)/2) -> 0.028443472 | E21: ='Historical '!F17/(('Historical '!E46+'Historical '!F46)/2) -> -0.017701595 | F21: ='Historical '!G17/(('Historical '!F46+'Historical '!G46)/2) -> 0.011651795 | G21: ='Historical '!H17/(('Historical '!G46+'Historical '!H46)/2) -> 0.038064091
B22: Return on Equity | C22: ='Historical '!D17/('Historical '!D27+'Historical '!D28) -> 0.36480436 | D22: ='Historical '!E17/('Historical '!E27+'Historical '!E28) -> 0.078339013 | E22: ='Historical '!F17/('Historical '!F27+'Historical '!F28) -> -0.053344591 | F22: ='Historical '!G17/('Historical '!G27+'Historical '!G28) -> 0.034811812 | G22: ='Historical '!H17/('Historical '!H27+'Historical '!H28) -> 0.1065486
B23: Return on Capital Employed | C23: =('Historical '!D15+'Historical '!D12)/('Historical '!D46-'Historical '!D30-'Historical '!D31-'Historical '!D32) -> 0.2930936 | D23: =('Historical '!E15+'Historical '!E12)/('Historical '!E46-'Historical '!E30-'Historical '!E31-'Historical '!E32) -> 0.13051629 | E23: =('Historical '!F15+'Historical '!F12)/('Historical '!F46-'Historical '!F30-'Historical '!F31-'Historical '!F32) -> 0.035510302 | F23: =('Historical '!G15+'Historical '!G12)/('Historical '!G46-'Historical '!G30-'Historical '!G31-'Historical '!G32) -> 0.08471131 | G23: =('Historical '!H15+'Historical '!H12)/('Historical '!H46-'Historical '!H30-'Historical '!H31-'Historical '!H32) -> 0.11891971
B26: Interpretation
B27: Gross Profit Margin: Gross margin improved to 15% in FY26, indicating better control over production costs and stronger pricing.
B28: Operating Profit Margin: Operating margin recovered steadily after FY24, reflecting improved operating efficiency and cost management.
B29: Net Profit Margin: Net margin turned positive after FY24 and increased to 5% in FY26, indicating improved overall profitability.
B30: Return on Assets (ROA): ROA improved consistently after FY24, reflecting better utilization of the company's asset base.
B31: Return on Equity (ROE): ROE recovered from a negative return in FY24 to 11% in FY26, indicating improved returns for shareholders.
B32: Return on Capital Employed (ROCE): ROCE improved over the period, demonstrating more efficient utilization of long-term capital.
B34: Efficiency Ratio
C36: FY22 | D36: FY23 | E36: FY24 | F36: FY25 | G36: FY26
B37: Inventory Turnover | C37: =[3]HistoricalFS!D9/AVERAGE([3]HistoricalFS!C65:D65) -> 3.4982666 | D37: =[3]HistoricalFS!E9/AVERAGE([3]HistoricalFS!D65:E65) -> 3.4546657 | E37: =[3]HistoricalFS!F9/AVERAGE([3]HistoricalFS!E65:F65) -> 3.5367349 | F37: =[3]HistoricalFS!G9/AVERAGE([3]HistoricalFS!F65:G65) -> 3.6633528 | G37: =[3]HistoricalFS!H9/AVERAGE([3]HistoricalFS!G65:H65) -> 3.7333917
B38: Debtors Turnover | C38: =[3]HistoricalFS!D6/AVERAGE([3]HistoricalFS!C64:D64) -> 22.39568 | D38: =[3]HistoricalFS!E6/AVERAGE([3]HistoricalFS!D64:E64) -> 23.737476 | E38: =[3]HistoricalFS!F6/AVERAGE([3]HistoricalFS!E64:F64) -> 31.564549 | F38: =[3]HistoricalFS!G6/AVERAGE([3]HistoricalFS!F64:G64) -> 37.929588 | G38: =[3]HistoricalFS!H6/AVERAGE([3]HistoricalFS!G64:H64) -> 45.620729
B39: Asset Turnover | C39: =[3]HistoricalFS!D6/[3]HistoricalFS!D69 -> 0.8638118 | D39: =[3]HistoricalFS!E6/[3]HistoricalFS!E69 -> 0.85268496 | E39: =[3]HistoricalFS!F6/[3]HistoricalFS!F69 -> 0.85094768 | F39: =[3]HistoricalFS!G6/[3]HistoricalFS!G69 -> 0.79337703 | G39: =[3]HistoricalFS!H6/[3]HistoricalFS!H69 -> 0.78289543
B40: Working Capital Turnover | C40: =[3]HistoricalFS!D6/([3]HistoricalFS!D67-SUM([3]HistoricalFS!D54:D55)) -> 6.6021006 | D40: =[3]HistoricalFS!E6/([3]HistoricalFS!E67-SUM([3]HistoricalFS!E54:E55)) -> 6.9923248 | E40: =[3]HistoricalFS!F6/([3]HistoricalFS!F67-SUM([3]HistoricalFS!F54:F55)) -> 7.3688922 | F40: =[3]HistoricalFS!G6/([3]HistoricalFS!G67-SUM([3]HistoricalFS!G54:G55)) -> 7.1587609 | G40: =[3]HistoricalFS!H6/([3]HistoricalFS!H67-SUM([3]HistoricalFS!H54:H55)) -> 9.2149594
B43: Interpretation
B44: Inventory Turnover: Inventory turnover remained around 3x, indicating efficient inventory management and steady inventory movement.
B45: Debtors Turnover: Debtors turnover remained stable, reflecting consistent collection efficiency and effective receivables management.
B46: Asset Turnover: Asset turnover improved gradually from 0.53x to 0.64x, indicating better utilization of assets to generate revenue.
B47: Working Capital Turnover: Working capital turnover increased to 13.38x in FY26, reflecting improved efficiency in utilizing working capital to drive sales.
B49: Solvency Ratio
C51: FY22 | D51: FY23 | E51: FY24 | F51: FY25 | G51: FY26
B52: Debt Equity Ratio | C52: ='Historical '!D29/('Historical '!D27+'Historical '!D28) -> 0.66025291 | D52: ='Historical '!E29/('Historical '!E27+'Historical '!E28) -> 0.82354793 | E52: ='Historical '!F29/('Historical '!F27+'Historical '!F28) -> 0.94617701 | F52: ='Historical '!G29/('Historical '!G27+'Historical '!G28) -> 1.0398315 | G52: ='Historical '!H29/('Historical '!H27+'Historical '!H28) -> 0.90421655
B53: Interest Coverage Ratio | C53: =('Historical '!D15+'Historical '!D12)/'Historical '!D12 -> 10.195355 | D53: =('Historical '!E15+'Historical '!E12)/'Historical '!E12 -> 3.8950609 | E53: =('Historical '!F15+'Historical '!F12)/'Historical '!F12 -> 0.84721554 | F53: =('Historical '!G15+'Historical '!G12)/'Historical '!G12 -> 2.1460192 | G53: =('Historical '!H15+'Historical '!H12)/'Historical '!H12 -> 3.228067
B57: Interpretation
B58: Debt Equity Ratio: The debt-equity ratio remained below 1x throughout the period, indicating a balanced capital structure and prudent use of leverage.
B59: Interest Coverage Ratio: The interest coverage ratio remained above 3.5x, reflecting the company's strong ability to meet its interest obligations from operating earnings.
B62: Profitability Ratio
D64: FY22 | E64: FY23 | F64: FY24 | G64: FY25 | H64: FY26
B65: EPS | D65: =[3]HistoricalFS!D41 -> 34.184328 | E65: =[3]HistoricalFS!E41 -> 6.607495 | F65: =[3]HistoricalFS!F41 -> -3.9328794 | G65: =[3]HistoricalFS!G41 -> 2.5423799 | H65: =[3]HistoricalFS!H41 -> 8.7201666
B66: P/E Ratio | D66: ='[3]Data Sheet'!$B$8/[3]HistoricalFS!D41 -> 5.4782413 | E66: ='[3]Data Sheet'!$B$8/[3]HistoricalFS!E41 -> 28.342057 | F66: ='[3]Data Sheet'!$B$8/[3]HistoricalFS!F41 -> -47.616512 | G66: ='[3]Data Sheet'!$B$8/[3]HistoricalFS!G41 -> 73.659329 | H66: ='[3]Data Sheet'!$B$8/[3]HistoricalFS!H41 -> 21.475507
B67: Dividend Payout | D67: ='[3]Data Sheet'!C31/[3]HistoricalFS!D36 -> 0.14918015 | E67: ='[3]Data Sheet'!D31/[3]HistoricalFS!E36 -> 0.54442965 | F67: ='[3]Data Sheet'!E31/[3]HistoricalFS!F36 -> -0.9146918 | G67: ='[3]Data Sheet'!F31/[3]HistoricalFS!G36 -> 1.4149626 | H67: ='[3]Data Sheet'!G31/[3]HistoricalFS!H36 -> 0.45837245
B69: Interpretations
B70: Earnings Per Share (EPS): EPS recovered strongly after the FY24 loss, increasing to ?8.65 in FY26, reflecting improved profitability.
B71: P/E Ratio: The P/E ratio normalized to 21.66x in FY26 as earnings strengthened, while the negative value in FY24 was due to the reported loss.
B72: Dividend Payout Ratio: The company maintained a conservative dividend payout policy, retaining most of its earnings for business growth and capital requirements.

Sheet Beneish -M Score 
B1: Beneish M Score
B4: Historical Input | F4: FY25 | G4: FY26
B6: Revenue | F6: ='Historical '!G7 -> 218542.51 | G6: ='Historical '!H7 -> 232139.94
B7: Trade Receivables | F7: ='Historical '!G41 -> 5260.06 | G7: ='Historical '!H41 -> 4916.89
B8: COGS | F8: ='Historical '!G8 -> 171714.99 | G8: ='Historical '!H8 -> 171435.78
B9: Current Assets | F9: ='Historical '!G44 -> 61496.98 | G9: ='Historical '!H44 -> 62223.64
B10: Net PP&E | F10: ='Historical '!G35 -> 150914.06 | G10: ='Historical '!H35 -> 179908.13
B11: Total Assets | F11: ='Historical '!G46 -> 275458.58 | G11: ='Historical '!H46 -> 296514.62
B12: Depreciation | F12: ='Historical '!G13 -> 10421.33 | G12: ='Historical '!H13 -> 11954.51
B13: SG&A | F13: ='Historical '!G10 -> 21529.07 | G13: ='Historical '!H10 -> 26351.72
B14: Total Debt | F14: ='Historical '!G29 -> 94801.05 | G14: ='Historical '!H29 -> 92381.68
B15: PAT | F15: ='Historical '!G17 -> 3173.78 | G15: ='Historical '!H17 -> 10885.82
B16: Cash Flow from Operations | F16: ='Historical '!G62 -> 23138 | G16: ='Historical '!H62 -> 35064
B18: Beneish Score | G18: Score
B20: Days' Sales in Receivables Index | G20: =(G7/G6)/(F7/F6) -> 0.88000645
B21: Gross Margin Index | G21: =((F6-F8)/F6)/((G6-G8)/G6) -> 0.81940129
B22: Asset Quality Index | G22: =(1-((G9+G10)/G11))/(1-((F9+F10)/F11)) -> 0.80131636
B23: Sales Growth Index | G23: =G6/F6 -> 1.0622187
B24: Depreciation Index | G24: =(F12/(F12+F10))/(G12/(G10+G12)) -> 1.0366977
B25: Selling, General & Administrative Index | G25: =(G13/G6)/(F13/F6) -> 1.1523111
B26: Leverage Index | G26: =(G14/G11)/(F14/F11) -> 0.90527995
B27: Total Accruals to Total Assets | G27: =(G15-G16)/G11 -> -0.081541274
B29: Variable | F29: Weight
B31: Constant | G31: −4.84
B32: DSRI | G32: 0.92
B33: GMI | G33: 0.528
B34: AQI | G34: 0.404
B35: SGI | G35: 0.892
B36: DEPI | G36: 0.115
B37: SGAI | G37: −0.172
B38: TATA | G38: 4.679
B39: LVGI | G39: −0.327
B41: M score | F41: =-4.84+0.92*0.88+0.82*0.53+0.4*0.8+0.89*1.06+1.04*0.12+1.15*-0.172+4.68*-0.08+0.91*-0.327 -> -3.07737

Sheet Comparative Income Statement 
B1: Comparative Statement
B4: Income Statement
B5: (In Cr)
B6: Particulars | D6: 44256 | E6: ='Profit & Loss'!G3 -> 44651 | F6: ='Profit & Loss'!H3 -> 45016 | G6: ='Profit & Loss'!I3 -> 45382 | H6: ='Profit & Loss'!J3 -> 45747 | I6: ='Profit & Loss'!K3 -> 46112 | K6: Trend Analysis
B8: ='Profit & Loss'!A4 -> Sales | D8: ='Historical '!C7 -> 156477.4 | E8: ='Historical '!D7 -> 243959.17 | F8: ='Historical '!E7 -> 243352.69 | G8: ='Historical '!F7 -> 229170.78 | H8: ='Historical '!G7 -> 218542.51 | I8: ='Historical '!H7 -> 232139.94
B9: y-o-y growth | D9: 0 | E9: =E8/D8-1 -> 0.55906968 | F9: =F8/E8-1 -> -0.0024859898 | G9: =G8/F8-1 -> -0.058277186 | H9: =H8/G8-1 -> -0.046377073 | I9: =I8/H8-1 -> 0.062218696
B11: Cost of Goods Sold | D11: ='Historical '!C8 -> 102979.74 | E11: ='Historical '!D8 -> 143605.19 | F11: ='Historical '!E8 -> 178329.36 | G11: ='Historical '!F8 -> 183154.84 | H11: ='Historical '!G8 -> 171714.99 | I11: ='Historical '!H8 -> 171435.78
B12: y-o-y growth | D12: 0 | E12: =E11/D11-1 -> 0.39449944 | F12: =F11/E11-1 -> 0.24180303 | G12: =G11/F11-1 -> 0.027059369 | H12: =H11/G11-1 -> -0.062459993 | I12: =I11/H11-1 -> -0.0016260083
B14: Gross Profit | D14: ='Historical '!C9 -> 53497.66 | E14: ='Historical '!D9 -> 100353.98 | F14: ='Historical '!E9 -> 65023.33 | G14: ='Historical '!F9 -> 46015.94 | H14: ='Historical '!G9 -> 46827.52 | I14: ='Historical '!H9 -> 60704.16
B15: y-o-y growth | D15: 0 | E15: =E14/D14-1 -> 0.87585737 | F15: =F14/E14-1 -> -0.35206028 | G15: =G14/F14-1 -> -0.29231647 | H15: =H14/G14-1 -> 0.017636932 | I15: =I14/H14-1 -> 0.29633515
B17: Selling & General Expenses | D17: ='Historical '!C10 -> 22993.4 | E17: ='Historical '!D10 -> 36864.03 | F17: ='Historical '!E10 -> 32723.17 | G17: ='Historical '!F10 -> 23768.02 | H17: ='Historical '!G10 -> 21529.07 | I17: ='Historical '!H10 -> 26351.72
B18: y-o-y growth | D18: 0 | E18: =E17/D17-1 -> 0.60324397 | F18: =F17/E17-1 -> -0.11232793 | G18: =G17/F17-1 -> -0.27366389 | H18: =H17/G17-1 -> -0.094200106 | I18: =I17/H17-1 -> 0.22400642
B20: EBITDA | D20: ='Historical '!C11 -> 30504.26 | E20: ='Historical '!D11 -> 63489.95 | F20: ='Historical '!E11 -> 32300.16 | G20: ='Historical '!F11 -> 22247.92 | H20: ='Historical '!G11 -> 25298.45 | I20: ='Historical '!H11 -> 34352.44
B21: y-o-y growth | D21: 0 | E21: =E20/D20-1 -> 1.081347 | F21: =F20/E20-1 -> -0.49125555 | G21: =G20/F20-1 -> -0.31121332 | H21: =H20/G20-1 -> 0.13711529 | I21: =I20/H20-1 -> 0.35788714
B23: Interest | D23: ='Historical '!C12 -> 7606.71 | E23: ='Profit & Loss'!G9 -> 5462.2 | F23: ='Profit & Loss'!H9 -> 6298.7 | G23: ='Profit & Loss'!I9 -> 7507.57 | H23: ='Profit & Loss'!J9 -> 7340.95 | I23: ='Profit & Loss'!K9 -> 7167.06
B24: y-o-y growth | D24: 0 | E24: =E23/D23-1 -> -0.28192346 | F24: =F23/E23-1 -> 0.15314342 | G24: =G23/F23-1 -> 0.19192373 | H24: =H23/G23-1 -> -0.022193599 | I24: =I23/H23-1 -> -0.02368767
B26: Depreciation | D26: ='Historical '!C13 -> 9233.64 | E26: ='Historical '!D13 -> 9100.87 | F26: ='Historical '!E13 -> 9335.2 | G26: ='Historical '!F13 -> 9882.16 | H26: ='Historical '!G13 -> 10421.33 | I26: ='Historical '!H13 -> 11954.51
B27: y-o-y growth | D27: 0 | E27: =E26/D26-1 -> -0.014378945 | F27: =F26/E26-1 -> 0.025748088 | G27: =G26/F26-1 -> 0.058591139 | H27: =H26/G26-1 -> 0.054559934 | I27: =I26/H26-1 -> 0.14711942
B29: Other Income | D29: ='Historical '!C14 -> 179.78 | E29: ='Historical '!D14 -> 1299.99 | F29: ='Historical '!E14 -> 1568.86 | G29: ='Historical '!F14 -> -6005.23 | H29: ='Historical '!G14 -> 876.7 | I29: ='Historical '!H14 -> 737.82
B30: y-o-y growth | D30: 0 | E30: =E29/D29-1 -> 6.2310046 | F30: =F29/E29-1 -> 0.20682467 | G30: =G29/F29-1 -> -4.8277667 | H30: =H29/G29-1 -> -1.1459894 | I30: =I29/H29-1 -> -0.15841223
B32: Earnings Before Tax | D32: ='Historical '!C15 -> 13843.69 | E32: ='Historical '!D15 -> 50226.87 | F32: ='Historical '!E15 -> 18235.12 | G32: ='Historical '!F15 -> -1147.04 | H32: ='Historical '!G15 -> 8412.87 | I32: ='Historical '!H15 -> 15968.69
B33: y-o-y growth | D33: 0 | E33: =E32/D32-1 -> 2.6281418 | F33: =F32/E32-1 -> -0.63694493 | G33: =G32/F32-1 -> -1.0629028 | H33: =H32/G32-1 -> -8.3344173 | I33: =I32/H32-1 -> 0.89812632
B35: Tax | D35: ='Historical '!C16 -> 5653.9 | E35: ='Historical '!D16 -> 8477.55 | F35: ='Historical '!E16 -> 10159.77 | G35: ='Historical '!F16 -> 3762.57 | H35: ='Historical '!G16 -> 5239.09 | I35: ='Historical '!H16 -> 5082.87
B36: y-o-y growth | D36: 0 | E36: =E35/D35-1 -> 0.49941633 | F36: =F35/E35-1 -> 0.19843233 | G36: =G35/F35-1 -> -0.62965992 | H36: =H35/G35-1 -> 0.39242326 | I36: =I35/H35-1 -> -0.029818155
B38: Net Profit | D38: ='Historical '!C17 -> 8189.79 | E38: ='Historical '!D17 -> 41749.32 | F38: ='Historical '!E17 -> 8075.35 | G38: ='Historical '!F17 -> -4909.61 | H38: ='Historical '!G17 -> 3173.78 | I38: ='Historical '!H17 -> 10885.82
B39: y-o-y growth | D39: 0 | E39: =E38/D38-1 -> 4.0977278 | F39: =F38/E38-1 -> -0.80657529 | G39: =G38/F38-1 -> -1.6079749 | H39: =H38/G38-1 -> -1.6464424 | I39: =I38/H38-1 -> 2.4299227

Sheet Comparative Balance Sheet  
B1: Comparative Statement
B4: Balance Sheet
B5: (In Cr)
B6: Particulars | D6: 44256 | E6: ='Profit & Loss'!G3 -> 44651 | F6: ='Profit & Loss'!H3 -> 45016 | G6: ='Profit & Loss'!I3 -> 45382 | H6: ='Profit & Loss'!J3 -> 45747 | I6: ='Profit & Loss'!K3 -> 46112 | K6: Trend Analysis
B8: ='Balance Sheet'!A4 -> Equity Share Capital | D8: ='Historical '!C27 -> 1197.61 | E8: ='Historical '!D27 -> 1221.21 | F8: ='Historical '!E27 -> 1221.24 | G8: ='Historical '!F27 -> 1247.44 | H8: ='Historical '!G27 -> 1247.44 | I8: ='Historical '!H27 -> 1247.44
B9: y-o-y growth | D9: 0 | E9: =E8/D8-1 -> 0.019705914 | F9: =F8/E8-1 -> 2.4565799e-05 | G9: =G8/F8-1 -> 0.021453605 | H9: =H8/G8-1 -> 0 | I9: =I8/H8-1 -> 0
B11: ='Balance Sheet'!A5 -> Reserves | D11: ='Historical '!C28 -> 73041.16 | E11: ='Historical '!D28 -> 113221.83 | F11: ='Historical '!E28 -> 101860.86 | G11: ='Historical '!F28 -> 90788.32 | H11: ='Historical '!G28 -> 89922.19 | I11: ='Historical '!H28 -> 100920.21
B12: y-o-y growth | D12: 0 | E12: =E11/D11-1 -> 0.55010997 | F12: =F11/E11-1 -> -0.10034258 | G12: =G11/F11-1 -> -0.1087026 | H12: =H11/G11-1 -> -0.0095401038 | I12: =I11/H11-1 -> 0.12230596
B14: ='Balance Sheet'!A7 -> Borrowings | D14: ='Historical '!C29 -> 88501.41 | E14: ='Historical '!D29 -> 75561.35 | F14: ='Historical '!E29 -> 84893.05 | G14: ='Historical '!F29 -> 87082.12 | H14: ='Historical '!G29 -> 94801.05 | I14: ='Historical '!H29 -> 92381.68
B15: y-o-y growth | D15: 0 | E15: =E14/D14-1 -> -0.14621304 | F15: =F14/E14-1 -> 0.12349832 | G15: =G14/F14-1 -> 0.02578621 | H15: =H14/G14-1 -> 0.088639666 | I15: =I14/H14-1 -> -0.025520498
B17: ='Balance Sheet'!A8 -> Other Liabilities | D17: ='Historical '!C30 -> 52803.01 | E17: ='Historical '!D30 -> 52399.28 | F17: ='Historical '!E30 -> 56193.63 | G17: ='Historical '!F30 -> 57195.54 | H17: ='Historical '!G30 -> 58518.9 | I17: ='Historical '!H30 -> 64933.29
B18: y-o-y growth | D18: 0 | E18: =E17/D17-1 -> -0.0076459656 | F18: =F17/E17-1 -> 0.072412255 | G18: =G17/F17-1 -> 0.017829601 | H18: =H17/G17-1 -> 0.023137468 | I18: =I17/H17-1 -> 0.10961228
B20: Trade Payables | D20: ='Historical '!C31 -> 25967 | E20: ='Historical '!D31 -> 36765 | F20: ='Historical '!E31 -> 37833 | G20: ='Historical '!F31 -> 30228 | H20: ='Historical '!G31 -> 29314 | I20: ='Historical '!H31 -> 34810
B21: y-o-y growth | D21: 0 | E21: =E20/D20-1 -> 0.41583548 | F21: =F20/E20-1 -> 0.029049368 | G21: =G20/F20-1 -> -0.20101499 | H21: =H20/G20-1 -> -0.030236866 | I21: =I20/H20-1 -> 0.18748721
B23: Advance From Customers | D23: ='Historical '!C32 -> 2399 | E23: ='Historical '!D32 -> 3253 | F23: ='Historical '!E32 -> 3394 | G23: ='Historical '!F32 -> 2771 | H23: ='Historical '!G32 -> 1655 | I23: ='Historical '!H32 -> 2222
B24: y-o-y growth | D24: 0 | E24: =E23/D23-1 -> 0.35598166 | F24: =F23/E23-1 -> 0.043344605 | G24: =G23/F23-1 -> -0.18355922 | H24: =H23/G23-1 -> -0.40274269 | I24: =I23/H23-1 -> 0.34259819
B26: Fixed Assets | D26: ='Historical '!C35 -> 135775.18 | E26: ='Historical '!D35 -> 133287.83 | F26: ='Historical '!E35 -> 146621.46 | G26: ='Historical '!F35 -> 148814.38 | H26: ='Historical '!G35 -> 150914.06 | I26: ='Historical '!H35 -> 179908.13
B27: y-o-y growth | D27: 0 | E27: =E26/D26-1 -> -0.018319622 | F27: =F26/E26-1 -> 0.10003636 | G27: =G26/F26-1 -> 0.014956337 | H27: =H26/G26-1 -> 0.014109389 | I27: =I26/H26-1 -> 0.19212305
B29: Capital Work in Progress | D29: ='Historical '!C36 -> 19007.4 | E29: ='Historical '!D36 -> 22045.55 | F29: ='Historical '!E36 -> 31213.02 | G29: ='Historical '!F36 -> 34355.53 | H29: ='Historical '!G36 -> 41622.35 | I29: ='Historical '!H36 -> 28496.71
B30: y-o-y growth | D30: 0 | E30: =E29/D29-1 -> 0.15984038 | F30: =F29/E29-1 -> 0.4158422 | G30: =G29/F29-1 -> 0.10067946 | H30: =H29/G29-1 -> 0.2115182 | I30: =I29/H29-1 -> -0.31535077
B32: Investments | D32: ='Historical '!C37 -> 10681.93 | E32: ='Historical '!D37 -> 13139.85 | F32: ='Historical '!E37 -> 8410.31 | G32: ='Historical '!F37 -> 6257.57 | H32: ='Historical '!G37 -> 6194.11 | I32: ='Historical '!H37 -> 7088.85
B33: y-o-y growth | D33: 0 | E33: =E32/D32-1 -> 0.23010074 | F33: =F32/E32-1 -> -0.35993866 | G33: =G32/F32-1 -> -0.25596441 | H33: =H32/G32-1 -> -0.010141317 | I33: =I32/H32-1 -> 0.14445013
B35: Others Assets | D35: ='Historical '!C38 -> 29846.28 | E35: ='Historical '!D38 -> 36978.69 | F35: ='Historical '!E38 -> 23121.16 | G35: ='Historical '!F38 -> 15786.18 | H35: ='Historical '!G38 -> 15231.08 | I35: ='Historical '!H38 -> 18797.29
B36: y-o-y growth | D36: 0 | E36: =E35/D35-1 -> 0.23897149 | F36: =F35/E35-1 -> -0.37474367 | G36: =G35/F35-1 -> -0.317241 | H36: =H35/G35-1 -> -0.035163668 | I36: =I35/H35-1 -> 0.23414032
B38: Recievables | D38: ='Historical '!C41 -> 9539.84 | E38: ='Historical '!D41 -> 12246.43 | F38: ='Historical '!E41 -> 8257.24 | G38: ='Historical '!F41 -> 6263.53 | H38: ='Historical '!G41 -> 5260.06 | I38: ='Historical '!H41 -> 4916.89
B39: y-o-y growth | D39: 0 | E39: =E38/D38-1 -> 0.2837144 | F39: =F38/E38-1 -> -0.32574309 | G39: =G38/F38-1 -> -0.24144993 | H39: =H38/G38-1 -> -0.16020838 | I39: =I38/H38-1 -> -0.065240701
B41: Inventory | D41: ='Historical '!C42 -> 33276.38 | E41: ='Historical '!D42 -> 48824.39 | F41: ='Historical '!E42 -> 54415.33 | G41: ='Historical '!F42 -> 49157.51 | H41: ='Historical '!G42 -> 44589.94 | I41: ='Historical '!H42 -> 47249.22
B42: y-o-y growth | D42: 0 | E42: =E41/D41-1 -> 0.46723862 | F42: =F41/E41-1 -> 0.11451121 | G42: =G41/F41-1 -> -0.096623874 | H42: =H41/G41-1 -> -0.092917033 | I42: =I41/H41-1 -> 0.059638564
B44: Cash at Bank | D44: ='Historical '!C43 -> 5782.18 | E44: ='Historical '!D43 -> 15898.93 | F44: ='Historical '!E43 -> 13357.26 | G44: ='Historical '!F43 -> 8677.72 | H44: ='Historical '!G43 -> 11646.98 | I44: ='Historical '!H43 -> 10057.53
B45: y-o-y growth | D45: 0 | E45: =E44/D44-1 -> 1.7496429 | F45: =F44/E44-1 -> -0.15986422 | G45: =G44/F44-1 -> -0.35033682 | H45: =H44/G44-1 -> 0.34217052 | I45: =I44/H44-1 -> -0.13646885

Sheet Common Balance Sheet
B1: Comparative Statement
B4: Balance Sheet
B5: (In Cr)
B6: Particulars | D6: 44256 | E6: ='Profit & Loss'!G3 -> 44651 | F6: ='Profit & Loss'!H3 -> 45016 | G6: ='Profit & Loss'!I3 -> 45382 | H6: ='Profit & Loss'!J3 -> 45747 | I6: ='Profit & Loss'!K3 -> 46112 | K6: Trend Analysis
B8: ='Balance Sheet'!A4 -> Equity Share Capital | D8: ='Historical '!C27 -> 1197.61 | E8: ='Historical '!D27 -> 1221.21 | F8: ='Historical '!E27 -> 1221.24 | G8: ='Historical '!F27 -> 1247.44 | H8: ='Historical '!G27 -> 1247.44 | I8: ='Historical '!H27 -> 1247.44
B9: y-o-y growth | D9: =D8/'Historical '!C$46 -> 0.0049100651 | E9: =E8/'Historical '!D$46 -> 0.0043240662 | F9: =F8/'Historical '!E$46 -> 0.0042791102 | G9: =G8/'Historical '!F$46 -> 0.0046319438 | H9: =H8/'Historical '!G$46 -> 0.0045285937 | I9: =I8/'Historical '!H$46 -> 0.0042070101
B11: ='Balance Sheet'!A5 -> Reserves | D11: ='Historical '!C28 -> 73041.16 | E11: ='Historical '!D28 -> 113221.83 | F11: ='Historical '!E28 -> 101860.86 | G11: ='Historical '!F28 -> 90788.32 | H11: ='Historical '!G28 -> 89922.19 | I11: ='Historical '!H28 -> 100920.21
B12: y-o-y growth | D12: =D11/'Historical '!C$46 -> 0.29946047 | E12: =E11/'Historical '!D$46 -> 0.4008964 | F12: =F11/'Historical '!E$46 -> 0.35691088 | G12: =G11/'Historical '!F$46 -> 0.33711152 | H12: =H11/'Historical '!G$46 -> 0.32644541 | I12: =I11/'Historical '!H$46 -> 0.34035492
B14: ='Balance Sheet'!A7 -> Borrowings | D14: ='Historical '!C29 -> 88501.41 | E14: ='Historical '!D29 -> 75561.35 | F14: ='Historical '!E29 -> 84893.05 | G14: ='Historical '!F29 -> 87082.12 | H14: ='Historical '!G29 -> 94801.05 | I14: ='Historical '!H29 -> 92381.68
B15: y-o-y growth | D15: =D14/'Historical '!C$46 -> 0.36284574 | E15: =E14/'Historical '!D$46 -> 0.26754799 | F15: =F14/'Historical '!E$46 -> 0.29745727 | G15: =G14/'Historical '!F$46 -> 0.32334981 | H15: =H14/'Historical '!G$46 -> 0.34415719 | I15: =I14/'Historical '!H$46 -> 0.3115586
B17: ='Balance Sheet'!A8 -> Other Liabilities | D17: ='Historical '!C30 -> 52803.01 | E17: ='Historical '!D30 -> 52399.28 | F17: ='Historical '!E30 -> 56193.63 | G17: ='Historical '!F30 -> 57195.54 | H17: ='Historical '!G30 -> 58518.9 | I17: ='Historical '!H30 -> 64933.29
B18: y-o-y growth | D18: =D17/'Historical '!C$46 -> 0.21648635 | E18: =E17/'Historical '!D$46 -> 0.18553562 | F18: =F17/'Historical '!E$46 -> 0.1968972 | G18: =G17/'Historical '!F$46 -> 0.21237617 | H18: =H17/'Historical '!G$46 -> 0.21244174 | I18: =I17/'Historical '!H$46 -> 0.21898849
B20: Trade Payables | D20: ='Historical '!C31 -> 25967 | E20: ='Historical '!D31 -> 36765 | F20: ='Historical '!E31 -> 37833 | G20: ='Historical '!F31 -> 30228 | H20: ='Historical '!G31 -> 29314 | I20: ='Historical '!H31 -> 34810
B21: y-o-y growth | D21: =D20/'Historical '!C$46 -> 0.10646175 | E21: =E20/'Historical '!D$46 -> 0.13017769 | F21: =F20/'Historical '!E$46 -> 0.13256328 | G21: =G20/'Historical '!F$46 -> 0.11224139 | H21: =H20/'Historical '!G$46 -> 0.1064189 | I21: =I20/'Historical '!H$46 -> 0.11739725
B23: Advance From Customers | D23: ='Historical '!C32 -> 2399 | E23: ='Historical '!D32 -> 3253 | F23: ='Historical '!E32 -> 3394 | G23: ='Historical '!F32 -> 2771 | H23: ='Historical '!G32 -> 1655 | I23: ='Historical '!H32 -> 2222
B24: y-o-y growth | D24: =D23/'Historical '!C$46 -> 0.0098356278 | E24: =E23/'Historical '!D$46 -> 0.011518238 | F24: =F23/'Historical '!E$46 -> 0.011892257 | G24: =G23/'Historical '!F$46 -> 0.010289165 | H24: =H23/'Historical '!G$46 -> 0.0060081628 | I24: =I23/'Historical '!H$46 -> 0.0074937283
B26: Fixed Assets | D26: ='Historical '!C35 -> 135775.18 | E26: ='Historical '!D35 -> 133287.83 | F26: ='Historical '!E35 -> 146621.46 | G26: ='Historical '!F35 -> 148814.38 | H26: ='Historical '!G35 -> 150914.06 | I26: ='Historical '!H35 -> 179908.13
B27: y-o-y growth | D27: =D26/'Historical '!C$46 -> 0.55666283 | E27: =E26/'Historical '!D$46 -> 0.47194619 | F27: =F26/'Historical '!E$46 -> 0.51374782 | G27: =G26/'Historical '!F$46 -> 0.55257154 | H27: =H26/'Historical '!G$46 -> 0.5478648 | I27: =I26/'Historical '!H$46 -> 0.60674286
B29: Capital Work in Progress | D29: ='Historical '!C36 -> 19007.4 | E29: ='Historical '!D36 -> 22045.55 | F29: ='Historical '!E36 -> 31213.02 | G29: ='Historical '!F36 -> 34355.53 | H29: ='Historical '!G36 -> 41622.35 | I29: ='Historical '!H36 -> 28496.71
B30: y-o-y growth | D30: =D29/'Historical '!C$46 -> 0.077928183 | E30: =E29/'Historical '!D$46 -> 0.078058989 | F30: =F29/'Historical '!E$46 -> 0.10936749 | G30: =G29/'Historical '!F$46 -> 0.12756757 | H30: =H29/'Historical '!G$46 -> 0.15110203 | I30: =I29/'Historical '!H$46 -> 0.096105582
B32: Investments | D32: ='Historical '!C37 -> 10681.93 | E32: ='Historical '!D37 -> 13139.85 | F32: ='Historical '!E37 -> 8410.31 | G32: ='Historical '!F37 -> 6257.57 | H32: ='Historical '!G37 -> 6194.11 | I32: ='Historical '!H37 -> 7088.85
B33: y-o-y growth | D33: =D32/'Historical '!C$46 -> 0.043794701 | E33: =E32/'Historical '!D$46 -> 0.046525644 | F33: =F32/'Historical '!E$46 -> 0.029468936 | G33: =G32/'Historical '!F$46 -> 0.023235356 | H33: =H32/'Historical '!G$46 -> 0.022486539 | I33: =I32/'Historical '!H$46 -> 0.023907253
B35: Others Assets | D35: ='Historical '!C38 -> 29846.28 | E35: ='Historical '!D38 -> 36978.69 | F35: ='Historical '!E38 -> 23121.16 | G35: ='Historical '!F38 -> 15786.18 | H35: ='Historical '!G38 -> 15231.08 | I35: ='Historical '!H38 -> 18797.29
B36: y-o-y growth | D36: =D35/'Historical '!C$46 -> 0.12236636 | E36: =E35/'Historical '!D$46 -> 0.13093432 | F36: =F35/'Historical '!E$46 -> 0.081014372 | G36: =G35/'Historical '!F$46 -> 0.058616606 | H36: =H35/'Historical '!G$46 -> 0.05529354 | I36: =I35/'Historical '!H$46 -> 0.063394142
B38: Recievables | D38: ='Historical '!C41 -> 9539.84 | E38: ='Historical '!D41 -> 12246.43 | F38: ='Historical '!E41 -> 8257.24 | G38: ='Historical '!F41 -> 6263.53 | H38: ='Historical '!G41 -> 5260.06 | I38: ='Historical '!H41 -> 4916.89
B39: y-o-y growth | D39: =D38/'Historical '!C$46 -> 0.039112261 | E39: =E38/'Historical '!D$46 -> 0.043362218 | F39: =F38/'Historical '!E$46 -> 0.028932593 | G39: =G38/'Historical '!F$46 -> 0.023257487 | H39: =H38/'Historical '!G$46 -> 0.019095648 | I39: =I38/'Historical '!H$46 -> 0.016582285
B41: Inventory | D41: ='Historical '!C42 -> 33276.38 | E41: ='Historical '!D42 -> 48824.39 | F41: ='Historical '!E42 -> 54415.33 | G41: ='Historical '!F42 -> 49157.51 | H41: ='Historical '!G42 -> 44589.94 | I41: ='Historical '!H42 -> 47249.22
B42: y-o-y growth | D42: =D41/'Historical '!C$46 -> 0.13642938 | E42: =E41/'Historical '!D$46 -> 0.17287763 | F42: =F41/'Historical '!E$46 -> 0.1906662 | G42: =G41/'Historical '!F$46 -> 0.18252968 | H42: =H41/'Historical '!G$46 -> 0.1618753 | I42: =I41/'Historical '!H$46 -> 0.1593487
B44: Cash at Bank | D44: ='Historical '!C43 -> 5782.18 | E44: ='Historical '!D43 -> 15898.93 | F44: ='Historical '!E43 -> 13357.26 | G44: ='Historical '!F43 -> 8677.72 | H44: ='Historical '!G43 -> 11646.98 | I44: ='Historical '!H43 -> 10057.53
B45: y-o-y growth | D45: =D44/'Historical '!C$46 -> 0.023706282 | E45: =E44/'Historical '!D$46 -> 0.056295007 | F45: =F44/'Historical '!E$46 -> 0.046802584 | G45: =G44/'Historical '!F$46 -> 0.032221759 | H45: =H44/'Historical '!G$46 -> 0.042282146 | I45: =I44/'Historical '!H$46 -> 0.033919171

Sheet Common Income Statement
B1: Comparative Statement
B4: Income Statement
B5: (In Cr)
B6: Particulars | D6: 44256 | E6: ='Profit & Loss'!G3 -> 44651 | F6: ='Profit & Loss'!H3 -> 45016 | G6: ='Profit & Loss'!I3 -> 45382 | H6: ='Profit & Loss'!J3 -> 45747 | I6: ='Profit & Loss'!K3 -> 46112 | K6: Trend Analysis
B8: ='Profit & Loss'!A4 -> Sales | D8: ='Historical '!C7 -> 156477.4 | E8: ='Historical '!D7 -> 243959.17 | F8: ='Historical '!E7 -> 243352.69 | G8: ='Historical '!F7 -> 229170.78 | H8: ='Historical '!G7 -> 218542.51 | I8: ='Historical '!H7 -> 232139.94
B9: y-o-y growth | D9: =D8/D8 -> 1 | E9: =E8/E8 -> 1 | F9: =F8/F8 -> 1 | G9: =G8/G8 -> 1 | H9: =H8/H8 -> 1 | I9: =I8/I8 -> 1
B11: Cost of Goods Sold | D11: ='Historical '!C8 -> 102979.74 | E11: ='Historical '!D8 -> 143605.19 | F11: ='Historical '!E8 -> 178329.36 | G11: ='Historical '!F8 -> 183154.84 | H11: ='Historical '!G8 -> 171714.99 | I11: ='Historical '!H8 -> 171435.78
B12: y-o-y growth | D12: =D11/D$8 -> 0.65811255 | E12: =E11/E$8 -> 0.58864436 | F12: =F11/F$8 -> 0.73280209 | G12: =G11/G$8 -> 0.79920677 | H12: =H11/H$8 -> 0.78572809 | I12: =I11/I$8 -> 0.73850187
B14: Gross Profit | D14: ='Historical '!C9 -> 53497.66 | E14: ='Historical '!D9 -> 100353.98 | F14: ='Historical '!E9 -> 65023.33 | G14: ='Historical '!F9 -> 46015.94 | H14: ='Historical '!G9 -> 46827.52 | I14: ='Historical '!H9 -> 60704.16
B15: y-o-y growth | D15: =D14/D$8 -> 0.34188745 | E15: =E14/E$8 -> 0.41135564 | F15: =F14/F$8 -> 0.26719791 | G15: =G14/G$8 -> 0.20079323 | H15: =H14/H$8 -> 0.21427191 | I15: =I14/I$8 -> 0.26149813
B17: Selling & General Expenses | D17: ='Historical '!C10 -> 22993.4 | E17: ='Historical '!D10 -> 36864.03 | F17: ='Historical '!E10 -> 32723.17 | G17: ='Historical '!F10 -> 23768.02 | H17: ='Historical '!G10 -> 21529.07 | I17: ='Historical '!H10 -> 26351.72
B18: y-o-y growth | D18: =D17/D$8 -> 0.1469439 | E18: =E17/E$8 -> 0.15110738 | F18: =F17/F$8 -> 0.13446808 | G18: =G17/G$8 -> 0.10371313 | H18: =H17/H$8 -> 0.098512047 | I18: =I17/I$8 -> 0.11351653
B20: EBITDA | D20: ='Historical '!C11 -> 30504.26 | E20: ='Historical '!D11 -> 63489.95 | F20: ='Historical '!E11 -> 32300.16 | G20: ='Historical '!F11 -> 22247.92 | H20: ='Historical '!G11 -> 25298.45 | I20: ='Historical '!H11 -> 34352.44
B21: y-o-y growth | D21: =D20/D$8 -> 0.19494355 | E21: =E20/E$8 -> 0.26024826 | F21: =F20/F$8 -> 0.13272983 | G21: =G20/G$8 -> 0.09708009 | H21: =H20/H$8 -> 0.11575986 | I21: =I20/I$8 -> 0.1479816
B23: Interest | D23: ='Historical '!C12 -> 7606.71 | E23: ='Profit & Loss'!G9 -> 5462.2 | F23: ='Profit & Loss'!H9 -> 6298.7 | G23: ='Profit & Loss'!I9 -> 7507.57 | H23: ='Profit & Loss'!J9 -> 7340.95 | I23: ='Profit & Loss'!K9 -> 7167.06
B24: y-o-y growth | D24: =D23/D$8 -> 0.048612196 | E24: =E23/E$8 -> 0.022389812 | F24: =F23/F$8 -> 0.02588301 | G24: =G23/G$8 -> 0.032759717 | H24: =H23/H$8 -> 0.03359049 | I24: =I23/I$8 -> 0.030873877
B26: Depreciation | D26: ='Historical '!C13 -> 9233.64 | E26: ='Historical '!D13 -> 9100.87 | F26: ='Historical '!E13 -> 9335.2 | G26: ='Historical '!F13 -> 9882.16 | H26: ='Historical '!G13 -> 10421.33 | I26: ='Historical '!H13 -> 11954.51
B27: y-o-y growth | D27: =D26/D$8 -> 0.059009416 | E27: =E26/E$8 -> 0.03730489 | F27: =F26/F$8 -> 0.038360784 | G27: =G26/G$8 -> 0.043121379 | H27: =H26/H$8 -> 0.047685597 | I27: =I26/I$8 -> 0.051496998
B29: Other Income | D29: ='Historical '!C14 -> 179.78 | E29: ='Historical '!D14 -> 1299.99 | F29: ='Historical '!E14 -> 1568.86 | G29: ='Historical '!F14 -> -6005.23 | H29: ='Historical '!G14 -> 876.7 | I29: ='Historical '!H14 -> 737.82
B30: y-o-y growth | D30: =D29/D$8 -> 0.0011489199 | E30: =E29/E$8 -> 0.0053287196 | F30: =F29/F$8 -> 0.006446857 | G30: =G29/G$8 -> -0.02620417 | H30: =H29/H$8 -> 0.0040115765 | I30: =I29/I$8 -> 0.0031783415
B32: Earnings Before Tax | D32: ='Historical '!C15 -> 13843.69 | E32: ='Historical '!D15 -> 50226.87 | F32: ='Historical '!E15 -> 18235.12 | G32: ='Historical '!F15 -> -1147.04 | H32: ='Historical '!G15 -> 8412.87 | I32: ='Historical '!H15 -> 15968.69
B33: y-o-y growth | D33: =D32/D$8 -> 0.088470859 | E33: =E32/E$8 -> 0.20588228 | F33: =F32/F$8 -> 0.074932889 | G33: =G32/G$8 -> -0.0050051756 | H33: =H32/H$8 -> 0.038495348 | I33: =I32/I$8 -> 0.068789067
B35: Tax | D35: ='Historical '!C16 -> 5653.9 | E35: ='Historical '!D16 -> 8477.55 | F35: ='Historical '!E16 -> 10159.77 | G35: ='Historical '!F16 -> 3762.57 | H35: ='Historical '!G16 -> 5239.09 | I35: ='Historical '!H16 -> 5082.87
B36: y-o-y growth | D36: =D35/D$8 -> 0.036132374 | E36: =E35/E$8 -> 0.034749872 | F36: =F35/F$8 -> 0.041749158 | G36: =G35/G$8 -> 0.016418193 | H36: =H35/H$8 -> 0.023972865 | I36: =I35/I$8 -> 0.021895715
B38: Net Profit | D38: ='Historical '!C17 -> 8189.79 | E38: ='Historical '!D17 -> 41749.32 | F38: ='Historical '!E17 -> 8075.35 | G38: ='Historical '!F17 -> -4909.61 | H38: ='Historical '!G17 -> 3173.78 | I38: ='Historical '!H17 -> 10885.82
B39: y-o-y growth | D39: =D38/D$8 -> 0.052338485 | E39: =E38/E$8 -> 0.17113241 | F39: =F38/F$8 -> 0.03318373 | G39: =G38/G$8 -> -0.021423368 | H39: =H38/H$8 -> 0.014522484 | I39: =I38/I$8 -> 0.046893352

Sheet Altman's scroe
B1: Altman's Z Score
B4: Financial Summary
B29: Workinng Capital/Total Assets
E30: ='[1]Reinvestment rate'!F34 -> 44986 | F30: ='[1]Reinvestment rate'!G34 -> 45352 | G30: ='[1]Reinvestment rate'!H34 -> 45717 | H30: ='[1]Reinvestment rate'!I34 -> 46082
B31: Working Capital | E31: ='Historical '!E60 -> -3706 | F31: ='Historical '!F60 -> 3384 | G31: ='Historical '!G60 -> 2207 | H31: ='Historical '!H60 -> 5442
B32: Total Assets | E32: ='Historical '!E46 -> 285395.78 | F32: ='Historical '!F46 -> 269312.42 | G32: ='Historical '!G46 -> 275458.58 | H32: ='Historical '!H46 -> 296514.62
B33: Working Capital/Total Assets (A) | E33: =E31/E32 -> -0.012985476 | F33: =F31/F32 -> 0.012565332 | G33: =G31/G32 -> 0.0080120939 | H33: =H31/H32 -> 0.018353227
B35: Retained Earnings /Total Assets
E36: =E30 -> 44986 | F36: =F30 -> 45352 | G36: =G30 -> 45717 | H36: =H30 -> 46082
B37: Retained Earnings | E37: ='Historical '!E28 -> 101860.86 | F37: ='Historical '!F28 -> 90788.32 | G37: ='Historical '!G28 -> 89922.19 | H37: ='Historical '!H28 -> 100920.21
B38: =B32 -> Total Assets | E38: =E32 -> 285395.78 | F38: =F32 -> 269312.42 | G38: =G32 -> 275458.58 | H38: =H32 -> 296514.62
B39: Retained Earnings/Total Assets (B) | E39: =E37/E38 -> 0.35691088 | F39: =F37/F38 -> 0.33711152 | G39: =G37/G38 -> 0.32644541 | H39: =H37/H38 -> 0.34035492
B41: EBIT/Total Assets
E42: 44986 | F42: 45352 | G42: 45717 | H42: 46082
B43: EBIT | E43: ='Historical '!C15+'Historical '!C12 -> 21450.4 | F43: ='Historical '!D15+'Historical '!D12 -> 55689.07 | G43: ='Historical '!E15+'Historical '!E12 -> 24533.82 | H43: ='Historical '!F15+'Historical '!F12 -> 6360.53
B44: =B38 -> Total Assets | E44: =E38 -> 285395.78 | F44: =F38 -> 269312.42 | G44: =G38 -> 275458.58 | H44: =H38 -> 296514.62
B45: EBIT/Total Assets (C) | E45: =E43/E44 -> 0.075160186 | F45: =F43/F44 -> 0.20678241 | G45: =G43/G44 -> 0.089065369 | H45: =H43/H44 -> 0.021450983
B47: Market Cap/Long Term Liabilities
E48: 44986 | F48: 45352 | G48: 45717 | H48: 46082
B49: Market Cap | E49: 173200 | F49: 174000 | G49: 210700 | H49: 233842
B50: Long Term Liabilities | E50: ='Balance Sheet'!H10 -> 51446 | F50: ='Balance Sheet'!I10 -> 51577 | G50: ='Balance Sheet'!J10 -> 68552 | H50: ='Balance Sheet'!K10 -> 63754
B51: Market Cap/Long Term Liabilities (D) | E51: =E49/E50 -> 3.3666369 | F51: =F49/F50 -> 3.3735968 | G51: =G49/G50 -> 3.0735792 | H51: =H49/H50 -> 3.6678797
B53: Sales/Total Assets
E54: 44986 | F54: 45352 | G54: 45717 | H54: 46082
B55: Sales | E55: ='Historical '!E7 -> 243352.69 | F55: ='Historical '!F7 -> 229170.78 | G55: ='Historical '!G7 -> 218542.51 | H55: ='Historical '!H7 -> 232139.94
B56: Total Assets | E56: =E38 -> 285395.78 | F56: =F38 -> 269312.42 | G56: =G38 -> 275458.58 | H56: =H38 -> 296514.62
B57: Return on Assets (E) | E57: =E55/E56 -> 0.85268496 | F57: =F55/F56 -> 0.85094768 | G57: =G55/G56 -> 0.79337703 | H57: =H55/H56 -> 0.78289543
B59: Altman's Score
E60: =E30 -> 44986 | F60: =F30 -> 45352 | G60: =G30 -> 45717 | H60: =H30 -> 46082
B61: Final Score | E61: =(E33*1.2)+(E39*1.5)+(E45*3.3)+(E51*0.9)+(E57*1.7) -> 5.24735 | F61: =(F33*1.2)+(F39*1.5)+(F45*3.3)+(F51*0.9)+(F57*1.7) -> 5.6859758 | G61: =(G33*1.2)+(G39*1.5)+(G45*3.3)+(G51*0.9)+(G57*1.7) -> 4.9081606 | H61: =(H33*1.2)+(H39*1.5)+(H45*3.3)+(H51*0.9)+(H57*1.7) -> 5.2353584
B62: Financial Stability | E62: =IF(E61<1.81," Distressed",IF(E61>3,"Strong","Grey Zone")) -> Strong | F62: =IF(F61<1.81," Distressed",IF(F61>3,"Strong","Grey Zone")) -> Strong | G62: =IF(G61<1.81," Distressed",IF(G61>3,"Strong","Grey Zone")) -> Strong | H62: =IF(H61<1.81," Distressed",IF(H61>3,"Strong","Grey Zone")) -> Strong

Sheet Dupont Analysis
B1: Dupont Analysis
B4: (TATA Steel BSE Code: 500470)
B5: Current Price: INR 187
B7: 52 Week (High: 224.40 & Low: 152.55)
B9: Financial Summary
B34: Return on Equity (ROE)
E35: ='[1]Reinvestment rate'!F34 -> 44986 | F35: ='[1]Reinvestment rate'!G34 -> 45352 | G35: ='[1]Reinvestment rate'!H34 -> 45717 | H35: ='[1]Reinvestment rate'!I34 -> 46082
B36: Net Profit | E36: ='Historical '!E17 -> 8075.35 | F36: ='Historical '!F17 -> -4909.61 | G36: ='Historical '!G17 -> 3173.78 | H36: ='Historical '!H17 -> 10885.82
B37: Average Shareholder Equity | E37: ='Balance Sheet'!H6 -> 108762.57 | F37: ='Balance Sheet'!I6 -> 97558.93 | G37: ='Balance Sheet'!J6 -> 91602.695 | H37: ='Balance Sheet'!K6 -> 96668.64
B38: Return on Equity | E38: =E36/E37 -> 0.07424751 | F38: =F36/F37 -> -0.050324558 | G38: =G36/G37 -> 0.034647234 | H38: =H36/H37 -> 0.11260963
B40: ROE-Dupont Equation
E41: =E35 -> 44986 | F41: =F35 -> 45352 | G41: =G35 -> 45717 | H41: =H35 -> 46082
B42: =B36 -> Net Profit | E42: =E36 -> 8075.35 | F42: =F36 -> -4909.61 | G42: =G36 -> 3173.78 | H42: =H36 -> 10885.82
B43: Revenue | E43: ='Historical '!E7 -> 243352.69 | F43: ='Historical '!F7 -> 229170.78 | G43: ='Historical '!G7 -> 218542.51 | H43: ='Historical '!H7 -> 232139.94
B44: Net Profit Margin (A) | E44: =E42/E43 -> 0.03318373 | F44: =F42/F43 -> -0.021423368 | G44: =G42/G43 -> 0.014522484 | H44: =H42/H43 -> 0.046893352
E46: 44986 | F46: 45352 | G46: 45717 | H46: 46082
B47: Revenue | E47: =E43 -> 243352.69 | F47: =F43 -> 229170.78 | G47: =G43 -> 218542.51 | H47: =H43 -> 232139.94
B48: Average Total Assets | E48: ='Balance Sheet'!H16 -> 390458.44 | F48: ='Balance Sheet'!I16 -> 366872.07 | G48: ='Balance Sheet'!J16 -> 350692 | H48: ='Balance Sheet'!K16 -> 364861.09
B49: Asset Turnover Ratio (B) | E49: =E47/E48 -> 0.62324864 | F49: =F47/F48 -> 0.6246613 | G49: =G47/G48 -> 0.62317507 | H49: =H47/H48 -> 0.63624196
E51: 44986 | F51: 45352 | G51: 45717 | H51: 46082
B52: Average Total Assets | E52: =E48 -> 390458.44 | F52: =F48 -> 366872.07 | G52: =G48 -> 350692 | H52: =H48 -> 364861.09
B53: Average Shareholder Equity | E53: =E37 -> 108762.57 | F53: =F37 -> 97558.93 | G53: =G37 -> 91602.695 | H53: =H37 -> 96668.64
B54: Equity Mulitplier (C) | E54: =E52/E53 -> 3.5900075 | F54: =F52/F53 -> 3.7605175 | G54: =G52/G53 -> 3.8284026 | H54: =H52/H53 -> 3.7743481
B56: Return on Equity (A*B*C) | E56: =E44*E49*E54 -> 0.07424751 | F56: =F44*F49*F54 -> -0.050324558 | G56: =G44*G49*G54 -> 0.034647234 | H56: =H44*H49*H54 -> 0.11260963
B58: Return on Asset
E59: =E35 -> 44986 | F59: =F35 -> 45352 | G59: =G35 -> 45717 | H59: =H35 -> 46082
B60: Net Profit | E60: =E42 -> 8075.35 | F60: =F42 -> -4909.61 | G60: =G42 -> 3173.78 | H60: =H42 -> 10885.82
B61: =B48 -> Average Total Assets | E61: =E52 -> 390458.44 | F61: =F52 -> 366872.07 | G61: =G52 -> 350692 | H61: =H52 -> 364861.09
B62: Return on Asset | E62: =E60/E61 -> 0.020681715 | F62: =F60/F61 -> -0.013382349 | G62: =G60/G61 -> 0.0090500496 | H62: =H60/H61 -> 0.029835519
B64: ROA - Dupont Equation
E65: =E59 -> 44986 | F65: =F59 -> 45352 | G65: =G59 -> 45717 | H65: =H59 -> 46082
B66: =B60 -> Net Profit | E66: =E42 -> 8075.35 | F66: =F42 -> -4909.61 | G66: =G42 -> 3173.78 | H66: =H42 -> 10885.82
B67: Revenue | E67: =E43 -> 243352.69 | F67: =F43 -> 229170.78 | G67: =G43 -> 218542.51 | H67: =H43 -> 232139.94
B68: Net Profit Margin (A) | E68: =E66/E67 -> 0.03318373 | F68: =F66/F67 -> -0.021423368 | G68: =G66/G67 -> 0.014522484 | H68: =H66/H67 -> 0.046893352
E70: =E46 -> 44986 | F70: =F46 -> 45352 | G70: =G46 -> 45717 | H70: =H46 -> 46082
B71: Revenue | E71: =E67 -> 243352.69 | F71: =F67 -> 229170.78 | G71: =G67 -> 218542.51 | H71: =H67 -> 232139.94
B72: Average Total Assets | E72: =E52 -> 390458.44 | F72: =F52 -> 366872.07 | G72: =G52 -> 350692 | H72: =H52 -> 364861.09
B73: Asset Turnover Ratio (B) | E73: =E71/E72 -> 0.62324864 | F73: =F71/F72 -> 0.6246613 | G73: =G71/G72 -> 0.62317507 | H73: =H71/H72 -> 0.63624196
B75: Return on Asset (A*B) | E75: =E68*E73 -> 0.020681715 | F75: =F68*F73 -> -0.013382349 | G75: =G68*G73 -> 0.0090500496 | H75: =H68*H73 -> 0.029835519

Sheet Assumption and Drivers
A1: # | B1: Operational Driver
B3: Year | D3: Steel Sales Volume (Mnt) | E3: Crude Steel Production (Mnt) | F3: Installed Capacity (Mnt) | G3: Revenue (In Cr)
B4: 2025-26 | D4: 31.97 | E4: 31.67 | F4: 22.47 | G4: 232140
B5: 2024-25 | D5: 30.96 | E5: 30.92 | F5: 20.72 | G5: =G4-13597 -> 218543
B6: 2023-24 | D6: 29.39 | E6: 29.94 | F6: 20.6 | G6: ='Profit & Loss'!I4 -> 229170.78
B7: 2022-23 | D7: 28.79 | E7: 30.65 | F7: 20.3 | G7: ='Profit & Loss'!I5 -> 206922.86
B9: Historical growth | D9: 2025-26 | E9: 2024-25 | F9: 2023-24
B10: Steel Sales Volume (Mnt) | D10: =D4/D5-1 -> 0.032622739 | E10: =D5/D6-1 -> 0.05341953 | F10: =D6/D7-1 -> 0.02084057
B11: Crude Steel Production (Mnt) | D11: =E4/E5-1 -> 0.024256145 | E11: =E5/E6-1 -> 0.032732131 | F11: =E6/E7-1 -> -0.023164763
B12: Installed Capacity (Mnt) | D12: =F4/F5-1 -> 0.084459459 | E12: =F5/F6-1 -> 0.0058252427 | F12: =F6/F7-1 -> 0.014778325
B14: Average Selling Price (ASP) | D14: Deliveries (Mnt) | E14: Revenue (Rs Cr) | F14: ASP(Rs/Tonne)
B15: 2025-26 | D15: 31.97 | E15: 232140 | F15: =E15/D15*1 -> 7261.1824
B16: 2024-25 | D16: 30.96 | E16: 218543 | F16: =E16/D16*1 -> 7058.8824
B17: 2023-24 | D17: 29.39 | E17: 229170.78 | F17: =E17/D17*1 -> 7797.5767
B18: 2022-23 | D18: 28.79 | E18: 206922.86 | F18: =E18/D18*1 -> 7187.3171
B20: Historical Drivers | D20: 2023A | E20: 2024A | F20: 2025A | G20: 2026A | H20: 2027F | I20: 2028F | J20: 2029F | K20: 2030F | L20: 2031F
B21: Sales Volume | D21: =D7 -> 28.79 | E21: =D6 -> 29.39 | F21: =D5 -> 30.96 | G21: =D4 -> 31.97 | H21: =G21*(1+H22) -> 33.40865 | I21: =H21*(1+I22) -> 35.1459 | J21: =I21*(1+J22) -> 36.727465 | K21: =J21*(1+K22) -> 38.196564 | L21: =K21*(1+L22) -> 39.724426
B22: Volume Growth | D22: 0 | E22: =E21/D21-1 -> 0.02084057 | F22: =F21/E21-1 -> 0.05341953 | G22: =G21/F21-1 -> 0.032622739 | H22: =Inputs!D11 -> 0.045 | I22: =Inputs!E11 -> 0.052 | J22: =Inputs!F11 -> 0.045 | K22: =Inputs!G11 -> 0.04 | L22: =Inputs!H11 -> 0.04
B23: Average Selling Price | D23: =F18 -> 7187.3171 | E23: =F17 -> 7797.5767 | F23: =F16 -> 7058.8824 | G23: =F15 -> 7261.1824 | H23: =G23*(1+H24) -> 7370.1001 | I23: =H23*(1+I24) -> 7443.8011 | J23: =I23*(1+J24) -> 7533.1267 | K23: =J23*(1+K24) -> 7608.458 | L23: =K23*(1+L24) -> 7707.3679
B24: Average Selling Price Growth | D24: 0 | E24: =E23/D23-1 -> 0.084907844 | F24: =F23/E23-1 -> -0.094733829 | G24: =G23/F23-1 -> 0.028658918 | H24: =Inputs!D19 -> 0.015 | I24: =Inputs!E19 -> 0.01 | J24: =Inputs!F19 -> 0.012 | K24: =Inputs!G19 -> 0.01 | L24: =Inputs!H19 -> 0.013
B26: Revenue | D26: =D21*D23 -> 206922.86 | E26: =E21*E23 -> 229170.78 | F26: =F21*F23 -> 218543 | G26: =G21*G23 -> 232140 | H26: =H21*H23 -> 246225.09 | I26: =I21*I23 -> 261619.09 | J26: =J21*J23 -> 276672.65 | K26: =K21*K23 -> 290616.95 | L26: =L21*L23 -> 306170.77
B28: Assumptions
B29: Volume Growth:Based on historical sales CAGR, capacity additions, and demand outlook.
B30: ASP Growth:Based on normalized long-term steel pricing and inflation.
B33: Costs Driver
B34: (In Cr)
B35: Manufacturing Cost Drivers | D35: 2023A | E35: 2024A | F35: 2025A | G35: 2026A | H35: 2027F | I35: 2028F | J35: 2029F | K35: 2030F | L35: 2031F
B36: Revenue | D36: =D26 -> 206922.86 | E36: =E26 -> 229170.78 | F36: =F26 -> 218543 | G36: =G26 -> 232140 | H36: =H26 -> 246225.09 | I36: =I26 -> 261619.09 | J36: =J26 -> 276672.65 | K36: =K26 -> 290616.95 | L36: =L26 -> 306170.77
B38: Material Cost (% Revenue) | D38: 0.4787 | E38: 0.3602 | F38: 0.3526 | G38: 0.3208 | H38: =Inputs!D27 -> 0.612 | I38: =Inputs!E27 -> 0.61 | J38: =Inputs!F27 -> 0.608 | K38: =Inputs!G27 -> 0.606 | L38: =Inputs!H27 -> 0.605
B39: Manufacturing OH (% Revenue) | D39: 0.1226 | E39: 0.138 | F39: 0.142 | G39: 0.1402 | H39: 0.139 | I39: 0.138 | J39: 0.137 | K39: 0.136 | L39: 0.135
B40: Power & Fuel (% Revenue) | D40: 0.0333 | E40: 0.044 | F40: 0.0391 | G40: 0.0622 | H40: 0.061 | I40: 0.06 | J40: 0.059 | K40: 0.058 | L40: 0.057
B41: Mining Cost (% Revenue) | D41: 0.0284 | E41: 0.0296 | F41: 0.0244 | G41: 0.0245 | H41: 0.024 | I41: 0.024 | J41: 0.023 | K41: 0.023 | L41: 0.022
B42: Freight & Logistics (% Revenue) | D42: 0.0519 | E42: 0.0564 | F42: 0.0625 | G42: 0.0601 | H42: 0.06 | I42: 0.059 | J42: 0.058 | K42: 0.057 | L42: 0.056
B43: Total Manufacturing Cost (% Revenue) | D43: 0.7149 | E43: 0.6282 | F43: 0.6206 | G43: 0.6078 | H43: 0.599 | I43: 0.593 | J43: 0.587 | K43: 0.582 | L43: 0.575
B45: Assumptions
B46: Material Cost: Forecast to decline gradually due to procurement efficiencies and improved raw material sourcing.
B47: Manufacturing Overheads: Forecast to improve marginally with better operational efficiency and higher capacity utilization.
B48: Power & Fuel: Assumed to remain broadly stable, supported by operational efficiencies and normalized energy costs.
B49: Mining Cost: Forecast to remain stable, reflecting captive mining operations and a consistent royalty structure.
B50: Freight & Logistics: Expected to improve gradually through logistics optimization and supply chain efficiencies.
B52: (In Cr)
B53: Operating Expense Drivers | D53: 2023A | E53: 2024A | F53: 2025A | G53: 2026A | H53: 2027F | I53: 2028F | J53: 2029F | K53: 2030F | L53: 2031F
B55: Employee Benefits (% Revenue) | D55: 0.0921 | E55: 0.1071 | F55: 0.1139 | G55: 0.112 | H55: 0.111 | I55: 0.11 | J55: 0.109 | K55: 0.108 | L55: 0.107
B56: Other Operating Expenses (% Revenue) | D56: 0.0365 | E56: 0.0469 | F56: 0.0491 | G56: 0.0597 | H56: =Inputs!D34 -> 0.063 | I56: =Inputs!E34 -> 0.062 | J56: =Inputs!F34 -> 0.061 | K56: =Inputs!G34 -> 0.06 | L56: =Inputs!H34 -> 0.059
B57: Total Operating Expenses (% Revenue) | D57: 0.1286 | E57: 0.154 | F57: 0.163 | G57: 0.1717 | H57: 0.169 | I57: 0.167 | J57: 0.165 | K57: 0.163 | L57: 0.161
B59: Assumptions
B60: Employee Benefits: Forecast to decline marginally as a percentage of revenue, driven by productivity improvements and operating leverage.
B61: Corporate & Administrative Expenses: Forecast to improve gradually through disciplined cost management and administrative efficiencies.
B64: Plant, Property and Equipment Schedule
B65: (In Cr)
B66: Plant, Property and Equipment Schedule | D66: 2023A | E66: 2024A | F66: 2025A | G66: 2026A | H66: 2027F | I66: 2028F | J66: 2029F | K66: 2030F | L66: 2031F
B68: Opening Net PPE | D68: 116166.46 | E68: =D71 -> 120646.05 | F68: =E71 -> 128495.09 | G68: =F71 -> 133744.28 | H68: =G71 -> 135815.52 | I68: =H71 -> 139262.67 | J68: =I71 -> 142532.91 | K68: =J71 -> 145576.31 | L68: =K71 -> 148337.17
B69: Capital Expenditure | D69: =14142.49-327.7 -> 13814.79 | E69: =18206.6-475.4 -> 17731.2 | F69: 15670.52 | G69: =14559.05-533.3 -> 14025.75 | H69: =H72*H36 -> 16497.081 | I69: =I72*I36 -> 17266.86 | J69: =J72*J36 -> 17983.722 | K69: =K72*K36 -> 18599.485 | L69: =L72*L36 -> 19288.759
B70: Depreciation & Amortization | D70: 9335.2 | E70: =9882.16 -> 9882.16 | F70: 10421.33 | G70: 11954.51 | H70: =H73*H36 -> 13049.93 | I70: =I73*I36 -> 13996.621 | J70: =J73*J36 -> 14940.323 | K70: =K73*K36 -> 15838.624 | L70: =L73*L36 -> 16839.392
B71: Closing Net PPE | D71: =D68+D69-D70 -> 120646.05 | E71: =E68+E69-E70 -> 128495.09 | F71: =F68+F69-F70 -> 133744.28 | G71: =G68+G69-G70 -> 135815.52 | H71: =H68+H69-H70 -> 139262.67 | I71: =I68+I69-I70 -> 142532.91 | J71: =J68+J69-J70 -> 145576.31 | K71: =K68+K69-K70 -> 148337.17 | L71: =L68+L69-L70 -> 150786.54
B72: Capex (% Revenue) | D72: =D69/D36 -> 0.066762996 | E72: =E69/E36 -> 0.07737112 | F72: =F69/F36 -> 0.071704516 | G72: =G69/G36 -> 0.060419359 | H72: =Inputs!D41 -> 0.067 | I72: =Inputs!E41 -> 0.066 | J72: =Inputs!F41 -> 0.065 | K72: =Inputs!G41 -> 0.064 | L72: =Inputs!H41 -> 0.063
B73: Depreciation & Amortization (%Revenue) | D73: =D70/D36 -> 0.045114397 | E73: =E70/E36 -> 0.043121379 | F73: =F70/F36 -> 0.04768549 | G73: =G70/G36 -> 0.051496985 | H73: =Inputs!D48 -> 0.053 | I73: =Inputs!E48 -> 0.0535 | J73: =Inputs!F48 -> 0.054 | K73: =Inputs!G48 -> 0.0545 | L73: =Inputs!H48 -> 0.055
B75: Assumptions | C75: x
B76: Net capital expenditure is forecast as a percentage of revenue, reflecting maintenance requirements and planned capacity expansion.
B77: Depreciation is projected using a stable depreciation rate on opening net PPE based on historical asset utilization.
B80: Working Capital Schedule
B81: (In Cr)
B82: Working Capital Schedule | D82: 2023A | E82: 2024A | F82: 2025A | G82: 2026A | H82: 2027F | I82: 2028F | J82: 2029F | K82: 2030F | L82: 2031F
B84: Revenue | D84: =D36 -> 206922.86 | E84: =E36 -> 229170.78 | F84: =F36 -> 218543 | G84: =G36 -> 232140 | H84: =H36 -> 246225.09 | I84: =I36 -> 261619.09 | J84: =J36 -> 276672.65 | K84: =K36 -> 290616.95 | L84: =L36 -> 306170.77
B85: COGS | D85: =D43*D36 -> 147929.15 | E85: =E43*E36 -> 143965.08 | F85: =F43*F36 -> 135627.79 | G85: =G43*G36 -> 141094.69 | H85: =H43*H36 -> 147488.83 | I85: =I43*I36 -> 155140.12 | J85: =J43*J36 -> 162406.85 | K85: =K43*K36 -> 169139.07 | L85: =L43*L36 -> 176048.19
B86: Trade Recievables | D86: 8257.24 | E86: 6263.53 | F86: 5260.06 | G86: 4916.89 | H86: =H94/365*H84 -> 6745.893 | I86: =I94/365*I84 -> 7167.6462 | J86: =J94/365*J84 -> 7580.0726 | K86: =K94/365*K84 -> 7962.1083 | L86: =L94/365*L84 -> 8388.2403
B87: Inventory | D87: 54415.33 | E87: 49157.51 | F87: 44589.94 | G87: 47249.22 | H87: =H95/365*H85 -> 50509.874 | I87: =I95/365*I85 -> 53130.178 | J87: =J95/365*J85 -> 56063.733 | K87: =K95/365*K85 -> 58387.732 | L87: =L95/365*L85 -> 61255.125
B88: Trade Payables | D88: 37832.54 | E88: 35434.66 | F88: 29314.38 | G88: 34810.14 | H88: =H96/365*H85 -> 35558.951 | I88: =I96/365*I85 -> 37403.645 | J88: =J96/365*J85 -> 38710.673 | K88: =K96/365*K85 -> 40315.339 | L88: =L96/365*L85 -> 41479.848
B89: Net Working Capital | D89: =D86+D87-D88 -> 24840.03 | E89: =E86+E87-E88 -> 19986.38 | F89: =F86+F87-F88 -> 20535.62 | G89: =G86+G87-G88 -> 17355.97 | H89: =H86+H87-H88 -> 21696.816 | I89: =I86+I87-I88 -> 22894.179 | J89: =J86+J87-J88 -> 24933.133 | K89: =K86+K87-K88 -> 26034.502 | L89: =L86+L87-L88 -> 28163.517
B90: Change in NWC | D90: - | E90: =E89-D89 -> -4853.65 | F90: =F89-E89 -> 549.24 | G90: =G89-F89 -> -3179.65 | H90: =H89-G89 -> 4340.8457 | I90: =I89-H89 -> 1197.3632 | J90: =J89-I89 -> 2038.954 | K90: =K89-J89 -> 1101.3688 | L90: =L89-K89 -> 2129.0152
B92: Working Capital Days | D92: 2023A | E92: 2024A | F92: 2025A | G92: 2026A | H92: 2027F | I92: 2028F | J92: 2029F | K92: 2030F | L92: 2031F
B94: Receivable Days | D94: =D86/D84*365 -> 14.565295 | E94: =E86/E84*365 -> 9.975916 | F94: =F86/F84*365 -> 8.785099 | G94: =G86/G84*365 -> 7.7309591 | H94: =Inputs!D55 -> 10 | I94: =Inputs!E55 -> 10 | J94: =Inputs!F55 -> 10 | K94: =Inputs!G55 -> 10 | L94: =Inputs!H55 -> 10
B95: Inventory Days | D95: =D87/D85*365 -> 134.26424 | E95: =E87/E85*365 -> 124.63085 | F95: =F87/F85*365 -> 119.99995 | G95: =G87/G85*365 -> 122.22972 | H95: =Inputs!D62 -> 125 | I95: =Inputs!E62 -> 125 | J95: =Inputs!F62 -> 126 | K95: =Inputs!G62 -> 126 | L95: =Inputs!H62 -> 127
B96: Payable Days | D96: =D88/D85*365 -> 93.347909 | E96: =E88/E85*365 -> 89.838804 | F96: =F88/F85*365 -> 78.890536 | G96: =G88/G85*365 -> 90.050879 | H96: =Inputs!D69 -> 88 | I96: =Inputs!E69 -> 88 | J96: =Inputs!F69 -> 87 | K96: =Inputs!G69 -> 87 | L96: =Inputs!H69 -> 86
B98: Assumptions
B99: Receivable days are assumed to remain stable, reflecting efficient customer collections and consistent credit policies.
B100: Inventory days are projected to improve gradually through better inventory management and production planning.
B101: Payable days are forecast to remain broadly stable, supported by strong supplier relationships and disciplined procurement practices.
B102: Net working capital is forecast using historical operating cycles and is expected to remain efficiently managed over the forecast period.
B105: Debt Schedule
B106: (In Cr)
B107: Debt Schedule | D107: 2023A | E107: 2024A | F107: 2025A | G107: 2026A | H107: 2027F | I107: 2028F | J107: 2029F | K107: 2030F | L107: 2031F
B109: Opening Debt | D109: =68828.68 -> 68828.68 | E109: =D110 -> 78017.7 | F109: =E110 -> 75817.19 | G109: =F110 -> 88963.81 | H109: =G110 -> 84956.39 | I109: =H110 -> 83257.26 | J109: =I110 -> 81592.11 | K109: =J110 -> 80776.19 | L109: =K110 -> 79968.43
B110: Closing Debt | D110: =51446.33+26571.37 -> 78017.7 | E110: =45820+29997.19 -> 75817.19 | F110: =68551.81+20412 -> 88963.81 | G110: =63753.67+21202.72 -> 84956.39 | H110: 83257.26 | I110: 81592.11 | J110: 80776.19 | K110: 79968.43 | L110: 79968.43
B111: Average Debt | D111: =AVERAGE(D109:D110) -> 73423.19 | E111: =AVERAGE(E109:E110) -> 76917.445 | F111: =AVERAGE(F109:F110) -> 82390.5 | G111: =AVERAGE(G109:G110) -> 86960.1 | H111: =AVERAGE(H109:H110) -> 84106.825 | I111: =AVERAGE(I109:I110) -> 82424.685 | J111: =AVERAGE(J109:J110) -> 81184.15 | K111: =AVERAGE(K109:K110) -> 80372.31 | L111: =AVERAGE(L109:L110) -> 79968.43
B112: Finance Cost | D112: 6298.7 | E112: 7507.57 | F112: 7340.95 | G112: 7167.06 | H112: =H113*H111 -> 6896.7596 | I112: =I113*I111 -> 6676.3995 | J112: =J113*J111 -> 6494.732 | K112: =K113*K111 -> 6429.7848 | L112: =L113*L111 -> 6397.4744
B113: Cost of Debt % | D113: =D112/D111 -> 0.085786248 | E113: =E112/E111 -> 0.097605556 | F113: =F112/F111 -> 0.089099471 | G113: =G112/G111 -> 0.082417799 | H113: 0.082 | I113: 0.081 | J113: 0.08 | K113: 0.08 | L113: 0.08
B115: Assumptions
B116: Closing debt is forecast to decline gradually, reflecting the company's deleveraging strategy and healthy cash flow generation.
B117: Cost of debt is projected to decline marginally, reflecting an improving debt profile and stable borrowing conditions.
B118: Interest expense is calculated using the average debt balance and the estimated cost of debt.

Sheet Forecasted Cash Flow 
B1: Forecasted Cash Flow
B2: In Cr
B3: Forecasted Cash Flow | D3: 2023A | E3: 2024A | F3: 2025A | G3: 2026A | H3: 2027F | I3: 2028F | J3: 2029F | K3: 2030F | L3: 2031F
B5: Cash Flow from Operating Activities
B6: Profit After Tax | D6: ='Forecasted Income Statement '!D16 -> 11724.669 | E6: ='Forecasted Income Statement '!E16 -> 22766.566 | F6: ='Forecasted Income Statement '!F16 -> 20671.298 | G6: ='Forecasted Income Statement '!G16 -> 22445.71 | H6: ='Forecasted Income Statement '!H16 -> 25162.485 | I6: ='Forecasted Income Statement '!I16 -> 28565.225 | J6: ='Forecasted Income Statement '!J16 -> 32057.479 | K6: ='Forecasted Income Statement '!K16 -> 35270.08 | L6: ='Forecasted Income Statement '!L16 -> 39242.954
B7: Add: Depreciation & Amortization | D7: ='Assumption and Drivers'!D70 -> 9335.2 | E7: ='Assumption and Drivers'!E70 -> 9882.16 | F7: ='Assumption and Drivers'!F70 -> 10421.33 | G7: ='Assumption and Drivers'!G70 -> 11954.51 | H7: ='Assumption and Drivers'!H70 -> 13049.93 | I7: ='Assumption and Drivers'!I70 -> 13996.621 | J7: ='Assumption and Drivers'!J70 -> 14940.323 | K7: ='Assumption and Drivers'!K70 -> 15838.624 | L7: ='Assumption and Drivers'!L70 -> 16839.392
B8: Add/Less: Working Capital | E8: ='Assumption and Drivers'!E90 -> -4853.65 | F8: ='Assumption and Drivers'!F90 -> 549.24 | G8: ='Assumption and Drivers'!G90 -> -3179.65 | H8: ='Assumption and Drivers'!H90 -> 4340.8457 | I8: ='Assumption and Drivers'!I90 -> 1197.3632 | J8: ='Assumption and Drivers'!J90 -> 2038.954 | K8: ='Assumption and Drivers'!K90 -> 1101.3688 | L8: ='Assumption and Drivers'!L90 -> 2129.0152
B9: Cash from Operations (CFO) | E9: =E6+E7-E8 -> 37502.376 | F9: =F6+F7-F8 -> 30543.388 | G9: =G6+G7-G8 -> 37579.87 | H9: =H6+H7-H8 -> 33871.569 | I9: =I6+I7-I8 -> 41364.483 | J9: =J6+J7-J8 -> 44958.848 | K9: =K6+K7-K8 -> 50007.335 | L9: =L6+L7-L8 -> 53953.331
B11: Cash Flow from Investing Activities
B12: Capital Expenditure | D12: ='Assumption and Drivers'!D69 -> 13814.79 | E12: ='Assumption and Drivers'!E69 -> 17731.2 | F12: ='Assumption and Drivers'!F69 -> 15670.52 | G12: ='Assumption and Drivers'!G69 -> 14025.75 | H12: ='Assumption and Drivers'!H69 -> 16497.081 | I12: ='Assumption and Drivers'!I69 -> 17266.86 | J12: ='Assumption and Drivers'!J69 -> 17983.722 | K12: ='Assumption and Drivers'!K69 -> 18599.485 | L12: ='Assumption and Drivers'!L69 -> 19288.759
B13: Cash from Investing (CFI) | D13: =SUM(D12)*-1 -> -13814.79 | E13: =SUM(E12)*-1 -> -17731.2 | F13: =SUM(F12)*-1 -> -15670.52 | G13: =SUM(G12)*-1 -> -14025.75 | H13: =SUM(H12)*-1 -> -16497.081 | I13: =SUM(I12)*-1 -> -17266.86 | J13: =SUM(J12)*-1 -> -17983.722 | K13: =SUM(K12)*-1 -> -18599.485 | L13: =SUM(L12)*-1 -> -19288.759
B15: Cash Flow from Financing Activities
B16: Net Borrowing/(Repayment) | D16: ='Assumption and Drivers'!D110-'Assumption and Drivers'!D109 -> 9189.02 | E16: ='Assumption and Drivers'!E110-'Assumption and Drivers'!E109 -> -2200.51 | F16: ='Assumption and Drivers'!F110-'Assumption and Drivers'!F109 -> 13146.62 | G16: ='Assumption and Drivers'!G110-'Assumption and Drivers'!G109 -> -4007.42 | H16: ='Assumption and Drivers'!H110-'Assumption and Drivers'!H109 -> -1699.13 | I16: ='Assumption and Drivers'!I110-'Assumption and Drivers'!I109 -> -1665.15 | J16: ='Assumption and Drivers'!J110-'Assumption and Drivers'!J109 -> -815.92 | K16: ='Assumption and Drivers'!K110-'Assumption and Drivers'!K109 -> -807.76 | L16: ='Assumption and Drivers'!L110-'Assumption and Drivers'!L109 -> 0
B17: Cash from Financing (CFF) | D17: =SUM(D16) -> 9189.02 | E17: =SUM(E16) -> -2200.51 | F17: =SUM(F16) -> 13146.62 | G17: =SUM(G16) -> -4007.42 | H17: =SUM(H16) -> -1699.13 | I17: =SUM(I16) -> -1665.15 | J17: =SUM(J16) -> -815.92 | K17: =SUM(K16) -> -807.76 | L17: =SUM(L16) -> 0
B19: Net Change in Cash | D19: =D17+D13+D9 -> -4625.77 | E19: =E17+E13+E9 -> 17570.666 | F19: =F17+F13+F9 -> 28019.488 | G19: =G17+G13+G9 -> 19546.7 | H19: =H17+H13+H9 -> 15675.358 | I19: =I17+I13+I9 -> 22432.474 | J19: =J17+J13+J9 -> 26159.206 | K19: =K17+K13+K9 -> 30600.091 | L19: =L17+L13+L9 -> 34664.573
B20: Opening Cash | D20: 17983.03 | E20: 13357.26 | F20: 8677.72 | G20: 11646.98 | H20: =G21 -> 10057.53 | I20: =H21 -> 25732.888 | J20: =I21 -> 48165.361 | K20: =J21 -> 74324.567 | L20: =K21 -> 104924.66
B21: Closing Cash | D21: =D19+D20 -> 13357.26 | E21: 8677.72 | F21: 11646.98 | G21: 10057.53 | H21: =H20+H19 -> 25732.888 | I21: =I20+I19 -> 48165.361 | J21: =J20+J19 -> 74324.567 | K21: =K20+K19 -> 104924.66 | L21: =L20+L19 -> 139589.23

Sheet Forcasted Balance Sheet 
B1: Forecasted Balance Sheet
B2: In Cr
B3: Forecasted Balance Sheet | D3: 2023A | E3: 2024A | F3: 2025A | G3: 2026A | H3: 2027F | I3: 2028F | J3: 2029F | K3: 2030F | L3: 2031F
B5: Cash and Cash Equivalent | D5: =D27-SUM(D6:D8,D11:D14) -> 7098.44 | E5: =E27-SUM(E6:E8,E11:E14) -> -12320.74 | F5: =F27-SUM(F6:F8,F11:F14) -> -8791.68 | G5: =G27-SUM(G6:G8,G11:G14) -> -2070.09 | H5: =H27-SUM(H6:H8,H11:H14) -> 13605.268 | I5: =I27-SUM(I6:I8,I11:I14) -> 36037.741 | J5: =J27-SUM(J6:J8,J11:J14) -> 62196.947 | K5: =K27-SUM(K6:K8,K11:K14) -> 92797.038 | L5: =L27-SUM(L6:L8,L11:L14) -> 127461.61
B6: Trade Recievables | D6: ='Assumption and Drivers'!D86 -> 8257.24 | E6: ='Assumption and Drivers'!E86 -> 6263.53 | F6: ='Assumption and Drivers'!F86 -> 5260.06 | G6: ='Assumption and Drivers'!G86 -> 4916.89 | H6: ='Assumption and Drivers'!H86 -> 6745.893 | I6: ='Assumption and Drivers'!I86 -> 7167.6462 | J6: ='Assumption and Drivers'!J86 -> 7580.0726 | K6: ='Assumption and Drivers'!K86 -> 7962.1083 | L6: ='Assumption and Drivers'!L86 -> 8388.2403
B7: Inventory | D7: ='Assumption and Drivers'!D87 -> 54415.33 | E7: ='Assumption and Drivers'!E87 -> 49157.51 | F7: ='Assumption and Drivers'!F87 -> 44589.94 | G7: ='Assumption and Drivers'!G87 -> 47249.22 | H7: ='Assumption and Drivers'!H87 -> 50509.874 | I7: ='Assumption and Drivers'!I87 -> 53130.178 | J7: ='Assumption and Drivers'!J87 -> 56063.733 | K7: ='Assumption and Drivers'!K87 -> 58387.732 | L7: ='Assumption and Drivers'!L87 -> 61255.125
B8: Other Current Assets | D8: 4829.75 | E8: 4218.41 | F8: 4538.44 | G8: 5600.33 | H8: =G8 -> 5600.33 | I8: =H8 -> 5600.33 | J8: =I8 -> 5600.33 | K8: =J8 -> 5600.33 | L8: =K8 -> 5600.33
B9: Total Current Assets | D9: =SUM(D5:D8) -> 74600.76 | E9: =SUM(E5:E8) -> 47318.71 | F9: =SUM(F5:F8) -> 45596.76 | G9: =SUM(G5:G8) -> 55696.35 | H9: =SUM(H5:H8) -> 76461.365 | I9: =SUM(I5:I8) -> 101935.9 | J9: =SUM(J5:J8) -> 131441.08 | K9: =SUM(K5:K8) -> 164747.21 | L9: =SUM(L5:L8) -> 202705.31
B11: Net PP&E | D11: ='Assumption and Drivers'!D71 -> 120646.05 | E11: ='Assumption and Drivers'!E71 -> 128495.09 | F11: ='Assumption and Drivers'!F71 -> 133744.28 | G11: ='Assumption and Drivers'!G71 -> 135815.52 | H11: ='Assumption and Drivers'!H71 -> 139262.67 | I11: ='Assumption and Drivers'!I71 -> 142532.91 | J11: ='Assumption and Drivers'!J71 -> 145576.31 | K11: ='Assumption and Drivers'!K71 -> 148337.17 | L11: ='Assumption and Drivers'!L71 -> 150786.54
B12: Goodwill | D12: 5601.65 | E12: 5745.3 | F12: 5958.53 | G12: 7533.8 | H12: =G12 -> 7533.8 | I12: =H12 -> 7533.8 | J12: =I12 -> 7533.8 | K12: =J12 -> 7533.8 | L12: =K12 -> 7533.8
B13: investments | D13: 1546.92 | E13: 2579.19 | F13: 2780.6 | G13: 3141.84 | H13: =G13 -> 3141.84 | I13: =H13 -> 3141.84 | J13: =I13 -> 3141.84 | K13: =J13 -> 3141.84 | L13: =K13 -> 3141.84
B14: Other Non Current Assets | D14: =E14 -> 37642.44 | E14: =F14 -> 37642.44 | F14: =G14 -> 37642.44 | G14: 37642.44 | H14: =G14 -> 37642.44 | I14: =H14 -> 37642.44 | J14: =I14 -> 37642.44 | K14: =J14 -> 37642.44 | L14: =K14 -> 37642.44
B15: Total assets | D15: =SUM(D9:D14) -> 240037.82 | E15: =SUM(E9:E14) -> 221780.73 | F15: =SUM(F9:F14) -> 225722.61 | G15: =SUM(G9:G14) -> 239829.95 | H15: =SUM(H9:H14) -> 264042.12 | I15: =SUM(I9:I14) -> 292786.89 | J15: =SUM(J9:J14) -> 325335.47 | K15: =SUM(K9:K14) -> 361402.46 | L15: =SUM(L9:L14) -> 401809.92
B17: Share Capital | D17: ='Balance Sheet'!H4 -> 1221.24 | E17: ='Balance Sheet'!I4 -> 1247.44 | F17: ='Balance Sheet'!J4 -> 1247.44 | G17: ='Balance Sheet'!K4 -> 1247.44 | H17: =G17 -> 1247.44 | I17: =H17 -> 1247.44 | J17: =I17 -> 1247.44 | K17: =J17 -> 1247.44 | L17: =K17 -> 1247.44
B18: Other Equity | D18: 101860.86 | E18: 90788.32 | F18: 89922.19 | G18: 100920.21 | H18: =G18+'Forecasted Income Statement '!H16 -> 126082.69 | I18: =H18+'Forecasted Income Statement '!I16 -> 154647.92 | J18: =I18+'Forecasted Income Statement '!J16 -> 186705.4 | K18: =J18+'Forecasted Income Statement '!K16 -> 221975.48 | L18: =K18+'Forecasted Income Statement '!L16 -> 261218.43
B19: Equity attributable to owners | D19: =SUM(D17:D18) -> 103082.1 | E19: =SUM(E17:E18) -> 92035.76 | F19: =SUM(F17:F18) -> 91169.63 | G19: =SUM(G17:G18) -> 102167.65 | H19: =SUM(H17:H18) -> 127330.13 | I19: =SUM(I17:I18) -> 155895.36 | J19: =SUM(J17:J18) -> 187952.84 | K19: =SUM(K17:K18) -> 223222.92 | L19: =SUM(L17:L18) -> 262465.87
B20: Non-controlling Interest | D20: 2093.11 | E20: 396.98 | F20: 183.15 | G20: 1612.8 | H20: =G20 -> 1612.8 | I20: =H20 -> 1612.8 | J20: =I20 -> 1612.8 | K20: =J20 -> 1612.8 | L20: =K20 -> 1612.8
B21: Total Equity | D21: =D17+D18+D20 -> 105175.21 | E21: =E17+E18+E20 -> 92432.74 | F21: =F17+F18+F20 -> 91352.78 | G21: =G17+G18+G20 -> 103780.45 | H21: =H17+H18+H20 -> 128942.93 | I21: =I17+I18+I20 -> 157508.16 | J21: =J17+J18+J20 -> 189565.64 | K21: =K17+K18+K20 -> 224835.72 | L21: =L17+L18+L20 -> 264078.67
B23: Trade Payables | D23: ='Assumption and Drivers'!D88 -> 37832.54 | E23: ='Assumption and Drivers'!E88 -> 35434.66 | F23: ='Assumption and Drivers'!F88 -> 29314.38 | G23: ='Assumption and Drivers'!G88 -> 34810.14 | H23: ='Assumption and Drivers'!H88 -> 35558.951 | I23: ='Assumption and Drivers'!I88 -> 37403.645 | J23: ='Assumption and Drivers'!J88 -> 38710.673 | K23: ='Assumption and Drivers'!K88 -> 40315.339 | L23: ='Assumption and Drivers'!L88 -> 41479.848
B24: Other Current Liabilites | D24: 14545.1 | E24: 15185.73 | F24: 13301.81 | G24: 13186.3 | H24: =G24 -> 13186.3 | I24: =H24 -> 13186.3 | J24: =I24 -> 13186.3 | K24: =J24 -> 13186.3 | L24: =K24 -> 13186.3
B25: Total Debt | D25: ='Assumption and Drivers'!D110 -> 78017.7 | E25: ='Assumption and Drivers'!E110 -> 75817.19 | F25: ='Assumption and Drivers'!F110 -> 88963.81 | G25: ='Assumption and Drivers'!G110 -> 84956.39 | H25: ='Assumption and Drivers'!H110 -> 83257.26 | I25: ='Assumption and Drivers'!I110 -> 81592.11 | J25: ='Assumption and Drivers'!J110 -> 80776.19 | K25: ='Assumption and Drivers'!K110 -> 79968.43 | L25: ='Assumption and Drivers'!L110 -> 79968.43
B26: Other Non Current Liabilites | D26: 4467.27 | E26: 2910.41 | F26: 2789.83 | G26: 3096.67 | H26: =G26 -> 3096.67 | I26: =H26 -> 3096.67 | J26: =I26 -> 3096.67 | K26: =J26 -> 3096.67 | L26: =K26 -> 3096.67
B27: Equity and Total Liabilties | D27: =SUM(D21:D26) -> 240037.82 | E27: =SUM(E21:E26) -> 221780.73 | F27: =SUM(F21:F26) -> 225722.61 | G27: =SUM(G21:G26) -> 239829.95 | H27: =SUM(H21:H26) -> 264042.12 | I27: =SUM(I21:I26) -> 292786.89 | J27: =SUM(J21:J26) -> 325335.47 | K27: =SUM(K21:K26) -> 361402.46 | L27: =SUM(L21:L26) -> 401809.92
B29: Balance Check | D29: =D15-D27 -> 0 | E29: =E15-E27 -> 0 | F29: =F15-F27 -> 0 | G29: =G15-G27 -> 0 | H29: =H15-H27 -> 0 | I29: =I15-I27 -> 0 | J29: =J15-J27 -> 0 | K29: =K15-K27 -> 0 | L29: =L15-L27 -> 0

Sheet Forecasted Income Statement 
B1: Forecasted Income Statement
B2: (In Cr)
B3: Forecasted Income Statement | D3: 2023A | E3: 2024A | F3: 2025A | G3: 2026A | H3: 2027F | I3: 2028F | J3: 2029F | K3: 2030F | L3: 2031F
B5: Revenue | D5: ='Assumption and Drivers'!D26 -> 206922.86 | E5: ='Assumption and Drivers'!E26 -> 229170.78 | F5: ='Assumption and Drivers'!F26 -> 218543 | G5: ='Assumption and Drivers'!G26 -> 232140 | H5: ='Assumption and Drivers'!H26 -> 246225.09 | I5: ='Assumption and Drivers'!I26 -> 261619.09 | J5: ='Assumption and Drivers'!J26 -> 276672.65 | K5: ='Assumption and Drivers'!K26 -> 290616.95 | L5: ='Assumption and Drivers'!L26 -> 306170.77
B6: Manufacturing Cost (COGS) | D6: ='Assumption and Drivers'!D43*'Assumption and Drivers'!D36 -> 147929.15 | E6: ='Assumption and Drivers'!E43*'Assumption and Drivers'!E36 -> 143965.08 | F6: ='Assumption and Drivers'!F43*'Assumption and Drivers'!F36 -> 135627.79 | G6: ='Assumption and Drivers'!G43*'Assumption and Drivers'!G36 -> 141094.69 | H6: ='Assumption and Drivers'!H43*'Assumption and Drivers'!H36 -> 147488.83 | I6: ='Assumption and Drivers'!I43*'Assumption and Drivers'!I36 -> 155140.12 | J6: ='Assumption and Drivers'!J43*'Assumption and Drivers'!J36 -> 162406.85 | K6: ='Assumption and Drivers'!K43*'Assumption and Drivers'!K36 -> 169139.07 | L6: ='Assumption and Drivers'!L43*'Assumption and Drivers'!L36 -> 176048.19
B7: Gross Profit | D7: =D5-D6 -> 58993.707 | E7: =E5-E6 -> 85205.696 | F7: =F5-F6 -> 82915.214 | G7: =G5-G6 -> 91045.308 | H7: =H5-H6 -> 98736.263 | I7: =I5-I6 -> 106478.97 | J7: =J5-J6 -> 114265.8 | K7: =K5-K6 -> 121477.89 | L7: =L5-L6 -> 130122.58
B8: Employee Benefits | D8: ='Assumption and Drivers'!D55*'Assumption and Drivers'!D36 -> 19057.595 | E8: ='Assumption and Drivers'!E55*'Assumption and Drivers'!E36 -> 24544.191 | F8: ='Assumption and Drivers'!F55*'Assumption and Drivers'!F36 -> 24892.048 | G8: ='Assumption and Drivers'!G55*'Assumption and Drivers'!G36 -> 25999.68 | H8: ='Assumption and Drivers'!H55*'Assumption and Drivers'!H36 -> 27330.985 | I8: ='Assumption and Drivers'!I55*'Assumption and Drivers'!I36 -> 28778.1 | J8: ='Assumption and Drivers'!J55*'Assumption and Drivers'!J36 -> 30157.319 | K8: ='Assumption and Drivers'!K55*'Assumption and Drivers'!K36 -> 31386.631 | L8: ='Assumption and Drivers'!L55*'Assumption and Drivers'!L36 -> 32760.272
B9: Other Operating Expenses | D9: ='Assumption and Drivers'!D56*'Assumption and Drivers'!D36 -> 7552.6844 | E9: ='Assumption and Drivers'!E56*'Assumption and Drivers'!E36 -> 10748.11 | F9: ='Assumption and Drivers'!F56*'Assumption and Drivers'!F36 -> 10730.461 | G9: ='Assumption and Drivers'!G56*'Assumption and Drivers'!G36 -> 13858.758 | H9: ='Assumption and Drivers'!H56*'Assumption and Drivers'!H36 -> 15512.181 | I9: ='Assumption and Drivers'!I56*'Assumption and Drivers'!I36 -> 16220.383 | J9: ='Assumption and Drivers'!J56*'Assumption and Drivers'!J36 -> 16877.032 | K9: ='Assumption and Drivers'!K56*'Assumption and Drivers'!K36 -> 17437.017 | L9: ='Assumption and Drivers'!L56*'Assumption and Drivers'!L36 -> 18064.075
B10: EBITDA | D10: =D7-D8-D9 -> 32383.428 | E10: =E7-E8-E9 -> 49913.396 | F10: =F7-F8-F9 -> 47292.705 | G10: =G7-G8-G9 -> 51186.87 | H10: =H7-H8-H9 -> 55893.096 | I10: =I7-I8-I9 -> 61480.486 | J10: =J7-J8-J9 -> 67231.454 | K10: =K7-K8-K9 -> 72654.238 | L10: =L7-L8-L9 -> 79298.23
B11: Depreciation & Amortization | D11: ='Assumption and Drivers'!D70 -> 9335.2 | E11: ='Assumption and Drivers'!E70 -> 9882.16 | F11: ='Assumption and Drivers'!F70 -> 10421.33 | G11: ='Assumption and Drivers'!G70 -> 11954.51 | H11: ='Assumption and Drivers'!H70 -> 13049.93 | I11: ='Assumption and Drivers'!I70 -> 13996.621 | J11: ='Assumption and Drivers'!J70 -> 14940.323 | K11: ='Assumption and Drivers'!K70 -> 15838.624 | L11: ='Assumption and Drivers'!L70 -> 16839.392
B12: EBIT | D12: =D10-D11 -> 23048.228 | E12: =E10-E11 -> 40031.236 | F12: =F10-F11 -> 36871.375 | G12: =G10-G11 -> 39232.36 | H12: =H10-H11 -> 42843.166 | I12: =I10-I11 -> 47483.864 | J12: =J10-J11 -> 52291.131 | K12: =K10-K11 -> 56815.614 | L12: =L10-L11 -> 62458.837
B13: Interest Expense | D13: ='Assumption and Drivers'!D112 -> 6298.7 | E13: ='Assumption and Drivers'!E112 -> 7507.57 | F13: ='Assumption and Drivers'!F112 -> 7340.95 | G13: ='Assumption and Drivers'!G112 -> 7167.06 | H13: ='Assumption and Drivers'!H112 -> 6896.7596 | I13: ='Assumption and Drivers'!I112 -> 6676.3995 | J13: ='Assumption and Drivers'!J112 -> 6494.732 | K13: ='Assumption and Drivers'!K112 -> 6429.7848 | L13: ='Assumption and Drivers'!L112 -> 6397.4744
B14: EBT | D14: =D12-D13 -> 16749.528 | E14: =E12-E13 -> 32523.666 | F14: =F12-F13 -> 29530.425 | G14: =G12-G13 -> 32065.3 | H14: =H12-H13 -> 35946.407 | I14: =I12-I13 -> 40807.465 | J14: =J12-J13 -> 45796.399 | K14: =K12-K13 -> 50385.829 | L14: =L12-L13 -> 56061.363
B15: Tax Expense (30%) | D15: =D14*30% -> 5024.8583 | E15: =E14*30% -> 9757.0998 | F15: =F14*30% -> 8859.1276 | G15: =G14*30% -> 9619.59 | H15: =H14*30% -> 10783.922 | I15: =I14*30% -> 12242.239 | J15: =J14*30% -> 13738.92 | K15: =K14*30% -> 15115.749 | L15: =L14*30% -> 16818.409
B16: Profit after Tax (PAT) | D16: =D14-D15 -> 11724.669 | E16: =E14-E15 -> 22766.566 | F16: =F14-F15 -> 20671.298 | G16: =G14-G15 -> 22445.71 | H16: =H14-H15 -> 25162.485 | I16: =I14-I15 -> 28565.225 | J16: =J14-J15 -> 32057.479 | K16: =K14-K15 -> 35270.08 | L16: =L14-L15 -> 39242.954
B18: Growth Margins | D18: 2023A | E18: 2024A | F18: 2025A | G18: 2026A | H18: 2027F | I18: 2028F | J18: 2029F | K18: 2030F | L18: 2031F
B20: Revenue | D20: 0 | E20: =E5/D5-1 -> 0.10751794 | F20: =F5/E5-1 -> -0.046374935 | G20: =G5/F5-1 -> 0.062216589 | H20: =H5/G5-1 -> 0.060675 | I20: =I5/H5-1 -> 0.06252 | J20: =J5/I5-1 -> 0.05754 | K20: =K5/J5-1 -> 0.0504 | L20: =L5/K5-1 -> 0.05352
B21: Manufacturing Cost (COGS) | D21: 0 | E21: =E6/D6-1 -> -0.026797075 | F21: =F6/E6-1 -> -0.057911946 | G21: =G6/F6-1 -> 0.040308158 | H21: =H6/G6-1 -> 0.045318073 | I21: =I6/H6-1 -> 0.051877062 | J21: =J6/I6-1 -> 0.046839764 | K21: =K6/J6-1 -> 0.041452811 | L21: =L6/K6-1 -> 0.040848797
B22: Gross Profit | D22: 0 | E22: =E7/D7-1 -> 0.44431838 | F22: =F7/E7-1 -> -0.026881792 | G22: =G7/F7-1 -> 0.0980531 | H22: =H7/G7-1 -> 0.084473929 | I22: =I7/H7-1 -> 0.078418055 | J22: =J7/I7-1 -> 0.07313027 | K22: =K7/J7-1 -> 0.063116707 | L22: =L7/K7-1 -> 0.071162679
B23: EBITDA | D23: 0 | E23: =E10/D10-1 -> 0.54132529 | F23: =F10/E10-1 -> -0.052504756 | G23: =G10/F10-1 -> 0.082341765 | H23: =H10/G10-1 -> 0.091942063 | I23: =I10/H10-1 -> 0.099965639 | J23: =J10/I10-1 -> 0.093541362 | K23: =K10/J10-1 -> 0.080658436 | L23: =L10/K10-1 -> 0.09144672
B24: EBIT | D24: 0 | E24: =E12/D12-1 -> 0.73684661 | F24: =F12/E12-1 -> -0.078934877 | G24: =G12/F12-1 -> 0.064033001 | H24: =H12/G12-1 -> 0.092036432 | I24: =I12/H12-1 -> 0.10831828 | J24: =J12/I12-1 -> 0.10124 | K24: =K12/J12-1 -> 0.086524868 | L24: =L12/K12-1 -> 0.099325217
B25: EBT | D25: 0 | E25: =E14/D14-1 -> 0.94176616 | F25: =F14/E14-1 -> -0.092032697 | G25: =G14/F14-1 -> 0.085839428 | H25: =H14/G14-1 -> 0.12103759 | I25: =I14/H14-1 -> 0.13523071 | J25: =J14/I14-1 -> 0.12225542 | K25: =K14/J14-1 -> 0.10021378 | L25: =L14/K14-1 -> 0.11264146
B26: Profit after Tax (PAT) | D26: 0 | E26: =E16/D16-1 -> 0.94176616 | F26: =F16/E16-1 -> -0.092032697 | G26: =G16/F16-1 -> 0.085839428 | H26: =H16/G16-1 -> 0.12103759 | I26: =I16/H16-1 -> 0.13523071 | J26: =J16/I16-1 -> 0.12225542 | K26: =K16/J16-1 -> 0.10021378 | L26: =L16/K16-1 -> 0.11264146

Sheet Relative Valuation 
B1: Relative Valuation
C4: Market Data | I4: Financials | M4: Valuation
B5: Company | C5: Share Price | D5: Share Outstanding | E5: Equity Value | F5: Net Debt | G5: Enterpise Value | I5: Revenue | J5: EBIDTA | K5: EBIT | M5: EV/EBIDTA | N5: EV/Revenue | O5: EV/EBIT
B6: Tata steel | C6: 185 | D6: 1247 | E6: =C6*D6 -> 230695 | F6: ='Balance Sheet'!K7-'Data Sheet'!K69 -> 82324.15 | G6: =E6+F6 -> 313019.15 | I6: ='Profit & Loss'!K4 -> 232139.94 | J6: ='Profit & Loss'!K10+'Profit & Loss'!K9+'Profit & Loss'!K8-'Profit & Loss'!K7 -> 34352.44 | K6: 24168 | M6: =G6/J6 -> 9.1119918 | N6: =G6/I6 -> 1.3484071 | O6: =G6/K6 -> 12.951802
B7: JSW Steel | C7: 1289 | D7: 245 | E7: =C7*D7 -> 315805 | F7: =99310-40989 -> 58321 | G7: =E7+F7 -> 374126 | I7: =189687 -> 189687 | J7: =30712 -> 30712 | K7: 16808 | M7: =G7/J7 -> 12.181753 | N7: =G7/I7 -> 1.9723334 | O7: =G7/K7 -> 22.258805
B8: Steel Authority of India (SAIL) | C8: 171 | D8: 413 | E8: =C8*D8 -> 70623 | F8: =31927.71-732.51 -> 31195.2 | G8: =E8+F8 -> 101818.2 | I8: =111134.75 -> 111134.75 | J8: =13319.56 -> 13319.56 | K8: 8151 | M8: =G8/J8 -> 7.6442615 | N8: =G8/I8 -> 0.91616889 | O8: =G8/K8 -> 12.491498
B9: Jindal Steel and Power | C9: 1132 | D9: 102 | E9: =C9*D9 -> 115464 | F9: =22609.55-4141.6 -> 18467.95 | G9: =E9+F9 -> 133931.95 | I9: =56412.57 -> 56412.57 | J9: =9972.62 -> 9972.62 | K9: 9230 | M9: =G9/J9 -> 13.429966 | N9: =G9/I9 -> 2.3741508 | O9: =G9/K9 -> 14.510504
B10: Jindal Stainless | C10: 695 | D10: 82.5 | E10: =C10*D10 -> 57337.5 | F10: =7460.33-2934.03 -> 4526.3 | G10: =E10+F10 -> 61863.8 | I10: =42954.66 -> 42954.66 | J10: =5928.64 -> 5928.64 | K10: =5020 -> 5020 | M10: =G10/J10 -> 10.434737 | N10: =G10/I10 -> 1.4402116 | O10: =G10/K10 -> 12.323466
B12: High | M12: =MAX(M7:M10) -> 13.429966 | N12: =MAX(N7:N10) -> 2.3741508 | O12: =MAX(O7:O10) -> 22.258805
B13: 75th Percentile | M13: =QUARTILE(M7:M10,3) -> 12.493806 | N13: =QUARTILE(N7:N10,3) -> 2.0727877 | O13: =QUARTILE(O7:O10,3) -> 16.447579
B14: Average | M14: =AVERAGE(M7:M10) -> 10.922679 | N14: =AVERAGE(N7:N10) -> 1.6757162 | O14: =AVERAGE(O7:O10) -> 15.396068
B15: Median | M15: =MEDIAN(M7:M10) -> 11.308245 | N15: =MEDIAN(N7:N10) -> 1.7062725 | O15: =MEDIAN(O7:O10) -> 13.501001
B16: 25th Percentile | M16: =QUARTILE(M7:M10,1) -> 9.7371182 | N16: =QUARTILE(N7:N10,1) -> 1.3092009 | O16: =QUARTILE(O7:O10,1) -> 12.44949
B17: Low | M17: =MIN(M7:M10) -> 7.6442615 | N17: =MIN(N7:N10) -> 0.91616889 | O17: =MIN(O7:O10) -> 12.323466
B19: Tata Steel Comparable Valuation | M19: EV/EBIDTA | N19: =N5 -> EV/Revenue | O19: EV/EBIT
B20: Implied Enterprise Value | M20: =$M$15*J6 -> 388465.81 | N20: =$N$15*I6 -> 396093.99 | O20: =O15*K6 -> 326292.19
B21: Net Debt | M21: =$F$6 -> 82324.15 | N21: =$F$6 -> 82324.15 | O21: =$F$6 -> 82324.15
B22: Implied Equity Value | M22: =M20-M21 -> 306141.66 | N22: =N20-N21 -> 313769.84 | O22: =O20-O21 -> 243968.04
B23: Shares Outstanding | M23: =$D$6 -> 1247 | N23: =$D$6 -> 1247 | O23: =$D$6 -> 1247
B25: Implied Value per Share | M25: =M22/M23 -> 245.50254 | N25: =N22/N23 -> 251.61976 | O25: =O22/O23 -> 195.64398
M26: =IF(M25>$C$6,"Undervalued","Overvalued") -> Undervalued | N26: =IF(N25>$C$6,"Undervalued","Overvalued") -> Undervalued | O26: =IF(O25>$C$6,"Undervalued","Overvalued") -> Undervalued

Sheet WACC
B1: Weighted Average Cost of Capital
B3: In Cr
B4: Peer Comps
G5: Debt/ | H5: Debt/ | I5: Levered | J5: Unlevered
B6: Name | C6: Country | D6: Total Debt | E6: Total Equity | F6: Tax Rate 1 | G6: Equity | H6: Capital | I6: Beta 2 | J6: Beta 3
B7: JSW Steel | C7: India | D7: =75608+19924 -> 95532 | E7: =305+99748 -> 100053 | F7: 0.3 | G7: =D7/E7 -> 0.95481395 | H7: =D7/(E7+D7) -> 0.48844237 | I7: 0.58 | J7: =I7/(1+(1-F7)*G7) -> 0.34764476
B8: Steel Authority of India (SAIL) | C8: India | D8: =7219+14450 -> 21669 | E8: =4131+56225 -> 60356 | F8: 0.3 | G8: =D8/E8 -> 0.35901982 | H8: =D8/(E8+D8) -> 0.26417556 | I8: 0.94 | J8: =I8/(1+(1-F8)*G8) -> 0.75121041
B9: Jindal Steel and Power | C9: India | D9: =19595+2443 -> 22038 | E9: =102+50797 -> 50899 | F9: 0.3 | G9: =D9/E9 -> 0.43297511 | H9: =D9/(E9+D9) -> 0.30215117 | I9: 0.61 | J9: =I9/(1+(1-F9)*G9) -> 0.46812076
B10: Jindal Stainless | C10: India | D10: =4936+2406 -> 7342 | E10: =165+19626 -> 19791 | F10: 0.3 | G10: =D10/E10 -> 0.37097671 | H10: =D10/(E10+D10) -> 0.270593 | I10: 1.13 | J10: =I10/(1+(1-F10)*G10) -> 0.89705059
E11: Average | F11: =AVERAGE(F7:F10) -> 0.3 | G11: =AVERAGE(G7:G10) -> 0.52944639 | H11: =AVERAGE(H7:H10) -> 0.33134052 | I11: =AVERAGE(I7:I10) -> 0.815 | J11: =AVERAGE(J7:J10) -> 0.61600663
E12: Median | F12: =MEDIAN(F7:F10) -> 0.3 | G12: =MEDIAN(G7:G10) -> 0.40197591 | H12: =MEDIAN(H7:H10) -> 0.28637209 | I12: =MEDIAN(I7:I10) -> 0.775 | J12: =MEDIAN(J7:J10) -> 0.60966558
B14: Cost of Debt | G14: Cost of Equity
B15: Pre-tax Cost of Debt | E15: ='Assumption and Drivers'!H113 -> 0.082 | G15: Risk Free Rate | J15: 0.0681
B16: Tax Rate | E16: 0.3 | G16: Equity Risk Premium | J16: 0.075
B17: After Tax Cost of Debt | E17: =E15*(1-E16) -> 0.0574 | G17: Levered Beta 4 | J17: =J24 -> 0.75192088
G18: Cost of Equity | J18: =J15+J16*J17 -> 0.12449407
B20: Capital Structure | G20: Levered Beta
D21: Current | E21: Target | G21: Comps Median Unlevered Beta | J21: =J12 -> 0.60966558
B22: Total Debt | C22: =63754+21203 -> 84957 | D22: =C22/$C$24 -> 0.26694045 | E22: 0.25 | G22: Target Debt/ Equity | J22: =E25 -> 0.33333333
B23: Market Capitalization | C23: 233305 | D23: =C23/$C$24 -> 0.73305955 | E23: =E24-E22 -> 0.75 | G23: Tax Rate | J23: =E16 -> 0.3
B24: Total Capitalization | C24: =SUM(C22:C23) -> 318262 | D24: =C24/$C$24 -> 1 | E24: =D24 -> 1 | G24: Levered Beta | J24: =J21*(1+(1-J23)*J22) -> 0.75192088
B25: Debt / Equity | D25: =D22/D23 -> 0.36414565 | E25: =E22/E23 -> 0.33333333
G26: Weighted Average Cost of Capital
B27: 1. Tax Rate considered as Marginal Tax Rate for the country | I27: Total Cost | J27: Total Weight
B28: 2. Levered Beta is based on 5 year monthly data | G28: Debt Capital | I28: =E17 -> 0.0574 | J28: =E22 -> 0.25
B29: 3. Unlevered Beta = Levered Beta/(1+(1-Tax Rate) x Debt/Equity) | G29: Equity Capital | I29: =J18 -> 0.12449407 | J29: =E23 -> 0.75
B30: 4. Levered Beta = Unlevered Beta*(1+(1-Tax Rate) x Debt/Equity) | G30: Weighted Average Cost of Capital | J30: =SUMPRODUCT(I28:I29,J28:J29) -> 0.10772055
B33: Assumptions
B34: Beta: Median unlevered beta of the peer group is relevered using Tata Steel's target capital structure to estimate the company's systematic risk.
B35: Risk-Free Rate: Based on the yield of the 10-year Government of India bond as a proxy for the risk-free return.
B36: Equity Risk Premium (ERP): Assumed at 7.50%, reflecting the long-term market risk premium for Indian equities.
B37: Cost of Debt: Estimated using the company's historical pre-tax borrowing cost and adjusted for the applicable corporate tax rate.
B38: Target Capital Structure: The valuation assumes a long-term target capital structure of 25% debt and 75% equity, reflecting a conservative financing mix.
B39: Cost of Equity: Estimated using the Capital Asset Pricing Model (CAPM): Risk-Free Rate + (Levered Beta × Equity Risk Premium).
B40: WACC: Calculated as the weighted average of the after-tax cost of debt and the cost of equity based on the target capital structure.

Sheet Inputs
B2: Drivers
B6: Driver Switch | C6: 3
D9: 2027F | E9: 2028F | F9: 2029F | G9: 2030F | H9: 2031F
B11: Revenue Growth | D11: {=INDEX(D12:D14,$C$6)} -> 0.045 | E11: {=INDEX(E12:E14,$C$6)} -> 0.052 | F11: {=INDEX(F12:F14,$C$6)} -> 0.045 | G11: {=INDEX(G12:G14,$C$6)} -> 0.04 | H11: {=INDEX(H12:H14,$C$6)} -> 0.04
B12: Best Case | D12: 0.062 | E12: 0.071 | F12: 0.061 | G12: 0.056 | H12: 0.055
B13: Base Case | D13: 0.055 | E13: 0.062 | F13: 0.055 | G13: 0.05 | H13: 0.05
B14: Worst Case | D14: 0.045 | E14: 0.052 | F14: 0.045 | G14: 0.04 | H14: 0.04
D17: 2027F | E17: 2028F | F17: 2029F | G17: 2030F | H17: 2031F
B19: Average Selling Price | D19: {=INDEX(D20:D22,$C$6)} -> 0.015 | E19: {=INDEX(E20:E22,$C$6)} -> 0.01 | F19: {=INDEX(F20:F22,$C$6)} -> 0.012 | G19: {=INDEX(G20:G22,$C$6)} -> 0.01 | H19: {=INDEX(H20:H22,$C$6)} -> 0.013
B20: Best Case | D20: 0.04 | E20: 0.045 | F20: 0.04 | G20: 0.047 | H20: 0.048
B21: Base Case | D21: 0.025 | E21: 0.025 | F21: 0.02 | G21: 0.02 | H21: 0.02
B22: Worst Case | D22: 0.015 | E22: 0.01 | F22: 0.012 | G22: 0.01 | H22: 0.013
D25: 2027F | E25: 2028F | F25: 2029F | G25: 2030F | H25: 2031F
B27: Material Cost | D27: {=INDEX(D28:D30,$C$6)} -> 0.612 | E27: {=INDEX(E28:E30,$C$6)} -> 0.61 | F27: {=INDEX(F28:F30,$C$6)} -> 0.608 | G27: {=INDEX(G28:G30,$C$6)} -> 0.606 | H27: {=INDEX(H28:H30,$C$6)} -> 0.605
B28: Best Case | D28: 0.599 | E28: 0.593 | F28: 0.587 | G28: 0.582 | H28: 0.575
B29: Base Case | D29: 0.604 | E29: 0.6 | F29: 0.596 | G29: 0.592 | H29: 0.588
B30: Worst Case | D30: 0.612 | E30: 0.61 | F30: 0.608 | G30: 0.606 | H30: 0.605
D32: 2027F | E32: 2028F | F32: 2029F | G32: 2030F | H32: 2031F
B34: Other operating Expense | D34: {=INDEX(D35:D37,$C$6)} -> 0.063 | E34: {=INDEX(E35:E37,$C$6)} -> 0.062 | F34: {=INDEX(F35:F37,$C$6)} -> 0.061 | G34: {=INDEX(G35:G37,$C$6)} -> 0.06 | H34: {=INDEX(H35:H37,$C$6)} -> 0.059
B35: Best Case | D35: 0.057 | E35: 0.056 | F35: 0.055 | G35: 0.054 | H35: 0.053
B36: Base Case | D36: 0.06 | E36: 0.059 | F36: 0.058 | G36: 0.057 | H36: 0.056
B37: Worst Case | D37: 0.063 | E37: 0.062 | F37: 0.061 | G37: 0.06 | H37: 0.059
D39: 2027F | E39: 2028F | F39: 2029F | G39: 2030F | H39: 2031F
B41: Capital Expenditure | D41: {=INDEX(D42:D44,$C$6)} -> 0.067 | E41: {=INDEX(E42:E44,$C$6)} -> 0.066 | F41: {=INDEX(F42:F44,$C$6)} -> 0.065 | G41: {=INDEX(G42:G44,$C$6)} -> 0.064 | H41: {=INDEX(H42:H44,$C$6)} -> 0.063
B42: Best Case | D42: 0.06 | E42: 0.06 | F42: 0.059 | G42: 0.058 | H42: 0.057
B43: Base Case | D43: 0.063 | E43: 0.063 | F43: 0.062 | G43: 0.061 | H43: 0.06
B44: Worst Case | D44: 0.067 | E44: 0.066 | F44: 0.065 | G44: 0.064 | H44: 0.063
D46: 2027F | E46: 2028F | F46: 2029F | G46: 2030F | H46: 2031F
B48: Deprication & Amortization | D48: {=INDEX(D49:D51,$C$6)} -> 0.053 | E48: {=INDEX(E49:E51,$C$6)} -> 0.0535 | F48: {=INDEX(F49:F51,$C$6)} -> 0.054 | G48: {=INDEX(G49:G51,$C$6)} -> 0.0545 | H48: {=INDEX(H49:H51,$C$6)} -> 0.055
B49: Best Case | D49: 0.0495 | E49: 0.05 | F49: 0.0505 | G49: 0.051 | H49: 0.0515
B50: Base Case | D50: 0.051 | E50: 0.0515 | F50: 0.052 | G50: 0.0525 | H50: 0.053
B51: Worst Case | D51: 0.053 | E51: 0.0535 | F51: 0.054 | G51: 0.0545 | H51: 0.055
D53: 2027F | E53: 2028F | F53: 2029F | G53: 2030F | H53: 2031F
D55: {=INDEX(D56:D58,$C$6)} -> 10 | E55: {=INDEX(E56:E58,$C$6)} -> 10 | F55: {=INDEX(F56:F58,$C$6)} -> 10 | G55: {=INDEX(G56:G58,$C$6)} -> 10 | H55: {=INDEX(H56:H58,$C$6)} -> 10
B56: Best Case | D56: 8 | E56: 8 | F56: 8 | G56: 8 | H56: 8
B57: Base Case | D57: 9 | E57: 9 | F57: 9 | G57: 9 | H57: 9
B58: Worst Case | D58: 10 | E58: 10 | F58: 10 | G58: 10 | H58: 10
D60: 2027F | E60: 2028F | F60: 2029F | G60: 2030F | H60: 2031F
B62: Recievable Days | D62: {=INDEX(D63:D65,$C$6)} -> 125 | E62: {=INDEX(E63:E65,$C$6)} -> 125 | F62: {=INDEX(F63:F65,$C$6)} -> 126 | G62: {=INDEX(G63:G65,$C$6)} -> 126 | H62: {=INDEX(H63:H65,$C$6)} -> 127
B63: Best Case | D63: 120 | E63: 120 | F63: 119 | G63: 118 | H63: 118
B64: Base Case | D64: 122 | E64: 122 | F64: 122 | G64: 122 | H64: 122
B65: Worst Case | D65: 125 | E65: 125 | F65: 126 | G65: 126 | H65: 127
D67: 2027F | E67: 2028F | F67: 2029F | G67: 2030F | H67: 2031F
B69: Payable Days | D69: {=INDEX(D70:D72,$C$6)} -> 88 | E69: {=INDEX(E70:E72,$C$6)} -> 88 | F69: {=INDEX(F70:F72,$C$6)} -> 87 | G69: {=INDEX(G70:G72,$C$6)} -> 87 | H69: {=INDEX(H70:H72,$C$6)} -> 86
B70: Best Case | D70: 92 | E70: 92 | F70: 93 | G70: 93 | H70: 94
B71: Base Case | D71: 90 | E71: 90 | F71: 90 | G71: 90 | H71: 90
B72: Worst Case | D72: 88 | E72: 88 | F72: 87 | G72: 87 | H72: 86

Sheet DCF
B1: Discounted Cash Flow - Base Case
B4: In Cr
B5: FCFF Schedule | D5: 2023A | E5: 2024A | F5: 2025A | G5: 2026A | H5: 2027F | I5: 2028F | J5: 2029F | K5: 2030F | L5: 2031F
B7: EBIT | D7: ='Forecasted Income Statement '!D12 -> 23048.228 | E7: ='Forecasted Income Statement '!E12 -> 40031.236 | F7: ='Forecasted Income Statement '!F12 -> 36871.375 | G7: ='Forecasted Income Statement '!G12 -> 39232.36 | H7: ='Forecasted Income Statement '!H12 -> 42843.166 | I7: ='Forecasted Income Statement '!I12 -> 47483.864 | J7: ='Forecasted Income Statement '!J12 -> 52291.131 | K7: ='Forecasted Income Statement '!K12 -> 56815.614 | L7: ='Forecasted Income Statement '!L12 -> 62458.837
B8: Tax Rate | D8: 0.3 | E8: 0.3 | F8: 0.3 | G8: 0.3 | H8: 0.3 | I8: 0.3 | J8: 0.3 | K8: 0.3 | L8: 0.3
B9: EBIT (1-Tax Rate) | D9: =D7*(1-D8) -> 16133.759 | E9: =E7*(1-E8) -> 28021.865 | F9: =F7*(1-F8) -> 25809.963 | G9: =G7*(1-G8) -> 27462.652 | H9: =H7*(1-H8) -> 29990.217 | I9: =I7*(1-I8) -> 33238.705 | J9: =J7*(1-J8) -> 36603.792 | K9: =K7*(1-K8) -> 39770.93 | L9: =L7*(1-L8) -> 43721.186
B10: Add: Depreciation | D10: ='Assumption and Drivers'!D70 -> 9335.2 | E10: ='Assumption and Drivers'!E70 -> 9882.16 | F10: ='Assumption and Drivers'!F70 -> 10421.33 | G10: ='Assumption and Drivers'!G70 -> 11954.51 | H10: ='Assumption and Drivers'!H70 -> 13049.93 | I10: ='Assumption and Drivers'!I70 -> 13996.621 | J10: ='Assumption and Drivers'!J70 -> 14940.323 | K10: ='Assumption and Drivers'!K70 -> 15838.624 | L10: ='Assumption and Drivers'!L70 -> 16839.392
B11: Less: Capex | D11: ='Assumption and Drivers'!D69 -> 13814.79 | E11: ='Assumption and Drivers'!E69 -> 17731.2 | F11: ='Assumption and Drivers'!F69 -> 15670.52 | G11: ='Assumption and Drivers'!G69 -> 14025.75 | H11: ='Assumption and Drivers'!H69 -> 16497.081 | I11: ='Assumption and Drivers'!I69 -> 17266.86 | J11: ='Assumption and Drivers'!J69 -> 17983.722 | K11: ='Assumption and Drivers'!K69 -> 18599.485 | L11: ='Assumption and Drivers'!L69 -> 19288.759
B12: Less: Net Working Capital Change | E12: ='Assumption and Drivers'!E90 -> -4853.65 | F12: ='Assumption and Drivers'!F90 -> 549.24 | G12: ='Assumption and Drivers'!G90 -> -3179.65 | H12: ='Assumption and Drivers'!H90 -> 4340.8457 | I12: ='Assumption and Drivers'!I90 -> 1197.3632 | J12: ='Assumption and Drivers'!J90 -> 2038.954 | K12: ='Assumption and Drivers'!K90 -> 1101.3688 | L12: ='Assumption and Drivers'!L90 -> 2129.0152
B13: FCFF | D13: =D9+D10-D11-D12 -> 11654.169 | E13: =E9+E10-E11-E12 -> 25026.475 | F13: =F9+F10-F11-F12 -> 20011.533 | G13: =G9+G10-G11-G12 -> 28571.062 | H13: =H9+H10-H11-H12 -> 22202.22 | I13: =I9+I10-I11-I12 -> 28771.103 | J13: =J9+J10-J11-J12 -> 31521.438 | K13: =K9+K10-K11-K12 -> 35908.7 | L13: =L9+L10-L11-L12 -> 39142.805
B16: Expected Growth | C16: 0.061
B17: Terminal Growth | C17: 0.025
B18: WACC | C18: =WACC!J30 -> 0.10772055
B21: FCFF Schedule | D21: 2027F | E21: 2028F | F21: 2029F | G21: 2030F | H21: 2031F
B23: Free Cash Flow to Firm (FCFF) | D23: =H13 -> 22202.22 | E23: =I13 -> 28771.103 | F23: =J13 -> 31521.438 | G23: =K13 -> 35908.7 | H23: =L13 -> 39142.805
B24: Discounting Factor | D24: =1/(1+$C$18)^1 -> 0.90275476 | E24: =1/(1+$C$18)^2 -> 0.81496616 | F24: =1/(1+$C$18)^3 -> 0.73571458 | G24: =1/(1+$C$18)^4 -> 0.66416984 | H24: =1/(1+$C$18)^5 -> 0.59958248
B26: PV of FCFF | D26: =D23*D24 -> 20043.159 | E26: =E23*E24 -> 23447.476 | F26: =F23*F24 -> 23190.782 | G26: =G23*G24 -> 23849.475 | H26: =H23*H24 -> 23469.34
B28: Terminal Value
B29: FCFF(n+1) | C29: =H23*(1+C17) -> 40121.375
B30: WACC | C30: =C18 -> 0.10772055
B31: Terminal Growth Rate | C31: =C17 -> 0.025
B33: Terminal Value | C33: =C29/(C30-C31) -> 485023.07
B35: Calculation of Enterprise Value
B37: PV of FCFF | C37: =SUM(D26:H26) -> 114000.23
B38: Pv of Terminal Value | C38: =C33*H24 -> 290811.34 | J38: `
B39: Value of Operating Assets | C39: =SUM(C37:C38) -> 404811.57
B40: Add Cash | C40: ='Forecasted Cash Flow '!G21 -> 10057.53
B41: Less Debt | C41: ='Forcasted Balance Sheet '!G25 -> 84956.39
B42: Equity Value | C42: =C39+C40-C41 -> 329912.71
B43: No. of Shares | C43: ='Forcasted Balance Sheet '!G17 -> 1247.44
B44: Value of shares | C44: =C42/C43 -> 264.47181
B46: Senstivity Analysis
B48: Terminal Growth ↓ / WACC →
B49: =C44 -> 264.47181 | C49: 0.1 | D49: 0.1077 | E49: 0.12 | F49: 0.13 | G49: 0.14
B50: 0.025 | C50: 288.47 | D50: 264.52973 | E50: 234.33848 | F50: 215.0058 | G50: 199.03532
B51: 0.03 | C51: 306.83605 | D51: 279.53517 | E51: 245.61588 | F51: 224.18883 | G51: 206.65759
B52: 0.035 | C52: 328.02765 | D52: 296.60462 | E52: 258.22004 | F52: 234.33848 | G52: 215.0058
B53: 0.04 | C53: 352.75118 | D53: 316.19541 | E53: 272.39971 | F53: 245.61588 | G53: 224.18883
B54: 0.045 | C54: 381.9699 | D54: 338.91074 | E54: 288.47 | F54: 258.22004 | G54: 234.33848

Sheet Football Feild Analysis
B1: Football Field Analysis
B4: Valuation Method | D4: Low | E4: High | F4: Start | G4: Width
B5: DCF | D5: 244.4 | E5: 353.6 | F5: 244.4 | G5: =E5-F5 -> 109.2
B6: EV / EBITDA | D6: 245.5 | E6: 245.5 | F6: 245.5 | G6: 2
B7: EV / Revenue | D7: 251.6 | E7: 251.6 | F7: 251.6 | G7: 2
B8: Current Market Price | D8: 185 | E8: 185 | F8: 185 | G8: 2

Sheet Data Room

Sheet Sheet3
A1: Date | B1: Price | C1: Vol.
A2: 46234 | B2: 189.69 | C2: 34250000 | E2: 1000000
A3: 46233 | B3: 186.92 | C3: 13770000
A4: 46232 | B4: 187.27 | C4: 24870000
A5: 46231 | B5: 182.63 | C5: 19140000
A6: 46230 | B6: 184.25 | C6: 11860000
A7: 46227 | B7: 182.67 | C7: 16120000
A8: 46226 | B8: 184.23 | C8: 20580000
A9: 46225 | B9: 186.53 | C9: 16640000
A10: 46224 | B10: 187.24 | C10: 21620000
A11: 46223 | B11: 186.41 | C11: 11190000
A12: 46220 | B12: 185.89 | C12: 20130000
A13: 46219 | B13: 185.49 | C13: 13170000
A14: 46218 | B14: 185.26 | C14: 24920000
... A991: 44775 | B991: 107 | C991: 64940000

Sheet Profit & Loss
A1: ='Data Sheet'!B1 -> TATA STEEL LTD | H1: =UPDATE | M1: SCREENER.IN
A3: Narration | B3: ='Data Sheet'!B16 -> 42825 | C3: ='Data Sheet'!C16 -> 43190 | D3: ='Data Sheet'!D16 -> 43555 | E3: ='Data Sheet'!E16 -> 43921 | F3: ='Data Sheet'!F16 -> 44286 | G3: ='Data Sheet'!G16 -> 44651 | H3: ='Data Sheet'!H16 -> 45016 | I3: ='Data Sheet'!I16 -> 45382 | ... K3: ='Data Sheet'!K16 -> 46112 | L3: Trailing | M3: Best Case | N3: Worst Case
A4: Sales | B4: ='Data Sheet'!B17 -> 112299.42 | C4: ='Data Sheet'!C17 -> 123249.07 | D4: ='Data Sheet'!D17 -> 157668.99 | E4: ='Data Sheet'!E17 -> 139816.65 | F4: ='Data Sheet'!F17 -> 156477.4 | G4: ='Data Sheet'!G17 -> 243959.17 | H4: ='Data Sheet'!H17 -> 243352.69 | I4: ='Data Sheet'!I17 -> 229170.78 | ... K4: ='Data Sheet'!K17 -> 232139.94 | L4: =SUM(Quarters!H4:K4) -> 232139.94 | M4: =$K4+M23*K4 -> 246583.38 | N4: =$K4+N23*L4 -> 228518.36
A5: Expenses | B5: =SUM('Data Sheet'!B18,'Data Sheet'!B20:B24, -1*'Data Sheet'!B19) -> 99155.79 | C5: =SUM('Data Sheet'!C18,'Data Sheet'!C20:C24, -1*'Data Sheet'!C19) -> 101815.88 | D5: =SUM('Data Sheet'!D18,'Data Sheet'!D20:D24, -1*'Data Sheet'!D19) -> 128350.77 | E5: =SUM('Data Sheet'!E18,'Data Sheet'!E20:E24, -1*'Data Sheet'!E19) -> 122353.59 | F5: =SUM('Data Sheet'!F18,'Data Sheet'!F20:F24, -1*'Data Sheet'!F19) -> 125973.14 | G5: =SUM('Data Sheet'!G18,'Data Sheet'!G20:G24, -1*'Data Sheet'!G19) -> 180469.22 | H5: =SUM('Data Sheet'!H18,'Data Sheet'!H20:H24, -1*'Data Sheet'!H19) -> 211052.53 | I5: =SUM('Data Sheet'!I18,'Data Sheet'!I20:I24, -1*'Data Sheet'!I19) -> 206922.86 | ... K5: =SUM('Data Sheet'!K18,'Data Sheet'!K20:K24, -1*'Data Sheet'!K19) -> 197787.5 | L5: =SUM(Quarters!H5:K5) -> 197787.5 | M5: =M4-M6 -> 210093.58 | N5: =N4-N6 -> 200989.8
A6: Operating Profit | B6: =B4-B5 -> 13143.63 | C6: =C4-C5 -> 21433.19 | D6: =D4-D5 -> 29318.22 | E6: =E4-E5 -> 17463.06 | F6: =F4-F5 -> 30504.26 | G6: =G4-G5 -> 63489.95 | H6: =H4-H5 -> 32300.16 | I6: =I4-I5 -> 22247.92 | ... K6: =K4-K5 -> 34352.44 | L6: =SUM(Quarters!H6:K6) -> 34352.44 | M6: =M4*M24 -> 36489.804 | N6: =N4*N24 -> 27528.562
A7: Other Income | B7: ='Data Sheet'!B25 -> -3789.11 | C7: ='Data Sheet'!C25 -> 10898.41 | D7: ='Data Sheet'!D25 -> 1524.31 | E7: ='Data Sheet'!E25 -> -2883.63 | F7: ='Data Sheet'!F25 -> 179.78 | G7: ='Data Sheet'!G25 -> 1299.99 | H7: ='Data Sheet'!H25 -> 1568.86 | I7: ='Data Sheet'!I25 -> -6005.23 | ... K7: ='Data Sheet'!K25 -> 737.82 | L7: =SUM(Quarters!H7:K7) -> 737.82 | M7: 0 | N7: 0
A8: Depreciation | B8: ='Data Sheet'!B26 -> 5672.88 | C8: ='Data Sheet'!C26 -> 5741.7 | D8: ='Data Sheet'!D26 -> 7341.83 | E8: ='Data Sheet'!E26 -> 8440.73 | F8: ='Data Sheet'!F26 -> 9233.64 | G8: ='Data Sheet'!G26 -> 9100.87 | H8: ='Data Sheet'!H26 -> 9335.2 | I8: ='Data Sheet'!I26 -> 9882.16 | ... K8: ='Data Sheet'!K26 -> 11954.51 | L8: =SUM(Quarters!H8:K8) -> 11954.51 | M8: =+$L8 -> 11954.51 | N8: =+$L8 -> 11954.51
A9: Interest | B9: ='Data Sheet'!B27 -> 5072.2 | C9: ='Data Sheet'!C27 -> 5454.74 | D9: ='Data Sheet'!D27 -> 7660.1 | E9: ='Data Sheet'!E27 -> 7533.46 | F9: ='Data Sheet'!F27 -> 7606.71 | G9: ='Data Sheet'!G27 -> 5462.2 | H9: ='Data Sheet'!H27 -> 6298.7 | I9: ='Data Sheet'!I27 -> 7507.57 | ... K9: ='Data Sheet'!K27 -> 7167.06 | L9: =SUM(Quarters!H9:K9) -> 7167.06 | M9: =+$L9 -> 7167.06 | N9: =+$L9 -> 7167.06
A10: Profit before tax | B10: ='Data Sheet'!B28 -> -1390.56 | C10: ='Data Sheet'!C28 -> 21135.16 | D10: ='Data Sheet'!D28 -> 15840.6 | E10: ='Data Sheet'!E28 -> -1394.76 | F10: ='Data Sheet'!F28 -> 13843.69 | G10: ='Data Sheet'!G28 -> 50226.87 | H10: ='Data Sheet'!H28 -> 18235.12 | I10: ='Data Sheet'!I28 -> -1147.04 | ... K10: ='Data Sheet'!K28 -> 15968.69 | L10: =SUM(Quarters!H10:K10) -> 15968.69 | M10: =M6+M7-SUM(M8:M9) -> 17368.234 | N10: =N6+N7-SUM(N8:N9) -> 8406.9924
A11: Tax | B11: ='Data Sheet'!B29 -> 2778.01 | C11: ='Data Sheet'!C29 -> 3392.33 | D11: ='Data Sheet'!D29 -> 6718.43 | E11: ='Data Sheet'!E29 -> -2568.41 | F11: ='Data Sheet'!F29 -> 5653.9 | G11: ='Data Sheet'!G29 -> 8477.55 | H11: ='Data Sheet'!H29 -> 10159.77 | I11: ='Data Sheet'!I29 -> 3762.57 | ... K11: ='Data Sheet'!K29 -> 5082.87 | L11: =SUM(Quarters!H11:K11) -> 5082.87 | M11: =IF($L10>0,$L11/$L10,0) -> 0.31830225 | N11: =IF($L10>0,$L11/$L10,0) -> 0.31830225
A12: Net profit | B12: ='Data Sheet'!B30 -> -4240.8 | C12: ='Data Sheet'!C30 -> 13434.33 | D12: ='Data Sheet'!D30 -> 10218.33 | E12: ='Data Sheet'!E30 -> 1556.54 | F12: ='Data Sheet'!F30 -> 7490.22 | G12: ='Data Sheet'!G30 -> 40153.93 | H12: ='Data Sheet'!H30 -> 8760.4 | I12: ='Data Sheet'!I30 -> -4437.44 | ... K12: ='Data Sheet'!K30 -> 10793.87 | L12: =SUM(Quarters!H12:K12) -> 10793.87 | M12: =M10-M11*M10 -> 11839.886 | N12: =N10-N11*N10 -> 5731.0278
A13: EPS | B13: =IF('Data Sheet'!B93>0,B12/'Data Sheet'!B93,0) -> -3.7641796 | C13: =IF('Data Sheet'!C93>0,C12/'Data Sheet'!C93,0) -> 11.925937 | D13: =IF('Data Sheet'!D93>0,D12/'Data Sheet'!D93,0) -> 9.070946 | E13: =IF('Data Sheet'!E93>0,E12/'Data Sheet'!E93,0) -> 1.381761 | F13: =IF('Data Sheet'!F93>0,F12/'Data Sheet'!F93,0) -> 6.2596378 | G13: =IF('Data Sheet'!G93>0,G12/'Data Sheet'!G93,0) -> 32.878023 | H13: =IF('Data Sheet'!H93>0,H12/'Data Sheet'!H93,0) -> 7.1680236 | I13: =IF('Data Sheet'!I93>0,I12/'Data Sheet'!I93,0) -> -3.5546441 | ... K13: =IF('Data Sheet'!K93>0,K12/'Data Sheet'!K93,0) -> 8.6465094 | L13: =IF('Data Sheet'!$B6>0,'Profit & Loss'!L12/'Data Sheet'!$B6,0) -> 8.6441442 | M13: =IF('Data Sheet'!$B6>0,'Profit & Loss'!M12/'Data Sheet'!$B6,0) -> 9.4818339 | N13: =IF('Data Sheet'!$B6>0,'Profit & Loss'!N12/'Data Sheet'!$B6,0) -> 4.5896264
A14: Price to earning | B14: =IF(B15>0,B15/B13,"") -> -12.217802 | C14: =IF(C15>0,C15/C13,"") -> 4.7887221 | D14: =IF(D15>0,D15/D13,"") -> 5.7436126 | E14: =IF(E15>0,E15/E13,"") -> 19.511333 | F14: =IF(F15>0,F15/F13,"") -> 12.970399 | G14: =IF(G15>0,G15/G13,"") -> 3.9759081 | H14: =IF(H15>0,H15/H13,"") -> 14.578635 | I14: =IF(I15>0,I15/I13,"") -> -43.844051 | ... K14: =IF(K15>0,K15/K13,"") -> 22.189301 | L14: =IF(L13>0,L15/L13,0) -> 21.664377 | M14: =M25 -> 33.381713 | N14: =N25 -> 17.968194
A15: Price | B15: ='Data Sheet'!B90 -> 45.99 | C15: ='Data Sheet'!C90 -> 57.11 | D15: ='Data Sheet'!D90 -> 52.1 | E15: ='Data Sheet'!E90 -> 26.96 | F15: ='Data Sheet'!F90 -> 81.19 | G15: ='Data Sheet'!G90 -> 130.72 | H15: ='Data Sheet'!H90 -> 104.5 | I15: ='Data Sheet'!I90 -> 155.85 | ... K15: ='Data Sheet'!K90 -> 191.86 | L15: ='Data Sheet'!B8 -> 187.27 | M15: =M13*M14 -> 316.51986 | N15: =N13*N14 -> 82.467299
F16: =F10/F11*100 -> 244.85205 | G16: =G10/G11*100 -> 592.46917 | H16: =H10/H11*100 -> 179.48359 | I16: =I10/I11*100 -> -30.485546 | J16: =J10/J11*100 -> 160.57884 | K16: =K10/K11*100 -> 314.1668
A17: RATIOS: | H17: =H13*H18 -> 3.5973162 | I17: =I13*I18 -> 0 | J17: =J13*J18 -> 3.5973725 | K17: =K13*K18 -> 3.9970842
A18: Dividend Payout | B18: =IF('Data Sheet'!B30>0, 'Data Sheet'!B31/'Data Sheet'!B30, 0) -> 0 | C18: =IF('Data Sheet'!C30>0, 'Data Sheet'!C31/'Data Sheet'!C30, 0) -> 0.085225687 | D18: =IF('Data Sheet'!D30>0, 'Data Sheet'!D31/'Data Sheet'!D30, 0) -> 0.14566177 | E18: =IF('Data Sheet'!E30>0, 'Data Sheet'!E31/'Data Sheet'!E30, 0) -> 0.73557377 | F18: =IF('Data Sheet'!F30>0, 'Data Sheet'!F31/'Data Sheet'!F30, 0) -> 0.39972391 | G18: =IF('Data Sheet'!G30>0, 'Data Sheet'!G31/'Data Sheet'!G30, 0) -> 0.15510736 | H18: =IF('Data Sheet'!H30>0, 'Data Sheet'!H31/'Data Sheet'!H30, 0) -> 0.50185608 | I18: =IF('Data Sheet'!I30>0, 'Data Sheet'!I31/'Data Sheet'!I30, 0) -> 0 | ... K18: =IF('Data Sheet'!K30>0, 'Data Sheet'!K31/'Data Sheet'!K30, 0) -> 0.4622772
A19: OPM | B19: =IF(B6>0,B6/B4,0) -> 0.11704094 | C19: =IF(C6>0,C6/C4,0) -> 0.17390143 | D19: =IF(D6>0,D6/D4,0) -> 0.18594792 | E19: =IF(E6>0,E6/E4,0) -> 0.12489972 | F19: =IF(F6>0,F6/F4,0) -> 0.19494355 | G19: =IF(G6>0,G6/G4,0) -> 0.26024826 | H19: =IF(H6>0,H6/H4,0) -> 0.13272983 | I19: =IF(I6>0,I6/I4,0) -> 0.09708009 | ... L19: =IF(L6>0,L6/L4,0) -> 0.1479816
G22: TRENDS: | H22: 10 YEARS | I22: 7 YEARS | J22: 5 YEARS | K22: 3 YEARS | L22: RECENT | M22: BEST | N22: WORST
G23: Sales Growth | H23: =IF(B4=0,"",POWER($K4/B4,1/9)-1) -> 0.084030178 | I23: =IF(D4=0,"",POWER($K4/D4,1/7)-1) -> 0.056818755 | J23: =IF(F4=0,"",POWER($K4/F4,1/5)-1) -> 0.082080696 | K23: =IF(H4=0,"",POWER($K4/H4, 1/3)-1) -> -0.01560083 | L23: =IF(ISERROR(MAX(IF(J4=0,"",(K4-J4)/J4),IF(K4=0,"",(L4-K4)/K4))),"",MAX(IF(J4=0,"",(K4-J4)/J4),IF(K4=0,"",(L4-K4)/K4))) -> 0.062218696 | M23: =MAX(K23:L23) -> 0.062218696 | N23: =MIN(H23:L23) -> -0.01560083
G24: OPM | H24: =IF(SUM(B4:$K$4)=0,"",SUMPRODUCT(B19:$K$19,B4:$K$4)/SUM(B4:$K$4)) -> 0.15595138 | I24: =IF(SUM(E4:$K$4)=0,"",SUMPRODUCT(E19:$K$19,E4:$K$4)/SUM(E4:$K$4)) -> 0.15419374 | J24: =IF(SUM(G4:$K$4)=0,"",SUMPRODUCT(G19:$K$19,G4:$K$4)/SUM(G4:$K$4)) -> 0.15223975 | K24: =IF(SUM(I4:$K$4)=0, "", SUMPRODUCT(I19:$K$19,I4:$K$4)/SUM(I4:$K$4)) -> 0.12046543 | L24: =L19 -> 0.1479816 | M24: =MAX(K24:L24) -> 0.1479816 | N24: =MIN(H24:L24) -> 0.12046543
G25: Price to Earning | H25: =IF(ISERROR(AVERAGEIF(B14:$L14,">0")),"",AVERAGEIF(B14:$L14,">0")) -> 17.968194 | I25: =IF(ISERROR(AVERAGEIF(E14:$L14,">0")),"",AVERAGEIF(E14:$L14,">0")) -> 21.597345 | J25: =IF(ISERROR(AVERAGEIF(G14:$L14,">0")),"",AVERAGEIF(G14:$L14,">0")) -> 23.739936 | K25: =IF(ISERROR(AVERAGEIF(I14:$L14,">0")),"",AVERAGEIF(I14:$L14,">0")) -> 33.381713 | L25: =L14 -> 21.664377 | M25: =MAX(K25:L25) -> 33.381713 | N25: =MIN(H25:L25) -> 17.968194

Sheet Quarters
A1: ='Profit & Loss'!A1 -> TATA STEEL LTD | E1: =UPDATE | J1: SCREENER.IN
A3: Narration | B3: ='Data Sheet'!B41 -> 45291 | C3: ='Data Sheet'!C41 -> 45382 | D3: ='Data Sheet'!D41 -> 45473 | E3: ='Data Sheet'!E41 -> 45565 | F3: ='Data Sheet'!F41 -> 45657 | G3: ='Data Sheet'!G41 -> 45747 | H3: ='Data Sheet'!H41 -> 45838 | I3: ='Data Sheet'!I41 -> 45930 | ... K3: ='Data Sheet'!K41 -> 46112
A4: Sales | B4: ='Data Sheet'!B42 -> 55311.88 | C4: ='Data Sheet'!C42 -> 58687.31 | D4: ='Data Sheet'!D42 -> 54771.39 | E4: ='Data Sheet'!E42 -> 53904.71 | F4: ='Data Sheet'!F42 -> 53648.3 | G4: ='Data Sheet'!G42 -> 56218.11 | H4: ='Data Sheet'!H42 -> 53178.12 | I4: ='Data Sheet'!I42 -> 58689.29 | ... K4: ='Data Sheet'!K42 -> 63270.13
A5: Expenses | B5: ='Data Sheet'!B43 -> 49048.31 | C5: ='Data Sheet'!C43 -> 52086.68 | D5: ='Data Sheet'!D43 -> 48076.92 | E5: ='Data Sheet'!E43 -> 47788.92 | F5: ='Data Sheet'!F43 -> 47744.81 | G5: ='Data Sheet'!G43 -> 49658.89 | H5: ='Data Sheet'!H43 -> 45750.58 | I5: ='Data Sheet'!I43 -> 49792.75 | ... K5: ='Data Sheet'!K43 -> 53441.47
A6: Operating Profit | B6: ='Data Sheet'!B50 -> 6263.57 | C6: ='Data Sheet'!C50 -> 6600.63 | D6: ='Data Sheet'!D50 -> 6694.47 | E6: ='Data Sheet'!E50 -> 6115.79 | F6: ='Data Sheet'!F50 -> 5903.49 | G6: ='Data Sheet'!G50 -> 6559.22 | H6: ='Data Sheet'!H50 -> 7427.54 | I6: ='Data Sheet'!I50 -> 8896.54 | ... K6: ='Data Sheet'!K50 -> 9828.66
A7: Other Income | B7: ='Data Sheet'!B44 -> -32.84 | C7: ='Data Sheet'!C44 -> -381.56 | D7: ='Data Sheet'!D44 -> -5.51 | E7: ='Data Sheet'!E44 -> 616.68 | F7: ='Data Sheet'!F44 -> 141.82 | G7: ='Data Sheet'!G44 -> 149.19 | H7: ='Data Sheet'!H44 -> 236.27 | I7: ='Data Sheet'!I44 -> -6.11 | ... K7: ='Data Sheet'!K44 -> 42.49
A8: Depreciation | B8: ='Data Sheet'!B45 -> 2422.04 | C8: ='Data Sheet'!C45 -> 2567.95 | D8: ='Data Sheet'!D45 -> 2535.43 | E8: ='Data Sheet'!E45 -> 2596.74 | F8: ='Data Sheet'!F45 -> 2569.19 | G8: ='Data Sheet'!G45 -> 2719.97 | H8: ='Data Sheet'!H45 -> 2744.3 | I8: ='Data Sheet'!I45 -> 2893 | ... K8: ='Data Sheet'!K45 -> 3268.4
A9: Interest | B9: ='Data Sheet'!B46 -> 1880.78 | C9: ='Data Sheet'!C46 -> 1842.25 | D9: ='Data Sheet'!D46 -> 1776.71 | E9: ='Data Sheet'!E46 -> 1971.4 | F9: ='Data Sheet'!F46 -> 1804.09 | G9: ='Data Sheet'!G46 -> 1788.75 | H9: ='Data Sheet'!H46 -> 1852.43 | I9: ='Data Sheet'!I46 -> 1774.96 | ... K9: ='Data Sheet'!K46 -> 1792.38
A10: Profit before tax | B10: ='Data Sheet'!B47 -> 1927.91 | C10: ='Data Sheet'!C47 -> 1808.87 | D10: ='Data Sheet'!D47 -> 2376.82 | E10: ='Data Sheet'!E47 -> 2164.33 | F10: ='Data Sheet'!F47 -> 1672.03 | G10: ='Data Sheet'!G47 -> 2199.69 | H10: ='Data Sheet'!H47 -> 3067.08 | I10: ='Data Sheet'!I47 -> 4222.47 | ... K10: ='Data Sheet'!K47 -> 4810.37
A11: Tax | B11: ='Data Sheet'!B48 -> 1405.77 | C11: ='Data Sheet'!C48 -> 1254.31 | D11: ='Data Sheet'!D48 -> 1458.25 | E11: ='Data Sheet'!E48 -> 1405.49 | F11: ='Data Sheet'!F48 -> 1376.54 | G11: ='Data Sheet'!G48 -> 998.81 | H11: ='Data Sheet'!H48 -> 1059.72 | I11: ='Data Sheet'!I48 -> 1039.38 | ... K11: ='Data Sheet'!K48 -> 1845.37
A12: Net profit | B12: ='Data Sheet'!B49 -> 513.37 | C12: ='Data Sheet'!C49 -> 611.48 | D12: ='Data Sheet'!D49 -> 959.61 | E12: ='Data Sheet'!E49 -> 833.45 | F12: ='Data Sheet'!F49 -> 326.64 | G12: ='Data Sheet'!G49 -> 1300.81 | H12: ='Data Sheet'!H49 -> 2077.68 | I12: ='Data Sheet'!I49 -> 3101.75 | ... K12: ='Data Sheet'!K49 -> 2925.74
A14: OPM | B14: =IF(B4>0,B6/B4,"") -> 0.11324095 | C14: =IF(C4>0,C6/C4,"") -> 0.11247116 | D14: =IF(D4>0,D6/D4,"") -> 0.12222567 | E14: =IF(E4>0,E6/E4,"") -> 0.11345558 | F14: =IF(F4>0,F6/F4,"") -> 0.11004058 | G14: =IF(G4>0,G6/G4,"") -> 0.1166745 | H14: =IF(H4>0,H6/H4,"") -> 0.13967286 | I14: =IF(I4>0,I6/I4,"") -> 0.15158711 | ... K14: =IF(K4>0,K6/K4,"") -> 0.15534439

Sheet Balance Sheet
A1: ='Profit & Loss'!A1 -> TATA STEEL LTD | E1: =UPDATE | J1: SCREENER.IN
A3: Narration | B3: ='Data Sheet'!B56 -> 42825 | C3: ='Data Sheet'!C56 -> 43190 | D3: ='Data Sheet'!D56 -> 43555 | E3: ='Data Sheet'!E56 -> 43921 | F3: ='Data Sheet'!F56 -> 44286 | G3: ='Data Sheet'!G56 -> 44651 | H3: ='Data Sheet'!H56 -> 45016 | I3: ='Data Sheet'!I56 -> 45382 | ... K3: ='Data Sheet'!K56 -> 46112
A4: Equity Share Capital | B4: ='Data Sheet'!B57 -> 970.24 | C4: ='Data Sheet'!C57 -> 1144.95 | D4: ='Data Sheet'!D57 -> 1144.94 | E4: ='Data Sheet'!E57 -> 1144.95 | F4: ='Data Sheet'!F57 -> 1197.61 | G4: ='Data Sheet'!G57 -> 1221.21 | H4: ='Data Sheet'!H57 -> 1221.24 | I4: ='Data Sheet'!I57 -> 1247.44 | ... K4: ='Data Sheet'!K57 -> 1247.44 | N4: 44621 | O4: 44986 | P4: 45352 | Q4: 45717 | R4: 46082
A5: Reserves | B5: ='Data Sheet'!B58 -> 36849.08 | C5: ='Data Sheet'!C58 -> 59725.67 | D5: ='Data Sheet'!D58 -> 67780.14 | E5: ='Data Sheet'!E58 -> 72431.35 | F5: ='Data Sheet'!F58 -> 73041.16 | G5: ='Data Sheet'!G58 -> 113221.83 | H5: ='Data Sheet'!H58 -> 101860.86 | I5: ='Data Sheet'!I58 -> 90788.32 | ... K5: ='Data Sheet'!K58 -> 100920.21 | M5: Equity Capital | N5: 1221 | O5: 1221 | P5: 1247 | Q5: 1247 | R5: 1247
A6: Average | C6: =((C4+C5)+(B4+B5))/2 -> 49344.97 | D6: =((D4+D5)+(C4+C5))/2 -> 64897.85 | E6: =((E4+E5)+(D4+D5))/2 -> 71250.69 | F6: =((F4+F5)+(E4+E5))/2 -> 73907.535 | G6: =((G4+G5)+(F4+F5))/2 -> 94340.905 | H6: =((H4+H5)+(G4+G5))/2 -> 108762.57 | I6: =((I4+I5)+(H4+H5))/2 -> 97558.93 | J6: =((J4+J5)+(I4+I5))/2 -> 91602.695 | K6: =((K4+K5)+(J4+J5))/2 -> 96668.64 | M6: Reserves | N6: 113222 | O6: 101861 | P6: 90788 | Q6: 89922 | R6: 100920
A7: Borrowings | B7: ='Data Sheet'!B59 -> 83014.49 | C7: ='Data Sheet'!C59 -> 92147.05 | D7: ='Data Sheet'!D59 -> 100816.22 | E7: ='Data Sheet'!E59 -> 116328.2 | F7: ='Data Sheet'!F59 -> 88501.41 | G7: ='Data Sheet'!G59 -> 75561.35 | H7: ='Data Sheet'!H59 -> 84893.05 | I7: ='Data Sheet'!I59 -> 87082.12 | ... K7: ='Data Sheet'!K59 -> 92381.68 | M7: Borrowings - | N7: 75561 | O7: 84893 | P7: 87082 | Q7: 94801 | R7: 92382
A8: Other Liabilities | B8: ='Data Sheet'!B60 -> 51613.56 | C8: ='Data Sheet'!C60 -> 55704.47 | D8: ='Data Sheet'!D60 -> 63032.14 | E8: ='Data Sheet'!E60 -> 59244.62 | F8: ='Data Sheet'!F60 -> 81169.01 | G8: ='Data Sheet'!G60 -> 92417.28 | H8: ='Data Sheet'!H60 -> 97420.63 | I8: ='Data Sheet'!I60 -> 90194.54 | ... K8: ='Data Sheet'!K60 -> 101965.29 | M8: Long term Borrowings | N8: 44764 | O8: 51446 | P8: 51577 | Q8: 68552 | R8: 63754
A9: Total | B9: ='Data Sheet'!B61 -> 172447.37 | C9: ='Data Sheet'!C61 -> 208722.14 | D9: ='Data Sheet'!D61 -> 232773.44 | E9: ='Data Sheet'!E61 -> 249149.12 | F9: ='Data Sheet'!F61 -> 243909.19 | G9: ='Data Sheet'!G61 -> 282421.67 | H9: ='Data Sheet'!H61 -> 285395.78 | I9: ='Data Sheet'!I61 -> 269312.42 | ... K9: ='Data Sheet'!K61 -> 296514.62 | M9: Short term Borrowings | N9: 24065 | O9: 26571 | P9: 29997 | Q9: 20412 | R9: 21203
A10: long term | G10: 44764 | H10: 51446 | I10: 51577 | J10: 68552 | K10: 63754 | M10: Lease Liabilities | N10: 6733 | O10: 6875 | P10: 5508 | Q10: 5837 | R10: 7425
A11: Net Block | B11: ='Data Sheet'!B62 -> 92006.55 | C11: ='Data Sheet'!C62 -> 96104.89 | D11: ='Data Sheet'!D62 -> 124441.91 | E11: ='Data Sheet'!E62 -> 134550.66 | F11: ='Data Sheet'!F62 -> 135775.18 | G11: ='Data Sheet'!G62 -> 133287.83 | H11: ='Data Sheet'!H62 -> 146621.46 | I11: ='Data Sheet'!I62 -> 148814.38 | ... K11: ='Data Sheet'!K62 -> 179908.13 | M11: Preference Capital | N11: 0 | O11: 0 | P11: 0 | Q11: 0 | R11: 0
A12: Capital Work in Progress | B12: ='Data Sheet'!B63 -> 15784.13 | C12: ='Data Sheet'!C63 -> 16614.41 | D12: ='Data Sheet'!D63 -> 18641.21 | E12: ='Data Sheet'!E63 -> 19496.83 | F12: ='Data Sheet'!F63 -> 19007.4 | G12: ='Data Sheet'!G63 -> 22045.55 | H12: ='Data Sheet'!H63 -> 31213.02 | I12: ='Data Sheet'!I63 -> 34355.53 | ... K12: ='Data Sheet'!K63 -> 28496.71 | M12: Other Borrowings | N12: 0 | O12: 0 | P12: 0 | Q12: 0 | R12: 0
A13: Investments | B13: ='Data Sheet'!B64 -> 12457.12 | C13: ='Data Sheet'!C64 -> 17899.47 | D13: ='Data Sheet'!D64 -> 5738.17 | E13: ='Data Sheet'!E64 -> 6285.18 | F13: ='Data Sheet'!F64 -> 10681.93 | G13: ='Data Sheet'!G64 -> 13139.85 | H13: ='Data Sheet'!H64 -> 8410.31 | I13: ='Data Sheet'!I64 -> 6257.57 | ... K13: ='Data Sheet'!K64 -> 7088.85 | M13: Other Liabilities - | N13: 92417 | O13: 97421 | P13: 90195 | Q13: 89488 | R13: 101965
A14: Other Assets | B14: ='Data Sheet'!B65 -> 52199.57 | C14: ='Data Sheet'!C65 -> 78103.37 | D14: ='Data Sheet'!D65 -> 83952.15 | E14: ='Data Sheet'!E65 -> 88816.45 | F14: ='Data Sheet'!F65 -> 78444.68 | G14: ='Data Sheet'!G65 -> 113948.44 | H14: ='Data Sheet'!H65 -> 99150.99 | I14: ='Data Sheet'!I65 -> 79884.94 | ... K14: ='Data Sheet'!K65 -> 81020.93 | M14: Non controlling int | N14: 2655 | O14: 2093 | P14: 397 | Q14: 183 | R14: 1613
A15: Total | B15: ='Data Sheet'!B66 -> 172447.37 | C15: ='Data Sheet'!C66 -> 208722.14 | D15: ='Data Sheet'!D66 -> 232773.44 | E15: ='Data Sheet'!E66 -> 249149.12 | F15: ='Data Sheet'!F66 -> 243909.19 | G15: ='Data Sheet'!G66 -> 282421.67 | H15: ='Data Sheet'!H66 -> 285395.78 | I15: ='Data Sheet'!I66 -> 269312.42 | ... K15: ='Data Sheet'!K66 -> 296514.62 | M15: Trade Payables | N15: 36765 | O15: 37833 | P15: 30228 | Q15: 29314 | R15: 34810
A16: Average | C16: =((C14+C15)+(B14+B15))/2 -> 255736.23 | D16: =((D14+D15)+(C14+C15))/2 -> 301775.55 | E16: =((E14+E15)+(D14+D15))/2 -> 327345.58 | F16: =((F14+F15)+(E14+E15))/2 -> 330159.72 | G16: =((G14+G15)+(F14+F15))/2 -> 359361.99 | H16: =((H14+H15)+(G14+G15))/2 -> 390458.44 | I16: =((I14+I15)+(H14+H15))/2 -> 366872.07 | J16: =((J14+J15)+(I14+I15))/2 -> 350692 | K16: =((K14+K15)+(J14+J15))/2 -> 364861.09 | M16: Advance from Customers | N16: 3253 | O16: 3394 | P16: 2771 | Q16: 1655 | R16: 2222
A17: Working Capital | B17: =B14-B8 -> 586.01 | C17: =C14-C8 -> 22398.9 | D17: =D14-D8 -> 20920.01 | E17: =E14-E8 -> 29571.83 | F17: =F14-F8 -> -2724.33 | G17: =G14-G8 -> 21531.16 | H17: =H14-H8 -> 1730.36 | I17: =I14-I8 -> -10309.6 | ... K17: =K14-K8 -> -20944.36 | M17: Other liability items | N17: 49744 | O17: 54101 | P17: 56799 | Q17: 58335 | R17: 63320
A18: Debtors | B18: ='Data Sheet'!B67 -> 11586.82 | C18: ='Data Sheet'!C67 -> 12415.52 | D18: ='Data Sheet'!D67 -> 11811 | E18: ='Data Sheet'!E67 -> 7884.91 | F18: ='Data Sheet'!F67 -> 9539.84 | G18: ='Data Sheet'!G67 -> 12246.43 | H18: ='Data Sheet'!H67 -> 8257.24 | I18: ='Data Sheet'!I67 -> 6263.53 | ... K18: ='Data Sheet'!K67 -> 4916.89 | M18: Total Liabilities | N18: 282422 | O18: 285396 | P18: 269312 | Q18: 275459 | R18: 296515
A19: Inventory | B19: ='Data Sheet'!B68 -> 24803.82 | C19: ='Data Sheet'!C68 -> 28331.04 | D19: ='Data Sheet'!D68 -> 31656.1 | E19: ='Data Sheet'!E68 -> 31068.72 | F19: ='Data Sheet'!F68 -> 33276.38 | G19: ='Data Sheet'!G68 -> 48824.39 | H19: ='Data Sheet'!H68 -> 54415.33 | I19: ='Data Sheet'!I68 -> 49157.51 | ... K19: ='Data Sheet'!K68 -> 47249.22 | M19: Fixed Assets - | N19: 133288 | O19: 146621 | P19: 148814 | Q19: 150914 | R19: 179908
M20: Land | N20: 20770 | O20: 21701 | P20: 22067 | Q20: 22299 | R20: 23659
A21: Debtor Days | B21: =IF('Profit & Loss'!B4>0,'Balance Sheet'!B18/('Profit & Loss'!B4/365),0) -> 37.659939 | C21: =IF('Profit & Loss'!C4>0,'Balance Sheet'!C18/('Profit & Loss'!C4/365),0) -> 36.768349 | D21: =IF('Profit & Loss'!D4>0,'Balance Sheet'!D18/('Profit & Loss'!D4/365),0) -> 27.342187 | E21: =IF('Profit & Loss'!E4>0,'Balance Sheet'!E18/('Profit & Loss'!E4/365),0) -> 20.584045 | F21: =IF('Profit & Loss'!F4>0,'Balance Sheet'!F18/('Profit & Loss'!F4/365),0) -> 22.252681 | G21: =IF('Profit & Loss'!G4>0,'Balance Sheet'!G18/('Profit & Loss'!G4/365),0) -> 18.322521 | H21: =IF('Profit & Loss'!H4>0,'Balance Sheet'!H18/('Profit & Loss'!H4/365),0) -> 12.384875 | I21: =IF('Profit & Loss'!I4>0,'Balance Sheet'!I18/('Profit & Loss'!I4/365),0) -> 9.975916 | ... K21: =IF('Profit & Loss'!K4>0,'Balance Sheet'!K18/('Profit & Loss'!K4/365),0) -> 7.7309611 | M21: Building | N21: 27588 | O21: 28904 | P21: 30173 | Q21: 31819 | R21: 36997
A22: Inventory Turnover | B22: =IF('Balance Sheet'!B19>0,'Profit & Loss'!B4/'Balance Sheet'!B19,0) -> 4.527505 | C22: =IF('Balance Sheet'!C19>0,'Profit & Loss'!C4/'Balance Sheet'!C19,0) -> 4.3503193 | D22: =IF('Balance Sheet'!D19>0,'Profit & Loss'!D4/'Balance Sheet'!D19,0) -> 4.9806827 | E22: =IF('Balance Sheet'!E19>0,'Profit & Loss'!E4/'Balance Sheet'!E19,0) -> 4.5002385 | F22: =IF('Balance Sheet'!F19>0,'Profit & Loss'!F4/'Balance Sheet'!F19,0) -> 4.7023564 | G22: =IF('Balance Sheet'!G19>0,'Profit & Loss'!G4/'Balance Sheet'!G19,0) -> 4.996666 | H22: =IF('Balance Sheet'!H19>0,'Profit & Loss'!H4/'Balance Sheet'!H19,0) -> 4.4721348 | I22: =IF('Balance Sheet'!I19>0,'Profit & Loss'!I4/'Balance Sheet'!I19,0) -> 4.6619688 | ... K22: =IF('Balance Sheet'!K19>0,'Profit & Loss'!K4/'Balance Sheet'!K19,0) -> 4.9130957 | M22: Plant Machinery | N22: 152754 | O22: 163134 | P22: 175111 | Q22: 186115 | R22: 224912
M23: Equipments | N23: 0 | O23: 0 | P23: 0 | Q23: 0 | R23: 0
A24: Return on Equity | B24: =IF(SUM('Balance Sheet'!B4:B5)>0,'Profit & Loss'!B12/SUM('Balance Sheet'!B4:B5),"") -> -0.11213316 | C24: =IF(SUM('Balance Sheet'!C4:C5)>0,'Profit & Loss'!C12/SUM('Balance Sheet'!C4:C5),"") -> 0.22070303 | D24: =IF(SUM('Balance Sheet'!D4:D5)>0,'Profit & Loss'!D12/SUM('Balance Sheet'!D4:D5),"") -> 0.14825271 | E24: =IF(SUM('Balance Sheet'!E4:E5)>0,'Profit & Loss'!E12/SUM('Balance Sheet'!E4:E5),"") -> 0.021155454 | F24: =IF(SUM('Balance Sheet'!F4:F5)>0,'Profit & Loss'!F12/SUM('Balance Sheet'!F4:F5),"") -> 0.10089364 | G24: =IF(SUM('Balance Sheet'!G4:G5)>0,'Profit & Loss'!G12/SUM('Balance Sheet'!G4:G5),"") -> 0.35086389 | H24: =IF(SUM('Balance Sheet'!H4:H5)>0,'Profit & Loss'!H12/SUM('Balance Sheet'!H4:H5),"") -> 0.084984687 | I24: =IF(SUM('Balance Sheet'!I4:I5)>0,'Profit & Loss'!I12/SUM('Balance Sheet'!I4:I5),"") -> -0.048214303 | ... K24: =IF(SUM('Balance Sheet'!K4:K5)>0,'Profit & Loss'!K12/SUM('Balance Sheet'!K4:K5),"") -> 0.10564861 | M24: Furniture n fittings | N24: 991 | O24: 1111 | P24: 1238 | Q24: 1298 | R24: 1429
A25: Return on Capital Emp | C25: =IF((B4+B5+B7+C4+C5+C7)>0,('Profit & Loss'!C10+'Profit & Loss'!C9)*2/(B4+B5+B7+C4+C5+C7),"") -> 0.19419212 | D25: =IF((C4+C5+C7+D4+D5+D7)>0,('Profit & Loss'!D10+'Profit & Loss'!D9)*2/(C4+C5+C7+D4+D5+D7),"") -> 0.14562384 | E25: =IF((D4+D5+D7+E4+E5+E7)>0,('Profit & Loss'!E10+'Profit & Loss'!E9)*2/(D4+D5+D7+E4+E5+E7),"") -> 0.034137476 | F25: =IF((E4+E5+E7+F4+F5+F7)>0,('Profit & Loss'!F10+'Profit & Loss'!F9)*2/(E4+E5+E7+F4+F5+F7),"") -> 0.12165447 | G25: =IF((F4+F5+F7+G4+G5+G7)>0,('Profit & Loss'!G10+'Profit & Loss'!G9)*2/(F4+F5+F7+G4+G5+G7),"") -> 0.31574728 | H25: =IF((G4+G5+G7+H4+H5+H7)>0,('Profit & Loss'!H10+'Profit & Loss'!H9)*2/(G4+G5+G7+H4+H5+H7),"") -> 0.1298156 | I25: =IF((H4+H5+H7+I4+I5+I7)>0,('Profit & Loss'!I10+'Profit & Loss'!I9)*2/(H4+H5+H7+I4+I5+I7),"") -> 0.034653505 | J25: =IF((I4+I5+I7+J4+J5+J7)>0,('Profit & Loss'!J10+'Profit & Loss'!J9)*2/(I4+I5+I7+J4+J5+J7),"") -> 0.086301362 | K25: =IF((J4+J5+J7+K4+K5+K7)>0,('Profit & Loss'!K10+'Profit & Loss'!K9)*2/(J4+J5+J7+K4+K5+K7),"") -> 0.1216007 | M25: Railway sidings | N25: 1780 | O25: 1841 | P25: 1872 | Q25: 1890 | R25: 2384
M26: Vehicles | N26: 686 | O26: 749 | P26: 794 | Q26: 830 | R26: 978
M27: Intangible Assets | N27: 6229 | O27: 7572 | P27: 7772 | Q27: 7896 | R27: 10230
M28: Other fixed assets | N28: 10953 | O28: 20384 | P28: 20546 | Q28: 20881 | R28: 22389
M29: Gross Block | N29: 221752 | O29: 245395 | P29: 259572 | Q29: 273028 | R29: 322978
M30: Accumulated Depreciation | N30: 88464 | O30: 98773 | P30: 110758 | Q30: 122114 | R30: 143070
M31: CWIP | N31: 22046 | O31: 31213 | P31: 34356 | Q31: 41622 | R31: 28497
M32: Investments | N32: 13140 | O32: 8410 | P32: 6258 | Q32: 6194 | R32: 7089
M33: Other Assets - | N33: 113948 | O33: 99151 | P33: 79885 | Q33: 76728 | R33: 81021
M34: Inventories | N34: 48824 | O34: 54415 | P34: 49158 | Q34: 44590 | R34: 47249
M35: Trade receivables + | N35: 12246 | O35: 8257 | P35: 6264 | Q35: 5260 | R35: 4917
M36: Cash Equivalents | N36: 15899 | O36: 13357 | P36: 8678 | Q36: 11647 | R36: 10058
M37: Loans n Advances | N37: -158 | O37: -90 | P37: -56 | Q37: 49 | R37: 1167
... M39: Total Assets | N39: 282422 | O39: 285396 | P39: 269312 | Q39: 275459 | R39: 296515

Sheet Cash Flow
A1: ='Balance Sheet'!A1 -> TATA STEEL LTD | E1: =UPDATE | J1: SCREENER.IN
A3: Narration | B3: ='Data Sheet'!B81 -> 42825 | C3: ='Data Sheet'!C81 -> 43190 | D3: ='Data Sheet'!D81 -> 43555 | E3: ='Data Sheet'!E81 -> 43921 | F3: ='Data Sheet'!F81 -> 44286 | G3: ='Data Sheet'!G81 -> 44651 | H3: ='Data Sheet'!H81 -> 45016 | I3: ='Data Sheet'!I81 -> 45382 | ... K3: ='Data Sheet'!K81 -> 46112
A4: Cash from Operating Activity | B4: ='Data Sheet'!B82 -> 10824.36 | C4: ='Data Sheet'!C82 -> 8023.39 | D4: ='Data Sheet'!D82 -> 25335.95 | E4: ='Data Sheet'!E82 -> 20168.72 | F4: ='Data Sheet'!F82 -> 44326.68 | G4: ='Data Sheet'!G82 -> 44380.99 | H4: ='Data Sheet'!H82 -> 21683.08 | I4: ='Data Sheet'!I82 -> 20300.67 | ... K4: ='Data Sheet'!K82 -> 35064.46
A5: Cash from Investing Activity | B5: ='Data Sheet'!B83 -> -9489.65 | C5: ='Data Sheet'!C83 -> -11730.31 | D5: ='Data Sheet'!D83 -> -29176.45 | E5: ='Data Sheet'!E83 -> -14012.06 | F5: ='Data Sheet'!F83 -> -9437.27 | G5: ='Data Sheet'!G83 -> -10905.02 | H5: ='Data Sheet'!H83 -> -18179.45 | I5: ='Data Sheet'!I83 -> -14252.74 | ... K5: ='Data Sheet'!K83 -> -14397.35
A6: Cash from Financing Activity | B6: ='Data Sheet'!B84 -> -2579.36 | C6: ='Data Sheet'!C84 -> 6639.94 | D6: ='Data Sheet'!D84 -> -672.7 | E6: ='Data Sheet'!E84 -> -1694.62 | F6: ='Data Sheet'!F84 -> -37089.67 | G6: ='Data Sheet'!G84 -> -23401.09 | H6: ='Data Sheet'!H84 -> -6980.69 | I6: ='Data Sheet'!I84 -> -11096.99 | ... K6: ='Data Sheet'!K84 -> -21387.12
A7: Net Cash Flow | B7: ='Data Sheet'!B85 -> -1244.65 | C7: ='Data Sheet'!C85 -> 2933.02 | D7: ='Data Sheet'!D85 -> -4513.2 | E7: ='Data Sheet'!E85 -> 4462.04 | F7: ='Data Sheet'!F85 -> -2200.26 | G7: ='Data Sheet'!G85 -> 10074.88 | H7: ='Data Sheet'!H85 -> -3477.06 | I7: ='Data Sheet'!I85 -> -5049.06 | ... K7: ='Data Sheet'!K85 -> -720.01

Sheet Customization
A1: How to use it?
A3: You can customize this workbook as you want.
B4: You can add custom formating, add conditional formating, add your own formulas… do ANYTHING.
B5: Please don't edit the "Data Sheet" only.
A7: After customization, you can upload this back on Screener.
B8: Upload on: | C8: https://www.screener.in/excel/
A10: Download your customized workbooks now onwards.
B11: Now whenever you will "Export to excel" from Screener, it will export your customized file.
A14: TESTING:
B15: This is a testing feature currently.
B16: You can report any formula errors on the worksheet at: support@screener.in

Sheet Data Sheet
A1: COMPANY NAME | B1: TATA STEEL LTD | E1: =IF(B2<>B3, "A NEW VERSION OF THE WORKSHEET IS AVAILABLE", "")
A2: LATEST VERSION | B2: 2.1 | E2: PLEASE DO NOT MAKE ANY CHANGES TO THIS SHEET
A3: CURRENT VERSION | B3: 2.1
A5: META
A6: Number of shares | B6: =IF(B9>0, B9/B8, 0) -> 1248.6916
A7: Face Value | B7: 1
A8: Current Price | B8: 187.27
A9: Market Capitalization | B9: 233842.47
A15: PROFIT & LOSS
A16: Report Date | B16: 42825 | C16: 43190 | D16: 43555 | E16: 43921 | F16: 44286 | G16: 44651 | H16: 45016 | I16: 45382 | J16: 45747 | K16: 46112
A17: Sales | B17: 112299.42 | C17: 123249.07 | D17: 157668.99 | E17: 139816.65 | F17: 156477.4 | G17: 243959.17 | H17: 243352.69 | I17: 229170.78 | J17: 218542.51 | K17: 232139.94
A18: Raw Material Cost | B18: 43843.03 | C18: 46137.01 | D18: 60877.05 | E18: 58039.99 | F18: 55100.81 | G18: 91076.61 | H18: 116597.19 | I18: 97506.39 | J18: 95097.3 | K18: 92628.07
A19: Change in Inventory | B19: 4538.13 | C19: -99.31 | D19: 96.71 | E19: 565.24 | F19: -1516.77 | G19: 7597.87 | H19: 3358.89 | I19: -4409.35 | J19: 96.65 | K19: -989.62
A20: Power and Fuel | B20: 5220.83 | C20: 4440.43 | D20: 5316.56 | E20: 5319.92 | F20: 5708.42 | G20: 8028.29 | H20: 9526.91 | I20: 16612.61 | J20: 13124.85 | K20: 14333.15
A21: Other Mfr. Exp | B21: 15799.14 | C21: 16955.79 | D21: 20734.28 | E21: 21232.69 | F21: 20744.93 | G21: 28834.06 | H21: 33144.83 | I21: 40116.91 | J21: 38700.5 | K21: 37485.96
A22: Employee Cost | B22: 17252.22 | C22: 17077.51 | D22: 18758.87 | E22: 18533.58 | F22: 19908.81 | G22: 23264.1 | H22: 22419.32 | I22: 24509.58 | J22: 24888.99 | K22: 25998.98
A23: Selling and admin | B23: 13772.32 | C23: 14423.87 | D23: 16917.14 | E23: 15599.07 | F23: 17509.77 | G23: 27445.67 | H23: 25519.92 | I23: 14453.57 | J23: 12137.26 | K23: 13348.99
A24: Other Expenses | B24: 7806.38 | C24: 2681.96 | D24: 5843.58 | E24: 4193.58 | F24: 5483.63 | G24: 9418.36 | H24: 7203.25 | I24: 9314.45 | J24: 9391.81 | K24: 13002.73
A25: Other Income | B25: -3789.11 | C25: 10898.41 | D25: 1524.31 | E25: -2883.63 | F25: 179.78 | G25: 1299.99 | H25: 1568.86 | I25: -6005.23 | J25: 876.7 | K25: 737.82
A26: Depreciation | B26: 5672.88 | C26: 5741.7 | D26: 7341.83 | E26: 8440.73 | F26: 9233.64 | G26: 9100.87 | H26: 9335.2 | I26: 9882.16 | J26: 10421.33 | K26: 11954.51
A27: Interest | B27: 5072.2 | C27: 5454.74 | D27: 7660.1 | E27: 7533.46 | F27: 7606.71 | G27: 5462.2 | H27: 6298.7 | I27: 7507.57 | J27: 7340.95 | K27: 7167.06
... A31: Dividend Amount | B31: 970.24 | C31: 1144.95 | D31: 1488.42 | E31: 1144.95 | F31: 2994.02 | G31: 6228.17 | H31: 4396.46 | I31: 4490.78 | J31: 4490.78 | K31: 4989.76
A40: Quarters
A41: Report Date | B41: 45291 | C41: 45382 | D41: 45473 | E41: 45565 | F41: 45657 | G41: 45747 | H41: 45838 | I41: 45930 | J41: 46022 | K41: 46112
A42: Sales | B42: 55311.88 | C42: 58687.31 | D42: 54771.39 | E42: 53904.71 | F42: 53648.3 | G42: 56218.11 | H42: 53178.12 | I42: 58689.29 | J42: 57002.4 | K42: 63270.13
A43: Expenses | B43: 49048.31 | C43: 52086.68 | D43: 48076.92 | E43: 47788.92 | F43: 47744.81 | G43: 49658.89 | H43: 45750.58 | I43: 49792.75 | J43: 48802.7 | K43: 53441.47
A44: Other Income | B44: -32.84 | C44: -381.56 | D44: -5.51 | E44: 616.68 | F44: 141.82 | G44: 149.19 | H44: 236.27 | I44: -6.11 | J44: 465.17 | K44: 42.49
A45: Depreciation | B45: 2422.04 | C45: 2567.95 | D45: 2535.43 | E45: 2596.74 | F45: 2569.19 | G45: 2719.97 | H45: 2744.3 | I45: 2893 | J45: 3048.81 | K45: 3268.4
A46: Interest | B46: 1880.78 | C46: 1842.25 | D46: 1776.71 | E46: 1971.4 | F46: 1804.09 | G46: 1788.75 | H46: 1852.43 | I46: 1774.96 | J46: 1747.29 | K46: 1792.38
A47: Profit before tax | B47: 1927.91 | C47: 1808.87 | D47: 2376.82 | E47: 2164.33 | F47: 1672.03 | G47: 2199.69 | H47: 3067.08 | I47: 4222.47 | J47: 3868.77 | K47: 4810.37
A48: Tax | B48: 1405.77 | C48: 1254.31 | D48: 1458.25 | E48: 1405.49 | F48: 1376.54 | G48: 998.81 | H48: 1059.72 | I48: 1039.38 | J48: 1138.4 | K48: 1845.37
A49: Net profit | B49: 513.37 | C49: 611.48 | D49: 959.61 | E49: 833.45 | F49: 326.64 | G49: 1300.81 | H49: 2077.68 | I49: 3101.75 | J49: 2688.7 | K49: 2925.74
A50: Operating Profit | B50: 6263.57 | C50: 6600.63 | D50: 6694.47 | E50: 6115.79 | F50: 5903.49 | G50: 6559.22 | H50: 7427.54 | I50: 8896.54 | J50: 8199.7 | K50: 9828.66
A55: BALANCE SHEET
A56: Report Date | B56: 42825 | C56: 43190 | D56: 43555 | E56: 43921 | F56: 44286 | G56: 44651 | H56: 45016 | I56: 45382 | J56: 45747 | K56: 46112
A57: Equity Share Capital | B57: 970.24 | C57: 1144.95 | D57: 1144.94 | E57: 1144.95 | F57: 1197.61 | G57: 1221.21 | H57: 1221.24 | I57: 1247.44 | J57: 1247.44 | K57: 1247.44
A58: Reserves | B58: 36849.08 | C58: 59725.67 | D58: 67780.14 | E58: 72431.35 | F58: 73041.16 | G58: 113221.83 | H58: 101860.86 | I58: 90788.32 | J58: 89922.19 | K58: 100920.21
A59: Borrowings | B59: 83014.49 | C59: 92147.05 | D59: 100816.22 | E59: 116328.2 | F59: 88501.41 | G59: 75561.35 | H59: 84893.05 | I59: 87082.12 | J59: 94801.05 | K59: 92381.68
A60: Other Liabilities | B60: 51613.56 | C60: 55704.47 | D60: 63032.14 | E60: 59244.62 | F60: 81169.01 | G60: 92417.28 | H60: 97420.63 | I60: 90194.54 | J60: 89487.9 | K60: 101965.29
A61: Total | B61: 172447.37 | C61: 208722.14 | D61: 232773.44 | E61: 249149.12 | F61: 243909.19 | G61: 282421.67 | H61: 285395.78 | I61: 269312.42 | J61: 275458.58 | K61: 296514.62
A62: Net Block | B62: 92006.55 | C62: 96104.89 | D62: 124441.91 | E62: 134550.66 | F62: 135775.18 | G62: 133287.83 | H62: 146621.46 | I62: 148814.38 | J62: 150914.06 | K62: 179908.13
A63: Capital Work in Progress | B63: 15784.13 | C63: 16614.41 | D63: 18641.21 | E63: 19496.83 | F63: 19007.4 | G63: 22045.55 | H63: 31213.02 | I63: 34355.53 | J63: 41622.35 | K63: 28496.71
A64: Investments | B64: 12457.12 | C64: 17899.47 | D64: 5738.17 | E64: 6285.18 | F64: 10681.93 | G64: 13139.85 | H64: 8410.31 | I64: 6257.57 | J64: 6194.11 | K64: 7088.85
A65: Other Assets | B65: 52199.57 | C65: 78103.37 | D65: 83952.15 | E65: 88816.45 | F65: 78444.68 | G65: 113948.44 | H65: 99150.99 | I65: 79884.94 | J65: 76728.06 | K65: 81020.93
A66: Total | B66: 172447.37 | C66: 208722.14 | D66: 232773.44 | E66: 249149.12 | F66: 243909.19 | G66: 282421.67 | H66: 285395.78 | I66: 269312.42 | J66: 275458.58 | K66: 296514.62
A67: Receivables | B67: 11586.82 | C67: 12415.52 | D67: 11811 | E67: 7884.91 | F67: 9539.84 | G67: 12246.43 | H67: 8257.24 | I67: 6263.53 | J67: 5260.06 | K67: 4916.89
... A70: No. of Equity Shares | B70: 970436562 | C70: 1203340563 | D70: 1203331928 | E70: 1203332459 | F70: 1203334622 | G70: 1221566453 | H70: 12212353070 | I70: 12474347611 | J70: 12477659071 | K70: 12477659071
A71: New Bonus Shares
A72: Face value | B72: 10 | C72: 10 | D72: 10 | E72: 10 | F72: 10 | G72: 10 | H72: 1 | I72: 1 | J72: 1 | K72: 1
A80: CASH FLOW:
A81: Report Date | B81: 42825 | C81: 43190 | D81: 43555 | E81: 43921 | F81: 44286 | G81: 44651 | H81: 45016 | I81: 45382 | J81: 45747 | K81: 46112
A82: Cash from Operating Activity | B82: 10824.36 | C82: 8023.39 | D82: 25335.95 | E82: 20168.72 | F82: 44326.68 | G82: 44380.99 | H82: 21683.08 | I82: 20300.67 | J82: 23137.58 | K82: 35064.46
A83: Cash from Investing Activity | B83: -9489.65 | C83: -11730.31 | D83: -29176.45 | E83: -14012.06 | F83: -9437.27 | G83: -10905.02 | H83: -18179.45 | I83: -14252.74 | J83: -13611.02 | K83: -14397.35
A84: Cash from Financing Activity | B84: -2579.36 | C84: 6639.94 | D84: -672.7 | E84: -1694.62 | F84: -37089.67 | G84: -23401.09 | H84: -6980.69 | I84: -11096.99 | J84: -7002.44 | K84: -21387.12
A85: Net Cash Flow | B85: -1244.65 | C85: 2933.02 | D85: -4513.2 | E85: 4462.04 | F85: -2200.26 | G85: 10074.88 | H85: -3477.06 | I85: -5049.06 | J85: 2524.12 | K85: -720.01
A90: PRICE: | B90: 45.99 | C90: 57.11 | D90: 52.1 | E90: 26.96 | F90: 81.19 | G90: 130.72 | H90: 104.5 | I90: 155.85 | J90: 154.24 | K90: 191.86
A92: DERIVED:
A93: Adjusted Equity Shares in Cr | B93: 1126.62 | C93: 1126.48 | D93: 1126.49 | E93: 1126.49 | F93: 1196.59 | G93: 1221.3 | H93: 1222.15 | I93: 1248.35 | J93: 1248.35 | K93: 1248.35

Sheet Cash Flow 
B1: 44621 | C1: 44986 | D1: 45352 | E1: 45717 | F1: 46082
A2: Cash from Operating Activity - | B2: 44381 | C2: 21683 | D2: 20301 | E2: 23138 | F2: 35064
A3: Profit from operations | B3: 65900 | C3: 30908 | D3: 22237 | E3: 23929 | F3: 34219
A4: Receivables | B4: 0 | C4: 0 | D4: 0 | E4: 0 | F4: 0
A5: Inventory | B5: -16917 | C5: -4031 | D5: 5566 | E5: 4776 | F5: 1290
A6: Payables | B6: 0 | C6: 0 | D6: 0 | E6: 0 | F6: 0
A7: Other WC items | B7: 7299 | C7: 325 | D7: -2182 | E7: -2569 | F7: 4152
A8: Working capital changes | B8: -9618 | C8: -3706 | D8: 3384 | E8: 2207 | F8: 5442
A9: Direct taxes | B9: -11902 | C9: -5519 | D9: -5320 | E9: -2998 | F9: -4597
A10: Cash from Investing Activity - | B10: -10905 | C10: -18179 | D10: -14253 | E10: -13611 | F10: -14397
A11: Fixed assets purchased | B11: -10522 | C11: -14142 | D11: -18207 | E11: -15671 | F11: -14559
A12: Fixed assets sold | B12: 569 | C12: 328 | D12: 475 | E12: 1264 | F12: 1401
A13: Investments purchased | B13: -1153 | C13: -326 | D13: -4 | E13: -393 | F13: -553
... A31: CFO/OP | B31: 0.89 | C31: 0.84 | D31: 1.15 | E31: 1.03 | F31: 1.15
